Workbook

Sheet 개요
A1: Wellbian KOL KPI — 2026-09-28 실측
A2: KOL 라운드(노드 판매) 후보 선별용 · 수집: X·TG·YT 공개 페이지 직접 조회 · TwitterScore = twitterscore.io 공개값
A4: 탭 구성
A5: KOL 통합 | B5: KOL 1명 = 1행. 지역·링크·대표 채널 KPI·퍼포먼스·TwitterScore를 한 줄에 (KOL Asset 시트 형식)
A6: 글로벌 X / YT / TG | B6: 채널별 24시간 · 7일 · 30일 퍼포먼스 (게시 수 · 평균 조회 · ER · 평균 반응 · 도달률)
A7: 한국 TG / YT / X | B7: 동일 기준. 한국은 TG 중심 (TG에는 좋아요 수치가 없어 도달률 = 조회÷구독자로 반응을 봄)
A8: TwitterScore | B8: 56개 X 계정 영향력 점수 · 스마트 팔로워 · 30일 퍼포먼스 등급 대조
A9: KOL Rounds 선정 | B9: 선정 규칙 → 1차 / 예비 / 런칭 홍보용 / 보류, KOL별 선정 이유
A11: 퍼포먼스 등급 [제안 기준]
A12: 등급 | B12: X (게시물당 평균 반응) | C12: TG (30일 중앙 조회) | D12: YT 롱폼 (30일 중앙 조회)
A13: P1 | B13: 400+ | C13: 3,000+ | D13: 10,000+
A14: P2 | B14: 150–399 | C14: 1,500–2,999 | D14: 3,000–9,999
A15: P3 | B15: 50–149 | C15: 500–1,499 | D15: 1,000–2,999
A16: P4 | B16: 50 미만 | C16: 500 미만 | D16: 1,000 미만
A17: 비활동 | B17: 30일 3건 미만 | C17: 30일 3건 미만 | D17: 30일 롱폼 0개
A19: KPI 정의
A20: 평균 조회 | B20: 기간 내 본인 게시물 조회수 평균 (리포스트·고정글 제외)
A21: ER | B21: (좋아요 + 답글 + 리포스트) ÷ 조회 — X만 측정 가능
A22: 평균 반응 | B22: 게시물 1건이 만드는 반응 수 = 평균 조회 × ER
A23: 도달률 | B23: TG·YT: 30일 중앙 조회 ÷ 구독자 / X: 30일 평균 조회 ÷ 팔로워
A24: 추세 | B24: 7일 평균 조회 ÷ 30일 평균 조회 − 1 (+면 최근 상승)
A25: TwitterScore | B25: S 200+ · A 100–199 · B 40–99 · C 15–39 · D 15 미만. 스마트 팔로워 = 영향력 계정 팔로워 수
A27: 현황 (KOL 단위, 대표 채널 기준)
A28: 지역 | B28: P1 | C28: P2 | D28: P3 | E28: P4 | F28: 비활동·없음 | G28: 합계
A29: 한국 | B29: 3 | C29: 11 | D29: 21 | E29: 24 | F29: 22 | G29: 81
A30: 글로벌 | B30: 8 | C30: 12 | D30: 14 | E30: 11 | F30: 9 | G30: 54
A32: 주의
A33: ⚠️ 게시량이 많은 계정은 30일을 다 불러오지 못해 일부 기간만 집계 (각 탭 메모에 '○/○ 이후만 수집' 표기)
A34: ⚠️ 병합·이동 [추정]: CoinFluencer #6+#47 · 나백이 #19+#39 · X @coinboy717 → 코인소년 · @AlphaSchool77 → 알파스쿨
A35: ⚠️ 적합성(DePIN·노드·XRP 홍보 이력, 스캠 홍보 이력)은 미측정 — 접촉 전 확인
A36: ⚠️ 제안 직전 수치 재측정 필요 (8/25 원본 시트 팔로워는 TG+YT 합산값이 섞여 있어 이 시트는 실측값만 사용)

Sheet KOL 통합
A1: KOL 통합 — 135명 (한국 81 · 글로벌 54)
A2: ■ KOL 1명 = 1행. 대표 채널 = 퍼포먼스가 가장 높은 채널이며, 팔로워·게시·조회는 대표 채널의 9/28 실측값
A3: ■ 퍼포먼스 등급 [제안 기준] — X: 게시물당 평균 반응(평균 조회×ER) P1 400+ · P2 150+ · P3 50+ · P4 50 미만 / TG: 30일 중앙 조회 P1 3,000+ · P2 1,500+ · P3 500+ / YT 롱폼: 30일 중앙 조회 P1 10,000+ · P2 3,000+ · P3 1,000+ / 비활동: 30일 게시 X·TG 3건 미만, YT 롱폼 0개
A4: ■ 게시물당 조회: X = 30일 평균 조회, TG·YT = 30일 중앙 조회 · 도달률 = 게시물당 조회 ÷ 팔로워(구독자) · ER은 X 계정 기준
A5: ■ 재단·KOL 제안 전에는 해당 채널 수치를 다시 확인할 것
F7: 퍼포먼스 · 30일 (대표 채널) | L7: TwitterScore | O7: 링크
A8: 지역 | B8: 카테고리 | C8: 이름/핸들 | D8: 대표 채널 | E8: 활동 채널 | F8: 퍼포먼스 | G8: 팔로워/구독 | H8: 30일 게시 | I8: 게시물당 조회 | J8: ER (X) | K8: 도달률 | L8: Twitter Score | M8: TS 등급 | N8: 스마트 팔로워 | O8: X 링크 | P8: TG 링크 | Q8: YT 링크 | R8: 검증 | S8: 검증일 | T8: 비고 | U8: 출처 | V8: KOL ID | W8: 대표 채널 ID | X8: 계정 연결 | Y8: 측정일 | Z8: 후속 검토
A9: KR | C9: 코인하는 해달 | D9: Telegram | E9: TG | F9: P1 | G9: 30100 | H9: 133 | I9: 5000 | K9: 0.16611296 | P9: https://t.me/seaotterbtc | R9: ✅ 실측 | S9: 2026-09-28 | T9: 한국 1위 | U9: W1 검증 KOL (8/25 원본) → 9/28 재측정 | V9: WB-K001 | W9: WB-C099 | X9: 기존 목록 연결 | Y9: 46293 | Z9: 노드 구매·적합성·과거 판매 실적 미확인
A10: KR | C10: CoinFluencer | D10: Telegram | E10: X·TG·YT | F10: P1 | G10: 6630 | H10: 4 | I10: 3290 | K10: 0.49622926 | L10: 2 | M10: D | N10: 6 | O10: https://x.com/TheP2E_NFT | P10: https://t.me/hjwnews | Q10: https://www.youtube.com/@CoinFluencer | R10: ✅ 실측 | S10: 2026-09-28 | T10: 동일 브랜드 병합 [추정] · X 시트 100,000 → 실제 7,219 · 저빈도 (마지막 9/17) | U10: W1 검증 KOL (8/25 원본) → 9/28 재측정 | V10: WB-K002 | W10: WB-C098 | X10: 연결 확인 필요 | Y10: 46293 | Z10: 노드 구매·적합성·과거 판매 실적 미확인
A11: KR | C11: 취미생활방 | D11: Telegram | E11: TG | F11: P1 | G11: 49700 | H11: 431 | I11: 3010 | K11: 0.06056338 | P11: https://t.me/enjoymyhobby | R11: ✅ 실측 | S11: 2026-09-28 | T11: 하루 14건 → 고정 필요 | U11: W1 검증 KOL (8/25 원본) → 9/28 재측정 | V11: WB-K003 | W11: WB-C100 | X11: 기존 목록 연결 | Y11: 46293 | Z11: 노드 구매·적합성·과거 판매 실적 미확인
A12: KR | C12: 매실남 | D12: YouTube | E12: YT | F12: P2 | G12: 10200 | H12: 3 | I12: 6200 | K12: 0.60784314 | Q12: https://www.youtube.com/@pluman | R12: ✅ 실측 | S12: 2026-09-28 | U12: W1 검증 KOL (8/25 원본) → 9/28 재측정 | V12: WB-K004 | W12: WB-C165 | X12: 기존 목록 연결 | Y12: 46293 | Z12: 노드 구매·적합성·과거 판매 실적 미확인
A13: KR | C13: 코백남 | D13: YouTube | E13: TG·YT | F13: P2 | G13: 57900 | H13: 1 | I13: 4300 | K13: 0.074265976 | P13: https://t.me/cobacknamannounce | Q13: https://www.youtube.com/@cobacknam | R13: ✅ 실측 | S13: 2026-09-28 | T13: 시트 팔로워는 TG+YT 합산 · TG 채널 병행 | U13: W1 검증 KOL (8/25 원본) → 9/28 재측정 | V13: WB-K005 | W13: WB-C166 | X13: 기존 목록 연결 | Y13: 46293 | Z13: 노드 구매·적합성·과거 판매 실적 미확인
A14: KR | C14: 졸업준비위원회 | D14: Telegram | E14: TG | F14: P2 | G14: 23000 | H14: 157 | I14: 2830 | K14: 0.12304348 | P14: https://t.me/officialunivercityofcrypto | R14: ✅ 실측 | S14: 2026-09-28 | U14: W1 검증 KOL (8/25 원본) → 9/28 재측정 | V14: WB-K006 | W14: WB-C105 | X14: 기존 목록 연결 | Y14: 46293 | Z14: 노드 구매·적합성·과거 판매 실적 미확인
A15: KR | C15: Crypto Judy | D15: Telegram | E15: TG | F15: P2 | G15: 17400 | H15: 839 | I15: 2210 | K15: 0.12701149 | P15: https://t.me/lovejudylee | R15: ✅ 실측 | S15: 2026-09-28 | T15: 하루 28건+ → 공지 묻힘 위험 · 30일 일부만 수집 | U15: W1 검증 KOL (8/25 원본) → 9/28 재측정 | V15: WB-K007 | W15: WB-C104 | X15: 기존 목록 연결 | Y15: 46293 | Z15: 노드 구매·적합성·과거 판매 실적 미확인
A16: KR | C16: 라오니 | D16: Telegram | E16: TG | F16: P2 | G16: 14900 | H16: 329 | I16: 2200 | K16: 0.14765101 | P16: https://t.me/Raoni1 | R16: ✅ 실측 | S16: 2026-09-28 | U16: W1 검증 KOL (8/25 원본) → 9/28 재측정 | V16: WB-K008 | W16: WB-C103 | X16: 기존 목록 연결 | Y16: 46293 | Z16: 노드 구매·적합성·과거 판매 실적 미확인
A17: KR | C17: 신기돈 | D17: Telegram | E17: TG | F17: P2 | G17: 22900 | H17: 137 | I17: 1840 | K17: 0.080349345 | P17: https://t.me/tlsrltnf | R17: ✅ 실측 | S17: 2026-09-28 | U17: W1 검증 KOL (8/25 원본) → 9/28 재측정 | V17: WB-K009 | W17: WB-C107 | X17: 기존 목록 연결 | Y17: 46293 | Z17: 노드 구매·적합성·과거 판매 실적 미확인
A18: KR | C18: 크립토마카세 | D18: Telegram | E18: TG | F18: P2 | G18: 11000 | H18: 25 | I18: 1830 | K18: 0.16636364 | P18: https://t.me/cryptomacase | R18: ✅ 실측 | S18: 2026-09-28 | T18: 저빈도 · 고효율 | U18: W1 검증 KOL (8/25 원본) → 9/28 재측정 | V18: WB-K010 | W18: WB-C102 | X18: 기존 목록 연결 | Y18: 46293 | Z18: 노드 구매·적합성·과거 판매 실적 미확인
A19: KR | C19: jobless | D19: Telegram | E19: TG | F19: P2 | G19: 6050 | H19: 6 | I19: 1750 | K19: 0.2892562 | P19: https://t.me/Jobless_investor | R19: ✅ 실측 | S19: 2026-09-28 | T19: 마지막 9/3 | U19: W1 검증 KOL (8/25 원본) → 9/28 재측정 | V19: WB-K011 | W19: WB-C101 | X19: 기존 목록 연결 | Y19: 46293 | Z19: 노드 구매·적합성·과거 판매 실적 미확인
A20: KR | C20: 마샬 | D20: Telegram | E20: TG | F20: P2 | G20: 21700 | H20: 154 | I20: 1730 | K20: 0.079723502 | P20: https://t.me/marshallog | R20: ✅ 실측 | S20: 2026-09-28 | U20: W1 검증 KOL (8/25 원본) → 9/28 재측정 | V20: WB-K012 | W20: WB-C108 | X20: 기존 목록 연결 | Y20: 46293 | Z20: 노드 구매·적합성·과거 판매 실적 미확인
A21: KR | C21: 잼민123 | D21: Telegram | E21: TG·YT | F21: P2 | G21: 26200 | H21: 430 | I21: 1690 | K21: 0.064503817 | P21: https://t.me/mujammin123 | Q21: https://www.youtube.com/@jammin2 | R21: ✅ 실측 | S21: 2026-09-28 | U21: W1 검증 KOL (8/25 원본) → 9/28 재측정 | V21: WB-K013 | W21: WB-C109 | X21: 기존 목록 연결 | Y21: 46293 | Z21: 노드 구매·적합성·과거 판매 실적 미확인
A22: KR | C22: 킬베로스 | D22: Telegram | E22: TG | F22: P2 | G22: 15100 | H22: 38 | I22: 1650 | K22: 0.10927152 | P22: https://t.me/killberosDAO | R22: ✅ 실측 | S22: 2026-09-28 | T22: 8/25 대비 하락 | U22: W1 검증 KOL (8/25 원본) → 9/28 재측정 | V22: WB-K014 | W22: WB-C106 | X22: 기존 목록 연결 | Y22: 46293 | Z22: 노드 구매·적합성·과거 판매 실적 미확인
A23: KR | C23: 나백이 | D23: YouTube | E23: X·TG·YT | F23: P3 | G23: 16700 | H23: 1 | I23: 2900 | J23: 0.0054 | K23: 0.17365269 | L23: 17 | M23: C | N23: 164 | O23: https://x.com/Naback222 | P23: https://t.me/ysytop2 | Q23: https://www.youtube.com/@naback222 | R23: ✅ 실측 | S23: 2026-09-28 | T23: 동일인 병합 [추정] | U23: W1 검증 KOL (8/25 원본) → 9/28 재측정 | V23: WB-K015 | W23: WB-C168 | X23: 연결 확인 필요 | Y23: 46293 | Z23: 노드 구매·적합성·과거 판매 실적 미확인
A24: KR | C24: 코인소년 | D24: YouTube | E24: X·TG·YT | F24: P3 | G24: 53200 | H24: 6 | I24: 2200 | J24: 0.0172 | K24: 0.041353383 | L24: 11 | M24: D | N24: 82 | O24: https://x.com/coinboy717 | P24: https://t.me/coinboys | Q24: https://www.youtube.com/@coinboys | R24: ✅ 실측 | S24: 2026-09-28 | T24: X @coinboy717 표시명 '코인소년' → 시트(#48)에서 이동 [추정] · TG 채널 병행 | U24: W1 검증 KOL (8/25 원본) → 9/28 재측정 | V24: WB-K016 | W24: WB-C169 | X24: 연결 확인 필요 | Y24: 46293 | Z24: 노드 구매·적합성·과거 판매 실적 미확인
A25: KR | C25: 요블이네 | D25: Telegram | E25: TG | F25: P3 | G25: 22700 | H25: 185 | I25: 1480 | K25: 0.065198238 | P25: https://t.me/yobeullyANN | R25: ✅ 실측 | S25: 2026-09-28 | U25: W1 검증 KOL (8/25 원본) → 9/28 재측정 | V25: WB-K017 | W25: WB-C126 | X25: 기존 목록 연결 | Y25: 46293 | Z25: 노드 구매·적합성·과거 판매 실적 미확인
A26: KR | C26: 알파스쿨 | D26: Telegram | E26: X·TG | F26: P3 | G26: 10800 | H26: 101 | I26: 1300 | J26: 0.0292 | K26: 0.12037037 | L26: 4 | M26: D | N26: 51 | O26: https://x.com/AlphaSchool77 | P26: https://t.me/AlphaSchool77 | R26: ✅ 실측 | S26: 2026-09-28 | T26: X @AlphaSchool77 → 시트(#51)에서 이동 [추정] · X는 WL 기브어웨이 위주 | U26: W1 검증 KOL (8/25 원본) → 9/28 재측정 | V26: WB-K018 | W26: WB-C114 | X26: 연결 확인 필요 | Y26: 46293 | Z26: 노드 구매·적합성·과거 판매 실적 미확인
A27: KR | C27: T.A Crypto | D27: YouTube | E27: TG·YT | F27: P3 | G27: 7410 | H27: 1 | I27: 1200 | K27: 0.16194332 | P27: https://t.me/yul_papa | Q27: https://www.youtube.com/@TA_crypto | R27: ✅ 실측 | S27: 2026-09-28 | T27: TG 채널 병행 | U27: W1 검증 KOL (8/25 원본) → 9/28 재측정 | V27: WB-K019 | W27: WB-C170 | X27: 기존 목록 연결 | Y27: 46293 | Z27: 노드 구매·적합성·과거 판매 실적 미확인
A28: KR | C28: BMT | D28: Telegram | E28: TG | F28: P3 | G28: 13700 | H28: 84 | I28: 1200 | K28: 0.087591241 | P28: https://t.me/BMTube | R28: ✅ 실측 | S28: 2026-09-28 | U28: W1 검증 KOL (8/25 원본) → 9/28 재측정 | V28: WB-K020 | W28: WB-C120 | X28: 기존 목록 연결 | Y28: 46293 | Z28: 노드 구매·적합성·과거 판매 실적 미확인
A29: KR | C29: 개인적인 DYOR | D29: Telegram | E29: TG | F29: P3 | G29: 9730 | H29: 67 | I29: 976 | K29: 0.10030832 | P29: https://t.me/LEEHEESANGDYOR | R29: ✅ 실측 | S29: 2026-09-28 | U29: W1 검증 KOL (8/25 원본) → 9/28 재측정 | V29: WB-K021 | W29: WB-C119 | X29: 기존 목록 연결 | Y29: 46293 | Z29: 노드 구매·적합성·과거 판매 실적 미확인
A30: KR | C30: 바나나우유 일기장 | D30: Telegram | E30: TG | F30: P3 | G30: 8760 | H30: 10 | I30: 892 | K30: 0.10182648 | P30: https://t.me/Bananamilkrich | R30: ✅ 실측 | S30: 2026-09-28 | U30: W1 검증 KOL (8/25 원본) → 9/28 재측정 | V30: WB-K022 | W30: WB-C117 | X30: 기존 목록 연결 | Y30: 46293 | Z30: 노드 구매·적합성·과거 판매 실적 미확인
A31: KR | C31: Trader Hyun | D31: Telegram | E31: TG | F31: P3 | G31: 6530 | H31: 14 | I31: 880 | K31: 0.13476263 | P31: https://t.me/TraderHyun | R31: ✅ 실측 | S31: 2026-09-28 | U31: W1 검증 KOL (8/25 원본) → 9/28 재측정 | V31: WB-K023 | W31: WB-C112 | X31: 기존 목록 연결 | Y31: 46293 | Z31: 노드 구매·적합성·과거 판매 실적 미확인
A32: KR | C32: 에어드랍코리아 | D32: Telegram | E32: TG | F32: P3 | G32: 21900 | H32: 131 | I32: 844 | K32: 0.038538813 | P32: https://t.me/airdrop_kor | R32: ✅ 실측 | S32: 2026-09-28 | T32: 에어드랍 키워드 | U32: W1 검증 KOL (8/25 원본) → 9/28 재측정 | V32: WB-K024 | W32: WB-C130 | X32: 기존 목록 연결 | Y32: 46293 | Z32: 노드 구매·적합성·과거 판매 실적 미확인
A33: KR | C33: BQ 비큐 | D33: Telegram | E33: TG | F33: P3 | G33: 9600 | H33: 98 | I33: 821 | K33: 0.085520833 | P33: https://t.me/BQTelegram | R33: ✅ 실측 | S33: 2026-09-28 | U33: W1 검증 KOL (8/25 원본) → 9/28 재측정 | V33: WB-K025 | W33: WB-C121 | X33: 기존 목록 연결 | Y33: 46293 | Z33: 노드 구매·적합성·과거 판매 실적 미확인
A34: KR | C34: 젠티 | D34: Telegram | E34: TG | F34: P3 | G34: 14400 | H34: 94 | I34: 772 | K34: 0.053611111 | P34: https://t.me/Jenti_DeFi | R34: ✅ 실측 | S34: 2026-09-28 | U34: W1 검증 KOL (8/25 원본) → 9/28 재측정 | V34: WB-K026 | W34: WB-C128 | X34: 기존 목록 연결 | Y34: 46293 | Z34: 노드 구매·적합성·과거 판매 실적 미확인
A35: KR | C35: 크립토폴유 | D35: Telegram | E35: TG | F35: P3 | G35: 7620 | H35: 35 | I35: 766 | K35: 0.10052493 | P35: https://t.me/cryptoforu12 | R35: ✅ 실측 | S35: 2026-09-28 | U35: W1 검증 KOL (8/25 원본) → 9/28 재측정 | V35: WB-K027 | W35: WB-C118 | X35: 기존 목록 연결 | Y35: 46293 | Z35: 노드 구매·적합성·과거 판매 실적 미확인
A36: KR | C36: Road To Rome | D36: Telegram | E36: TG | F36: P3 | G36: 4840 | H36: 6 | I36: 718 | K36: 0.14834711 | P36: https://t.me/HeadingtoRome | R36: ✅ 실측 | S36: 2026-09-28 | U36: W1 검증 KOL (8/25 원본) → 9/28 재측정 | V36: WB-K028 | W36: WB-C111 | X36: 기존 목록 연결 | Y36: 46293 | Z36: 노드 구매·적합성·과거 판매 실적 미확인
A37: KR | C37: A라는 사람 | D37: Telegram | E37: TG | F37: P3 | G37: 3920 | H37: 18 | I37: 707 | K37: 0.18035714 | P37: https://t.me/aispersons | R37: ✅ 실측 | S37: 2026-09-28 | T37: 8/25 대비 하락 | U37: W1 검증 KOL (8/25 원본) → 9/28 재측정 | V37: WB-K029 | W37: WB-C110 | X37: 기존 목록 연결 | Y37: 46293 | Z37: 노드 구매·적합성·과거 판매 실적 미확인
A38: KR | C38: 꿀찾는 양말 | D38: Telegram | E38: TG | F38: P3 | G38: 11400 | H38: 460 | I38: 628 | K38: 0.055087719 | P38: https://t.me/Honeyofwhitesocks_2 | R38: ✅ 실측 | S38: 2026-09-28 | U38: W1 검증 KOL (8/25 원본) → 9/28 재측정 | V38: WB-K030 | W38: WB-C127 | X38: 기존 목록 연결 | Y38: 46293 | Z38: 노드 구매·적합성·과거 판매 실적 미확인
A39: KR | C39: 큐브 | D39: Telegram | E39: TG | F39: P3 | G39: 9320 | H39: 38 | I39: 624 | K39: 0.06695279 | P39: https://t.me/cubestudy1557 | R39: ✅ 실측 | S39: 2026-09-28 | U39: W1 검증 KOL (8/25 원본) → 9/28 재측정 | V39: WB-K031 | W39: WB-C124 | X39: 기존 목록 연결 | Y39: 46293 | Z39: 노드 구매·적합성·과거 판매 실적 미확인
A40: KR | C40: 코인맵핵 | D40: Telegram | E40: TG | F40: P3 | G40: 16700 | H40: 76 | I40: 617 | K40: 0.036946108 | P40: https://t.me/centurywhale | R40: ✅ 실측 | S40: 2026-09-28 | U40: W1 검증 KOL (8/25 원본) → 9/28 재측정 | V40: WB-K032 | W40: WB-C131 | X40: 기존 목록 연결 | Y40: 46293 | Z40: 노드 구매·적합성·과거 판매 실적 미확인
A41: KR | C41: 코인위키 | D41: Telegram | E41: TG | F41: P3 | G41: 5910 | H41: 82 | I41: 615 | K41: 0.10406091 | P41: https://t.me/CoinWiki_MMWW | R41: ✅ 실측 | S41: 2026-09-28 | U41: W1 검증 KOL (8/25 원본) → 9/28 재측정 | V41: WB-K033 | W41: WB-C115 | X41: 기존 목록 연결 | Y41: 46293 | Z41: 노드 구매·적합성·과거 판매 실적 미확인
A42: KR | C42: 21M 포밍 | D42: Telegram | E42: TG | F42: P3 | G42: 5540 | H42: 8 | I42: 567 | K42: 0.10234657 | P42: https://t.me/vc_21m | R42: ✅ 실측 | S42: 2026-09-28 | T42: 8/25 대비 하락 | U42: W1 검증 KOL (8/25 원본) → 9/28 재측정 | V42: WB-K034 | W42: WB-C116 | X42: 기존 목록 연결 | Y42: 46293 | Z42: 노드 구매·적합성·과거 판매 실적 미확인
A43: KR | C43: 크립토스쿨 다오 | D43: Telegram | E43: TG | F43: P3 | G43: 12600 | H43: 191 | I43: 528 | K43: 0.041904762 | P43: https://t.me/CRYPTOSCH00L | R43: ✅ 실측 | S43: 2026-09-28 | U43: W1 검증 KOL (8/25 원본) → 9/28 재측정 | V43: WB-K035 | W43: WB-C129 | X43: 기존 목록 연결 | Y43: 46293 | Z43: 노드 구매·적합성·과거 판매 실적 미확인
A44: KR | C44: CEN | D44: X | E44: X·YT | F44: P4 | G44: 14000 | H44: 3 | I44: 1961 | J44: 0.0129 | K44: 0.14007143 | L44: 6 | M44: D | N44: 68 | O44: https://x.com/CENTWT | Q44: https://www.youtube.com/@CEN_CRYPTO | R44: ✅ 실측 | S44: 2026-09-28 | T44: 마지막 9/7 | U44: W1 검증 KOL (8/25 원본) → 9/28 재측정 | V44: WB-K036 | W44: WB-C190 | X44: 기존 목록 연결 | Y44: 46293 | Z44: 노드 구매·적합성·과거 판매 실적 미확인
A45: KR | C45: 크립토메이지 | D45: YouTube | E45: X·YT | F45: P4 | G45: 8590 | H45: 3 | I45: 570 | J45: 0.0112 | K45: 0.066356228 | L45: 3 | M45: D | N45: 28 | O45: https://x.com/p2ecoin91 | Q45: https://www.youtube.com/@cryptocurrencymage | R45: ✅ 실측 | S45: 2026-09-28 | U45: W1 검증 KOL (8/25 원본) → 9/28 재측정 | V45: WB-K037 | W45: WB-C171 | X45: 기존 목록 연결 | Y45: 46293 | Z45: 노드 구매·적합성·과거 판매 실적 미확인
A46: KR | C46: 에어드랍 ATM | D46: YouTube | E46: YT | F46: P4 | G46: 10000 | H46: 1 | I46: 476 | K46: 0.0476 | Q46: https://www.youtube.com/@airdropatm | R46: ✅ 실측 | S46: 2026-09-28 | T46: 에어드랍 키워드 | U46: W1 검증 KOL (8/25 원본) → 9/28 재측정 | V46: WB-K038 | W46: WB-C172 | X46: 기존 목록 연결 | Y46: 46293 | Z46: 노드 구매·적합성·과거 판매 실적 미확인
A47: KR | C47: 아크 | D47: Telegram | E47: TG | F47: P4 | G47: 12000 | H47: 119 | I47: 448 | K47: 0.037333333 | P47: https://t.me/Board_the_Ark | R47: ✅ 실측 | S47: 2026-09-28 | U47: W1 검증 KOL (8/25 원본) → 9/28 재측정 | V47: WB-K039 | W47: WB-C144 | X47: 기존 목록 연결 | Y47: 46293 | Z47: 노드 구매·적합성·과거 판매 실적 미확인
A48: KR | C48: 두신의 NFT | D48: Telegram | E48: TG·YT | F48: P4 | G48: 5320 | H48: 48 | I48: 416 | K48: 0.078195489 | P48: https://t.me/doosin_nft | Q48: https://www.youtube.com/@doosinnft | R48: ✅ 실측 | S48: 2026-09-28 | T48: 시트의 X(@AlphaSchool77)는 알파스쿨 계정으로 보여 제외 · 평균은 바이럴 1건으로 부풀려짐 | U48: W1 검증 KOL (8/25 원본) → 9/28 재측정 | V48: WB-K040 | W48: WB-C135 | X48: 기존 목록 연결 | Y48: 46293 | Z48: 노드 구매·적합성·과거 판매 실적 미확인
A49: KR | C49: 최저시급 김으악 | D49: Telegram | E49: TG | F49: P4 | G49: 9960 | H49: 869 | I49: 340 | K49: 0.034136546 | P49: https://t.me/Ugh_HH | R49: ✅ 실측 | S49: 2026-09-28 | T49: 하루 29건+ → 공지 묻힘 위험 · 30일 일부만 수집 | U49: W1 검증 KOL (8/25 원본) → 9/28 재측정 | V49: WB-K041 | W49: WB-C145 | X49: 기존 목록 연결 | Y49: 46293 | Z49: 노드 구매·적합성·과거 판매 실적 미확인
A50: KR | C50: SignalQuant | D50: Telegram | E50: TG | F50: P4 | G50: 4690 | H50: 70 | I50: 318 | K50: 0.067803838 | P50: https://t.me/Signal_Quant | R50: ✅ 실측 | S50: 2026-09-28 | U50: W1 검증 KOL (8/25 원본) → 9/28 재측정 | V50: WB-K042 | W50: WB-C137 | X50: 기존 목록 연결 | Y50: 46293 | Z50: 노드 구매·적합성·과거 판매 실적 미확인
A51: KR | C51: Daniel Social Club | D51: Telegram | E51: TG | F51: P4 | G51: 4570 | H51: 3 | I51: 297 | K51: 0.064989059 | P51: https://t.me/danielsocialclub | R51: ✅ 실측 | S51: 2026-09-28 | T51: 마지막 9/3 | U51: W1 검증 KOL (8/25 원본) → 9/28 재측정 | V51: WB-K043 | W51: WB-C138 | X51: 기존 목록 연결 | Y51: 46293 | Z51: 노드 구매·적합성·과거 판매 실적 미확인
A52: KR | C52: 왕베이 | D52: Telegram | E52: TG·YT | F52: P4 | G52: 7210 | H52: 115 | I52: 287 | K52: 0.039805825 | P52: https://t.me/cryptowangbei | Q52: https://www.youtube.com/@Wangbei__ | R52: ✅ 실측 | S52: 2026-09-28 | U52: W1 검증 KOL (8/25 원본) → 9/28 재측정 | V52: WB-K044 | W52: WB-C141 | X52: 기존 목록 연결 | Y52: 46293 | Z52: 노드 구매·적합성·과거 판매 실적 미확인
A53: KR | C53: 돈독(열충) | D53: Telegram | E53: X·TG | F53: P4 | G53: 7100 | H53: 364 | I53: 275 | J53: 0.0288 | K53: 0.038732394 | L53: 3 | M53: D | O53: https://x.com/heedan123 | P53: https://t.me/yeolchoongNotice | R53: ✅ 실측 | S53: 2026-09-28 | U53: W1 검증 KOL (8/25 원본) → 9/28 재측정 | V53: WB-K045 | W53: WB-C143 | X53: 기존 목록 연결 | Y53: 46293 | Z53: 노드 구매·적합성·과거 판매 실적 미확인
A54: KR | C54: 희단이 | D54: Telegram | E54: TG | F54: P4 | G54: 8200 | H54: 37 | I54: 264 | K54: 0.032195122 | P54: https://t.me/heedan22 | R54: ✅ 실측 | S54: 2026-09-28 | U54: W1 검증 KOL (8/25 원본) → 9/28 재측정 | V54: WB-K046 | W54: WB-C147 | X54: 기존 목록 연결 | Y54: 46293 | Z54: 노드 구매·적합성·과거 판매 실적 미확인
A55: KR | C55: 춘식이 | D55: Telegram | E55: TG | F55: P4 | G55: 6080 | H55: 70 | I55: 257 | K55: 0.042269737 | P55: https://t.me/choonsik | R55: ✅ 실측 | S55: 2026-09-28 | U55: W1 검증 KOL (8/25 원본) → 9/28 재측정 | V55: WB-K047 | W55: WB-C140 | X55: 기존 목록 연결 | Y55: 46293 | Z55: 노드 구매·적합성·과거 판매 실적 미확인
A56: KR | C56: 부의길목에서 | D56: Telegram | E56: TG·YT | F56: P4 | G56: 7770 | H56: 366 | I56: 227 | K56: 0.029214929 | P56: https://t.me/stay_news | Q56: https://www.youtube.com/@CoinStay | R56: ✅ 실측 | S56: 2026-09-28 | T56: YT 404 | U56: W1 검증 KOL (8/25 원본) → 9/28 재측정 | V56: WB-K048 | W56: WB-C149 | X56: 기존 목록 연결 | Y56: 46293 | Z56: 노드 구매·적합성·과거 판매 실적 미확인
A57: KR | C57: 코인한나 | D57: Telegram | E57: TG | F57: P4 | G57: 6680 | H57: 240 | I57: 212 | K57: 0.031736527 | P57: https://t.me/coinhanna_honeybag | R57: ✅ 실측 | S57: 2026-09-28 | U57: W1 검증 KOL (8/25 원본) → 9/28 재측정 | V57: WB-K049 | W57: WB-C148 | X57: 기존 목록 연결 | Y57: 46293 | Z57: 노드 구매·적합성·과거 판매 실적 미확인
A58: KR | C58: 옹살랜드 | D58: Telegram | E58: TG | F58: P4 | G58: 6280 | H58: 4 | I58: 209 | K58: 0.033280255 | P58: https://t.me/OngsalYee | R58: ✅ 실측 | S58: 2026-09-28 | U58: W1 검증 KOL (8/25 원본) → 9/28 재측정 | V58: WB-K050 | W58: WB-C146 | X58: 기존 목록 연결 | Y58: 46293 | Z58: 노드 구매·적합성·과거 판매 실적 미확인
A59: KR | C59: 크립토 부엉이 | D59: Telegram | E59: TG | F59: P4 | G59: 7810 | H59: 115 | I59: 195 | K59: 0.02496799 | P59: https://t.me/CryptoOwlNotice | R59: ✅ 실측 | S59: 2026-09-28 | U59: W1 검증 KOL (8/25 원본) → 9/28 재측정 | V59: WB-K051 | W59: WB-C150 | X59: 기존 목록 연결 | Y59: 46293 | Z59: 노드 구매·적합성·과거 판매 실적 미확인
A60: KR | C60: 안성국밥 (구 국밥집) | D60: Telegram | E60: TG | F60: P4 | G60: 4140 | H60: 146 | I60: 181 | K60: 0.043719807 | P60: https://t.me/coinkookbob | R60: ✅ 실측 | S60: 2026-09-28 | T60: 에어드랍 키워드 · 채널명 변경 | U60: W1 검증 KOL (8/25 원본) → 9/28 재측정 | V60: WB-K052 | W60: WB-C139 | X60: 기존 목록 연결 | Y60: 46293 | Z60: 노드 구매·적합성·과거 판매 실적 미확인
A61: KR | C61: 투자하는 30대 직장인정보방 | D61: Telegram | E61: X·TG | F61: P4 | G61: 1300 | H61: 7 | I61: 166 | J61: 0.0123 | K61: 0.12769231 | L61: 18 | M61: C | N61: 149 | O61: https://x.com/cryptoyobeul | P61: https://t.me/naverblog30 | R61: ✅ 실측 | S61: 2026-09-28 | T61: 평균 왜곡 | U61: W1 검증 KOL (8/25 원본) → 9/28 재측정 | V61: WB-K053 | W61: WB-C133 | X61: 기존 목록 연결 | Y61: 46293 | Z61: 노드 구매·적합성·과거 판매 실적 미확인
A62: KR | C62: 불불 | D62: Telegram | E62: TG | F62: P4 | G62: 1900 | H62: 3 | I62: 132 | K62: 0.069473684 | P62: https://t.me/bulbul2cryptoDAO | R62: ✅ 실측 | S62: 2026-09-28 | U62: W1 검증 KOL (8/25 원본) → 9/28 재측정 | V62: WB-K054 | W62: WB-C136 | X62: 기존 목록 연결 | Y62: 46293 | Z62: 노드 구매·적합성·과거 판매 실적 미확인
A63: KR | C63: JackpotDAO | D63: Telegram | E63: TG | F63: P4 | G63: 3380 | H63: 112 | I63: 131 | K63: 0.038757396 | P63: https://t.me/jackpot777DAO | R63: ✅ 실측 | S63: 2026-09-28 | U63: W1 검증 KOL (8/25 원본) → 9/28 재측정 | V63: WB-K055 | W63: WB-C142 | X63: 기존 목록 연결 | Y63: 46293 | Z63: 노드 구매·적합성·과거 판매 실적 미확인
A64: KR | C64: 생계형 에어드랍 | D64: Telegram | E64: TG | F64: P4 | G64: 1430 | H64: 13 | I64: 116 | K64: 0.081118881 | P64: https://t.me/sangp_airdrop | R64: ✅ 실측 | S64: 2026-09-28 | T64: 에어드랍 키워드 | U64: W1 검증 KOL (8/25 원본) → 9/28 재측정 | V64: WB-K056 | W64: WB-C134 | X64: 기존 목록 연결 | Y64: 46293 | Z64: 노드 구매·적합성·과거 판매 실적 미확인
A65: KR | C65: 크립토 원정대 | D65: Telegram | E65: X·TG | F65: P4 | G65: 7120 | H65: 77 | I65: 103 | K65: 0.014466292 | L65: 1 | M65: D | O65: https://x.com/0xsangp | P65: https://t.me/legoleecm777 | R65: ✅ 실측 | S65: 2026-09-28 | U65: W1 검증 KOL (8/25 원본) → 9/28 재측정 | V65: WB-K057 | W65: WB-C151 | X65: 기존 목록 연결 | Y65: 46293 | Z65: 노드 구매·적합성·과거 판매 실적 미확인
A66: KR | C66: KryptoKlang | D66: X | E66: X·TG | F66: P4 | G66: 2879 | H66: 11 | I66: 89 | J66: 0.0224 | K66: 0.030913512 | L66: 2 | M66: D | N66: 6 | O66: https://x.com/Stay1104 | P66: https://t.me/KryptoKlang | R66: ✅ 실측 | S66: 2026-09-28 | U66: W1 검증 KOL (8/25 원본) → 9/28 재측정 | V66: WB-K058 | W66: WB-C195 | X66: 기존 목록 연결 | Y66: 46293 | Z66: 노드 구매·적합성·과거 판매 실적 미확인
A67: KR | C67: 농사꾼 돈벌레 | D67: Telegram | E67: TG | F67: P4 | G67: 92 | H67: 105 | I67: 21 | K67: 0.22826087 | P67: https://t.me/donbug8282 | R67: ✅ 실측 | S67: 2026-09-28 | T67: 구독자 92 | U67: W1 검증 KOL (8/25 원본) → 9/28 재측정 | V67: WB-K059 | W67: WB-C132 | X67: 기존 목록 연결 | Y67: 46293 | Z67: 노드 구매·적합성·과거 판매 실적 미확인
A68: KR | C68: ORCA ALPHA | D68: Telegram | E68: TG | F68: 비활동 | G68: 1500 | H68: 2 | I68: 97 | K68: 0.064666667 | P68: https://t.me/orcaalpha | R68: ✅ 실측 | S68: 2026-09-28 | T68: 30일 2건 | U68: W1 검증 KOL (8/25 원본) → 9/28 재측정 | V68: WB-K060 | W68: WB-C154 | X68: 기존 목록 연결 | Y68: 46293 | Z68: 노드 구매·적합성·과거 판매 실적 미확인
A69: KR | C69: 디젠걸 | D69: Telegram | E69: TG | F69: 비활동 | G69: 891 | H69: 2 | I69: 58 | K69: 0.065095398 | P69: https://t.me/KDegengirl | R69: ✅ 실측 | S69: 2026-09-28 | T69: 30일 2건 | U69: W1 검증 KOL (8/25 원본) → 9/28 재측정 | V69: WB-K061 | W69: WB-C153 | X69: 기존 목록 연결 | Y69: 46293 | Z69: 노드 구매·적합성·과거 판매 실적 미확인
A70: KR | C70: 곰곰히 매매 | D70: Telegram | E70: TG | F70: 비활동 | G70: 33 | H70: 2 | I70: 29 | K70: 0.87878788 | P70: https://t.me/Kindibearbtc | R70: ✅ 실측 | S70: 2026-09-28 | T70: 30일 2건 | U70: W1 검증 KOL (8/25 원본) → 9/28 재측정 | V70: WB-K062 | W70: WB-C152 | X70: 기존 목록 연결 | Y70: 46293 | Z70: 노드 구매·적합성·과거 판매 실적 미확인
A71: KR | C71: 코마카세 | D71: Telegram | E71: TG | F71: 비활동 | G71: 486 | P71: https://t.me/COMADAO | R71: ✅ 실측 | S71: 2026-09-28 | T71: 에어드랍 키워드 · 비활성 | U71: W1 검증 KOL (8/25 원본) → 9/28 재측정 | V71: WB-K063 | W71: WB-C155 | X71: 기존 목록 연결 | Y71: 46293 | Z71: 노드 구매·적합성·과거 판매 실적 미확인
A72: KR | C72: 1분 코인 | D72: YouTube | E72: YT | F72: 비활동 | G72: 34200 | Q72: https://www.youtube.com/channel/UCKsMT8_jAvNWtOOS6Lo23EQ | R72: ✅ 실측 | S72: 2026-09-28 | T72: 롱폼 중단 | U72: W1 검증 KOL (8/25 원본) → 9/28 재측정 | V72: WB-K064 | W72: WB-C181 | X72: 기존 목록 연결 | Y72: 46293 | Z72: 노드 구매·적합성·과거 판매 실적 미확인
A73: KR | C73: 크립토 청춘 | D73: YouTube | E73: YT | F73: 비활동 | G73: 17700 | Q73: https://www.youtube.com/@CheongChun | R73: ✅ 실측 | S73: 2026-09-28 | T73: 롱폼 중단 | U73: W1 검증 KOL (8/25 원본) → 9/28 재측정 | V73: WB-K065 | W73: WB-C182 | X73: 기존 목록 연결 | Y73: 46293 | Z73: 노드 구매·적합성·과거 판매 실적 미확인
A74: KR | C74: 이도진 | D74: X | E74: X·YT | F74: 비활동 | G74: 12 | O74: https://x.com/Xrtrashbin | Q74: https://www.youtube.com/@leedogin | R74: ✅ 실측 | S74: 2026-09-28 | T74: X 계정 불일치 (팔로워 12) · 보류 · 계정 불일치 (시트 12,800) · 30일 미수집 → 7일 기준 | U74: W1 검증 KOL (8/25 원본) → 9/28 재측정 | V74: WB-K066 | W74: WB-C200 | X74: 연결 확인 필요 | Y74: 46293 | Z74: 노드 구매·적합성·과거 판매 실적 미확인
A75: KR | C75: Jerry Alpha | D75: YouTube | E75: YT | F75: 비활동 | G75: 11900 | Q75: https://www.youtube.com/@jerryalphanft | R75: ✅ 실측 | S75: 2026-09-28 | T75: 롱폼 중단 | U75: W1 검증 KOL (8/25 원본) → 9/28 재측정 | V75: WB-K067 | W75: WB-C179 | X75: 기존 목록 연결 | Y75: 46293 | Z75: 노드 구매·적합성·과거 판매 실적 미확인
A76: KR | C76: 로로 | D76: X | E76: X·YT | F76: 비활동 | G76: 2480 | L76: 2 | M76: D | O76: https://x.com/nftroro | Q76: https://www.youtube.com/@COINRORO | R76: ✅ 실측 | S76: 2026-09-28 | T76: 공개 영상 0 · X 비활성 · 보류 · 시트 11,500 · 전체 게시물 77개 · 30일 미수집 → 7일 기준 | U76: W1 검증 KOL (8/25 원본) → 9/28 재측정 | V76: WB-K068 | W76: WB-C199 | X76: 기존 목록 연결 | Y76: 46293 | Z76: 노드 구매·적합성·과거 판매 실적 미확인
A77: KR | C77: 영투한 | D77: YouTube | E77: YT | F77: 비활동 | G77: 10700 | Q77: https://www.youtube.com/@02HAN | R77: ✅ 실측 | S77: 2026-09-28 | T77: 롱폼 중단 | U77: W1 검증 KOL (8/25 원본) → 9/28 재측정 | V77: WB-K069 | W77: WB-C175 | X77: 기존 목록 연결 | Y77: 46293 | Z77: 노드 구매·적합성·과거 판매 실적 미확인
A78: KR | C78: 오늘의 꿀통 | D78: YouTube | E78: YT | F78: 비활동 | G78: 10200 | Q78: https://www.youtube.com/@honeyoftoday | R78: ✅ 실측 | S78: 2026-09-28 | T78: 롱폼 중단 | U78: W1 검증 KOL (8/25 원본) → 9/28 재측정 | V78: WB-K070 | W78: WB-C178 | X78: 기존 목록 연결 | Y78: 46293 | Z78: 노드 구매·적합성·과거 판매 실적 미확인
A79: KR | C79: 돈버는 꿀정보 | D79: YouTube | E79: YT | F79: 비활동 | G79: 9640 | Q79: https://www.youtube.com/@donkkul | R79: ✅ 실측 | S79: 2026-09-28 | T79: 롱폼 중단 | U79: W1 검증 KOL (8/25 원본) → 9/28 재측정 | V79: WB-K071 | W79: WB-C173 | X79: 기존 목록 연결 | Y79: 46293 | Z79: 노드 구매·적합성·과거 판매 실적 미확인
A80: KR | C80: 생계형 프로그래머 | D80: YouTube | E80: YT | F80: 비활동 | G80: 4720 | Q80: https://www.youtube.com/@sangptube | R80: ✅ 실측 | S80: 2026-09-28 | T80: 롱폼 중단 | U80: W1 검증 KOL (8/25 원본) → 9/28 재측정 | V80: WB-K072 | W80: WB-C183 | X80: 기존 목록 연결 | Y80: 46293 | Z80: 노드 구매·적합성·과거 판매 실적 미확인
A81: KR | C81: 츄카피 | D81: YouTube | E81: YT | F81: 비활동 | G81: 2300 | Q81: https://www.youtube.com/@chukapika | R81: ✅ 실측 | S81: 2026-09-28 | T81: 롱폼 중단 | U81: W1 검증 KOL (8/25 원본) → 9/28 재측정 | V81: WB-K073 | W81: WB-C184 | X81: 기존 목록 연결 | Y81: 46293 | Z81: 노드 구매·적합성·과거 판매 실적 미확인
A82: KR | C82: 코선생 | D82: Telegram | E82: TG | F82: 비활동 | G82: 1630 | P82: https://t.me/crypto_class_ann | R82: ✅ 실측 | S82: 2026-09-28 | T82: 비활성 | U82: W1 검증 KOL (8/25 원본) → 9/28 재측정 | V82: WB-K074 | W82: WB-C157 | X82: 기존 목록 연결 | Y82: 46293 | Z82: 노드 구매·적합성·과거 판매 실적 미확인
A83: KR | C83: 0xEdenity | D83: Telegram | E83: TG | F83: 비활동 | G83: 1380 | P83: https://t.me/Edenitywl | R83: ✅ 실측 | S83: 2026-09-28 | T83: 비활성 | U83: W1 검증 KOL (8/25 원본) → 9/28 재측정 | V83: WB-K075 | W83: WB-C158 | X83: 기존 목록 연결 | Y83: 46293 | Z83: 노드 구매·적합성·과거 판매 실적 미확인
A84: KR | C84: NFT Forum | D84: Telegram | E84: TG | F84: 비활동 | G84: 610 | P84: https://t.me/NFTForumKR | R84: ✅ 실측 | S84: 2026-09-28 | T84: 비활성 | U84: W1 검증 KOL (8/25 원본) → 9/28 재측정 | V84: WB-K076 | W84: WB-C159 | X84: 기존 목록 연결 | Y84: 46293 | Z84: 노드 구매·적합성·과거 판매 실적 미확인
A85: KR | C85: KOL scan 공지방 | D85: Telegram | E85: TG | F85: 비활동 | G85: 274 | P85: https://t.me/kol_scan | R85: ✅ 실측 | S85: 2026-09-28 | T85: 비활성 | U85: W1 검증 KOL (8/25 원본) → 9/28 재측정 | V85: WB-K077 | W85: WB-C160 | X85: 기존 목록 연결 | Y85: 46293 | Z85: 노드 구매·적합성·과거 판매 실적 미확인
A86: KR | C86: 졸업하자 | D86: Telegram | E86: TG | F86: 비활동 | G86: 261 | P86: https://t.me/letsjolup | R86: ✅ 실측 | S86: 2026-09-28 | T86: 비활성 | U86: W1 검증 KOL (8/25 원본) → 9/28 재측정 | V86: WB-K078 | W86: WB-C161 | X86: 기존 목록 연결 | Y86: 46293 | Z86: 노드 구매·적합성·과거 판매 실적 미확인
A87: KR | C87: 후니방 | D87: Telegram | E87: TG | F87: 비활동 | P87: https://t.me/hooniebang | R87: ✅ 실측 | S87: 2026-09-28 | T87: 미리보기 비공개 | U87: W1 검증 KOL (8/25 원본) → 9/28 재측정 | V87: WB-K079 | W87: WB-C162 | X87: 기존 목록 연결 | Y87: 46293 | Z87: 노드 구매·적합성·과거 판매 실적 미확인
A88: KR | C88: Crypto SENA | D88: Telegram | E88: TG | F88: 비활동 | G88: 7 | P88: https://t.me/CryptoSenaNotice | R88: ✅ 실측 | S88: 2026-09-28 | T88: 비활성 | U88: W1 검증 KOL (8/25 원본) → 9/28 재측정 | V88: WB-K080 | W88: WB-C163 | X88: 기존 목록 연결 | Y88: 46293 | Z88: 노드 구매·적합성·과거 판매 실적 미확인
A89: KR | C89: 기분좋은 마곤 | D89: Telegram | E89: TG | F89: 비활동 | G89: 5 | P89: https://t.me/magoniabbb | R89: ✅ 실측 | S89: 2026-09-28 | T89: 비활성 | U89: W1 검증 KOL (8/25 원본) → 9/28 재측정 | V89: WB-K081 | W89: WB-C164 | X89: 기존 목록 연결 | Y89: 46293 | Z89: 노드 구매·적합성·과거 판매 실적 미확인
A90: Global | B90: Crypto Trader / DeFi | C90: @IncomeSharks | D90: X | E90: X·YT | F90: P1 | G90: 742429 | H90: 40 | I90: 89477 | J90: 0.0078 | K90: 0.12051927 | L90: 235 | M90: S | N90: 2206 | O90: https://x.com/IncomeSharks | Q90: https://www.youtube.com/@IncomeSharks | R90: ✅ 실측 | S90: 2026-09-28 | U90: W1 검증 KOL (8/25 원본) → 9/28 재측정 | V90: WB-K082 | W90: WB-C002 | X90: 기존 목록 연결 | Y90: 46293 | Z90: 노드 구매·적합성·과거 판매 실적 미확인
A91: Global | B91: Crypto Trader, Macro, Youtube / PrimeXBT, OKX, Saros | C91: @Trader_XO | D91: X | E91: X·YT | F91: P1 | G91: 550420 | H91: 59 | I91: 85386 | J91: 0.0048 | K91: 0.15512881 | L91: 270 | M91: S | N91: 2422 | O91: https://x.com/Trader_XO | Q91: https://www.youtube.com/@TraderXO/streams | R91: ✅ 실측 | S91: 2026-09-28 | U91: W1 검증 KOL (8/25 원본) → 9/28 재측정 | V91: WB-K083 | W91: WB-C005 | X91: 기존 목록 연결 | Y91: 46293 | Z91: 노드 구매·적합성·과거 판매 실적 미확인
A92: Global | B92: Crypto Trader, Investor / Bybit | C92: @eliz883 | D92: X | E92: X·YT | F92: P1 | G92: 610000 | H92: 304 | I92: 85107 | J92: 0.0066 | K92: 0.13951967 | L92: 133 | M92: A | N92: 1208 | O92: https://x.com/eliz883 | Q92: https://www.youtube.com/@CryptoEliz | R92: ✅ 실측 | S92: 2026-09-28 | U92: W1 검증 KOL (8/25 원본) → 9/28 재측정 | V92: WB-K084 | W92: WB-C004 | X92: 기존 목록 연결 | Y92: 46293 | Z92: 노드 구매·적합성·과거 판매 실적 미확인
A93: Global | B93: Crypto Trader / NON | C93: @CryptoPoseidonn | D93: X | E93: X·TG | F93: P1 | G93: 175000 | H93: 11 | I93: 74045 | J93: 0.0089 | K93: 0.42311429 | L93: 128 | M93: A | N93: 990 | O93: https://x.com/CryptoPoseidonn | P93: https://t.me/poseidonkitchen | R93: ✅ 실측 | S93: 2026-09-28 | T93: 도달률 42% · 효율 최상 | U93: W1 검증 KOL (8/25 원본) → 9/28 재측정 | V93: WB-K085 | W93: WB-C003 | X93: 기존 목록 연결 | Y93: 46293 | Z93: 노드 구매·적합성·과거 판매 실적 미확인
A94: Global | B94: Crypto, Forex Trader / Solana | C94: @midrizzy1 | D94: X | E94: X·TG | F94: P1 | G94: 89700 | H94: 11 | I94: 62411 | J94: 0.028 | K94: 0.6957748 | L94: 1 | M94: D | N94: 6 | O94: https://x.com/midrizzy1 | P94: https://t.me/OfficialSabiigal | R94: ✅ 실측 | S94: 2026-09-28 | T94: 포렉스·라이프스타일 비중 높음 | U94: W1 검증 KOL (8/25 원본) → 9/28 재측정 | V94: WB-K086 | W94: WB-C001 | X94: 기존 목록 연결 | Y94: 46293 | Z94: 노드 구매·적합성·과거 판매 실적 미확인
A95: Global | B95: PH | C95: Gatzkiee | D95: YouTube | E95: YT | F95: P1 | G95: 35200 | H95: 12 | I95: 14000 | K95: 0.39772727 | Q95: https://www.youtube.com/@Gatzkiee | R95: ✅ 실측 | S95: 2026-09-28 | U95: W1 검증 KOL (8/25 원본) → 9/28 재측정 | V95: WB-K087 | W95: WB-C044 | X95: 기존 목록 연결 | Y95: 46293 | Z95: 노드 구매·적합성·과거 판매 실적 미확인
A96: Global | B96: Crypto, Meme Trader / Blofin, Pionex | C96: @FefeDemeny | D96: YouTube | E96: X·YT | F96: P1 | G96: 42500 | H96: 18 | I96: 13000 | J96: 0.0117 | K96: 0.30588235 | L96: 59 | M96: B | N96: 447 | O96: https://x.com/FefeDemeny | Q96: https://www.youtube.com/@100xclub | R96: ✅ 실측 | S96: 2026-09-28 | U96: W1 검증 KOL (8/25 원본) → 9/28 재측정 | V96: WB-K088 | W96: WB-C045 | X96: 기존 목록 연결 | Y96: 46293 | Z96: 노드 구매·적합성·과거 판매 실적 미확인
A97: Global | B97: PH | C97: InsaneonCrypto | D97: YouTube | E97: YT | F97: P1 | G97: 21600 | H97: 2 | I97: 10000 | K97: 0.46296296 | Q97: https://www.youtube.com/@InsaneonCrypto | R97: ✅ 실측 | S97: 2026-09-28 | U97: W1 검증 KOL (8/25 원본) → 9/28 재측정 | V97: WB-K089 | W97: WB-C046 | X97: 기존 목록 연결 | Y97: 46293 | Z97: 노드 구매·적합성·과거 판매 실적 미확인
A98: Global | B98: Crypto Trader / Bitunix | C98: @rektcapital | D98: X | E98: X·YT | F98: P2 | G98: 563000 | H98: 81 | I98: 65242 | J98: 0.0053 | K98: 0.11588277 | L98: 193 | M98: A | N98: 1860 | O98: https://x.com/rektcapital | Q98: https://www.youtube.com/@RektCapital | R98: ✅ 실측 | S98: 2026-09-28 | U98: W1 검증 KOL (8/25 원본) → 9/28 재측정 | V98: WB-K090 | W98: WB-C007 | X98: 기존 목록 연결 | Y98: 46293 | Z98: 노드 구매·적합성·과거 판매 실적 미확인
A99: Global | B99: Crypto research, DeFi / GMGN, Axiom , DeFi | C99: @DeRonin_ | D99: X | E99: X·TG | F99: P2 | G99: 118197 | H99: 48 | I99: 39946 | J99: 0.0096 | K99: 0.3379612 | L99: 153 | M99: A | N99: 1234 | O99: https://x.com/DeRonin_ | P99: https://t.me/deronin_alpha | R99: ✅ 실측 | S99: 2026-09-28 | T99: 가성비 후보 | U99: W1 검증 KOL (8/25 원본) → 9/28 재측정 | V99: WB-K091 | W99: WB-C006 | X99: 기존 목록 연결 | Y99: 46293 | Z99: 노드 구매·적합성·과거 판매 실적 미확인
A100: Global | B100: Crypto, Meme Trader / Blofin, The Haven | C100: @ColdBloodShill | D100: X | E100: X·YT | F100: P2 | G100: 352483 | H100: 146 | I100: 38127 | J100: 0.0068 | K100: 0.10816692 | L100: 423 | M100: S | N100: 3185 | O100: https://x.com/ColdBloodShill | Q100: https://www.youtube.com/@ColdBloodedShiller | R100: ✅ 실측 | S100: 2026-09-28 | U100: W1 검증 KOL (8/25 원본) → 9/28 재측정 | V100: WB-K092 | W100: WB-C011 | X100: 기존 목록 연결 | Y100: 46293 | Z100: 노드 구매·적합성·과거 판매 실적 미확인
A101: Global | B101: Crypto, Meme Trader / Bybit, $PENGU | C101: @MuroCrypto | D101: X | E101: X·YT | F101: P2 | G101: 403000 | H101: 147 | I101: 35672 | J101: 0.0048 | K101: 0.088516129 | L101: 143 | M101: A | N101: 1249 | O101: https://x.com/MuroCrypto | Q101: https://www.youtube.com/c/murocrypto | R101: ✅ 실측 | S101: 2026-09-28 | U101: W1 검증 KOL (8/25 원본) → 9/28 재측정 | V101: WB-K093 | W101: WB-C015 | X101: 기존 목록 연결 | Y101: 46293 | Z101: 노드 구매·적합성·과거 판매 실적 미확인
...

Sheet 글로벌 X
A1: 글로벌 X — 43개 계정
A2: ■ 정렬: 퍼포먼스 → 30일 평균 반응 높은 순 · 본인 글만 집계 (리포스트·고정 제외) · 수집 2026-09-28
A3: ■ 퍼포먼스 등급 [제안 기준] — X: 게시물당 평균 반응(평균 조회×ER) P1 400+ · P2 150+ · P3 50+ · P4 50 미만 · 비활동 = 30일 3건 미만
A4: ■ ⚠️ 게시량 과다 계정은 일부 기간만 수집 (메모 참고) · @haloETH ER은 답글 비중 과다로 참고만
D6: 영향력 | H6: 24시간 | L6: 7일 | P6: 30일
A7: 순위 | B7: KOL | C7: 퍼포먼스 | D7: Twitter Score | E7: TS 등급 | F7: 스마트 팔로워 | G7: 팔로워 | H7: 게시 | I7: 평균 조회 | J7: 평균 반응 | K7: ER | L7: 게시 | M7: 평균 조회 | N7: 평균 반응 | O7: ER | P7: 게시 | Q7: 평균 조회 | R7: 평균 반응 | S7: ER | T7: 도달률 (조회÷팔로워) | U7: 추세 (7d vs 30d) | V7: 메모 | W7: 링크 | X7: 채널 ID | Y7: KOL ID | Z7: 측정 상태
A8: 1 | B8: @midrizzy1 | C8: P1 | D8: 1 | E8: D | F8: 6 | G8: 89700 | L8: 2 | M8: 98126 | N8: 2198.0224 | O8: 0.0224 | P8: 11 | Q8: 62411 | R8: 1747.508 | S8: 0.028 | T8: 0.6957748 | U8: 0.57225489 | V8: 포렉스·라이프스타일 비중 높음 | W8: https://x.com/midrizzy1 | X8: WB-C001 | Y8: WB-K086 | Z8: {=_xlfn.XLOOKUP(X8,'측정 관리'!$A$5:$A$204,'측정 관리'!$K$5:$K$204,"",0)} -> 기간 확인 필요
A9: 2 | B9: @IncomeSharks | C9: P1 | D9: 235 | E9: S | F9: 2206 | G9: 742429 | H9: 1 | I9: 68228 | J9: 743.6852 | K9: 0.0109 | L9: 9 | M9: 85897 | N9: 764.4833 | O9: 0.0089 | P9: 40 | Q9: 89477 | R9: 697.9206 | S9: 0.0078 | T9: 0.12051927 | U9: -0.040010282 | W9: https://x.com/IncomeSharks | X9: WB-C002 | Y9: WB-K082 | Z9: {=_xlfn.XLOOKUP(X9,'측정 관리'!$A$5:$A$204,'측정 관리'!$K$5:$K$204,"",0)}
A10: 3 | B10: @CryptoPoseidonn | C10: P1 | D10: 128 | E10: A | F10: 990 | G10: 175000 | L10: 3 | M10: 66587 | N10: 685.8461 | O10: 0.0103 | P10: 11 | Q10: 74045 | R10: 659.0005 | S10: 0.0089 | T10: 0.42311429 | U10: -0.10072253 | V10: 도달률 42% · 효율 최상 | W10: https://x.com/CryptoPoseidonn | X10: WB-C003 | Y10: WB-K085 | Z10: {=_xlfn.XLOOKUP(X10,'측정 관리'!$A$5:$A$204,'측정 관리'!$K$5:$K$204,"",0)}
A11: 4 | B11: @eliz883 | C11: P1 | D11: 133 | E11: A | F11: 1208 | G11: 610000 | H11: 14 | I11: 61808 | J11: 414.1136 | K11: 0.0067 | L11: 90 | M11: 77406 | N11: 642.4698 | O11: 0.0083 | P11: 304 | Q11: 85107 | R11: 561.7062 | S11: 0.0066 | T11: 0.13951967 | U11: -0.090486094 | W11: https://x.com/eliz883 | X11: WB-C004 | Y11: WB-K084 | Z11: {=_xlfn.XLOOKUP(X11,'측정 관리'!$A$5:$A$204,'측정 관리'!$K$5:$K$204,"",0)}
A12: 5 | B12: @Trader_XO | C12: P1 | D12: 270 | E12: S | F12: 2422 | G12: 550420 | H12: 3 | I12: 32786 | J12: 98.358 | K12: 0.003 | L12: 27 | M12: 86878 | N12: 408.3266 | O12: 0.0047 | P12: 59 | Q12: 85386 | R12: 409.8528 | S12: 0.0048 | T12: 0.15512881 | U12: 0.017473591 | W12: https://x.com/Trader_XO | X12: WB-C005 | Y12: WB-K083 | Z12: {=_xlfn.XLOOKUP(X12,'측정 관리'!$A$5:$A$204,'측정 관리'!$K$5:$K$204,"",0)}
A13: 6 | B13: @DeRonin_ | C13: P2 | D13: 153 | E13: A | F13: 1234 | G13: 118197 | H13: 1 | I13: 41344 | J13: 628.4288 | K13: 0.0152 | L13: 7 | M13: 22230 | N13: 342.342 | O13: 0.0154 | P13: 48 | Q13: 39946 | R13: 383.4816 | S13: 0.0096 | T13: 0.3379612 | U13: -0.44349872 | V13: 가성비 후보 | W13: https://x.com/DeRonin_ | X13: WB-C006 | Y13: WB-K091 | Z13: {=_xlfn.XLOOKUP(X13,'측정 관리'!$A$5:$A$204,'측정 관리'!$K$5:$K$204,"",0)}
A14: 7 | B14: @rektcapital | C14: P2 | D14: 193 | E14: A | F14: 1860 | G14: 563000 | L14: 25 | M14: 52314 | N14: 360.9666 | O14: 0.0069 | P14: 81 | Q14: 65242 | R14: 345.7826 | S14: 0.0053 | T14: 0.11588277 | U14: -0.19815456 | W14: https://x.com/rektcapital | X14: WB-C007 | Y14: WB-K090 | Z14: {=_xlfn.XLOOKUP(X14,'측정 관리'!$A$5:$A$204,'측정 관리'!$K$5:$K$204,"",0)} -> 기간 확인 필요
A15: 8 | B15: @nobrainflip | C15: P2 | D15: 163 | E15: A | F15: 1645 | G15: 543000 | H15: 4 | I15: 139397 | J15: 376.3719 | K15: 0.0027 | L15: 52 | M15: 80919 | N15: 291.3084 | O15: 0.0036 | P15: 71 | Q15: 80343 | R15: 329.4063 | S15: 0.0041 | T15: 0.14796133 | U15: 0.0071692618 | W15: https://x.com/nobrainflip | X15: WB-C008 | Y15: WB-K100 | Z15: {=_xlfn.XLOOKUP(X15,'측정 관리'!$A$5:$A$204,'측정 관리'!$K$5:$K$204,"",0)}
A16: 9 | B16: @inmortalcrypto | C16: P2 | D16: 145 | E16: A | F16: 1257 | G16: 232451 | L16: 14 | M16: 31005 | N16: 384.462 | O16: 0.0124 | P16: 42 | Q16: 25898 | R16: 292.6474 | S16: 0.0113 | T16: 0.11141273 | U16: 0.19719669 | W16: https://x.com/inmortalcrypto | X16: WB-C009 | Y16: WB-K095 | Z16: {=_xlfn.XLOOKUP(X16,'측정 관리'!$A$5:$A$204,'측정 관리'!$K$5:$K$204,"",0)}
A17: 10 | B17: @follis_ | C17: P2 | D17: 121 | E17: A | F17: 876 | G17: 128000 | H17: 5 | I17: 16513 | J17: 232.8333 | K17: 0.0141 | L17: 33 | M17: 18918 | N17: 304.5798 | O17: 0.0161 | P17: 145 | Q17: 26419 | R17: 287.9671 | S17: 0.0109 | T17: 0.20639844 | U17: -0.28392445 | W17: https://x.com/follis_ | X17: WB-C010 | Y17: WB-K094 | Z17: {=_xlfn.XLOOKUP(X17,'측정 관리'!$A$5:$A$204,'측정 관리'!$K$5:$K$204,"",0)}
A18: 11 | B18: @ColdBloodShill | C18: P2 | D18: 423 | E18: S | F18: 3185 | G18: 352483 | H18: 2 | I18: 17567 | J18: 149.3195 | K18: 0.0085 | L18: 19 | M18: 27263 | N18: 245.367 | O18: 0.009 | P18: 146 | Q18: 38127 | R18: 259.2636 | S18: 0.0068 | T18: 0.10816692 | U18: -0.28494243 | W18: https://x.com/ColdBloodShill | X18: WB-C011 | Y18: WB-K092 | Z18: {=_xlfn.XLOOKUP(X18,'측정 관리'!$A$5:$A$204,'측정 관리'!$K$5:$K$204,"",0)}
A19: 12 | B19: @FefeDemeny | C19: P2 | D19: 59 | E19: B | F19: 447 | G19: 66900 | H19: 2 | I19: 12407 | J19: 116.6258 | K19: 0.0094 | L19: 17 | M19: 17577 | N19: 186.3162 | O19: 0.0106 | P19: 45 | Q19: 19233 | R19: 225.0261 | S19: 0.0117 | T19: 0.28748879 | U19: -0.086102012 | W19: https://x.com/FefeDemeny | X19: WB-C012 | Y19: WB-K088 | Z19: {=_xlfn.XLOOKUP(X19,'측정 관리'!$A$5:$A$204,'측정 관리'!$K$5:$K$204,"",0)}
A20: 13 | B20: @EricCryptoman | C20: P2 | D20: 227 | E20: S | F20: 1898 | G20: 272253 | H20: 2 | I20: 17946 | J20: 224.325 | K20: 0.0125 | L20: 30 | M20: 20823 | N20: 191.5716 | O20: 0.0092 | P20: 181 | Q20: 23777 | R20: 209.2376 | S20: 0.0088 | T20: 0.087334208 | U20: -0.12423771 | W20: https://x.com/EricCryptoman | X20: WB-C013 | Y20: WB-K101 | Z20: {=_xlfn.XLOOKUP(X20,'측정 관리'!$A$5:$A$204,'측정 관리'!$K$5:$K$204,"",0)}
A21: 14 | B21: @haloETH | C21: P2 | D21: 47 | E21: B | F21: 444 | G21: 58015 | L21: 2 | M21: 2986 | N21: 318.9048 | O21: 0.1068 | P21: 16 | Q21: 5438 | R21: 201.7498 | S21: 0.0371 | T21: 0.093734379 | U21: -0.45090107 | V21: 답글 비중 과다 · 참여 품앗이 의심 | W21: https://x.com/haloETH | X21: WB-C014 | Y21: WB-K098 | Z21: {=_xlfn.XLOOKUP(X21,'측정 관리'!$A$5:$A$204,'측정 관리'!$K$5:$K$204,"",0)}
A22: 15 | B22: @MuroCrypto | C22: P2 | D22: 143 | E22: A | F22: 1249 | G22: 403000 | L22: 32 | M22: 39978 | N22: 187.8966 | O22: 0.0047 | P22: 147 | Q22: 35672 | R22: 171.2256 | S22: 0.0048 | T22: 0.088516129 | U22: 0.12071092 | W22: https://x.com/MuroCrypto | X22: WB-C015 | Y22: WB-K093 | Z22: {=_xlfn.XLOOKUP(X22,'측정 관리'!$A$5:$A$204,'측정 관리'!$K$5:$K$204,"",0)}
A23: 16 | B23: @DaanCrypto | C23: P2 | D23: 192 | E23: A | F23: 1601 | G23: 415069 | P23: 7 | Q23: 20832 | R23: 170.8224 | S23: 0.0082 | T23: 0.050189246 | V23: 8/30 이후 게시 없음 | W23: https://x.com/DaanCrypto | X23: WB-C016 | Y23: WB-K096 | Z23: {=_xlfn.XLOOKUP(X23,'측정 관리'!$A$5:$A$204,'측정 관리'!$K$5:$K$204,"",0)}
A24: 17 | B24: @AltcoinSherpa | C24: P3 | D24: 280 | E24: S | F24: 2014 | G24: 263424 | H24: 6 | I24: 13439 | J24: 114.2315 | K24: 0.0085 | L24: 98 | M24: 16398 | N24: 162.3402 | O24: 0.0099 | P24: 530 | Q24: 14357 | R24: 119.1631 | S24: 0.0083 | T24: 0.054501488 | U24: 0.14216062 | V24: 30일 530건 → 스폰서 글 묻힘 위험 | W24: https://x.com/AltcoinSherpa | X24: WB-C017 | Y24: WB-K104 | Z24: {=_xlfn.XLOOKUP(X24,'측정 관리'!$A$5:$A$204,'측정 관리'!$K$5:$K$204,"",0)}
A25: 18 | B25: @DeFiOracle_ | C25: P3 | D25: 46 | E25: B | F25: 413 | G25: 18700 | L25: 4 | M25: 8172 | N25: 79.2684 | O25: 0.0097 | P25: 18 | Q25: 7805 | R25: 115.514 | S25: 0.0148 | T25: 0.41737968 | U25: 0.04702114 | W25: https://x.com/DeFiOracle_ | X25: WB-C018 | Y25: WB-K106 | Z25: {=_xlfn.XLOOKUP(X25,'측정 관리'!$A$5:$A$204,'측정 관리'!$K$5:$K$204,"",0)}
A26: 19 | B26: @KoroushAK | C26: P3 | D26: 189 | E26: A | F26: 1556 | G26: 377469 | H26: 2 | I26: 12650 | J26: 65.78 | K26: 0.0052 | L26: 16 | M26: 19177 | N26: 109.3089 | O26: 0.0057 | P26: 63 | Q26: 19273 | R26: 96.365 | S26: 0.005 | T26: 0.051058498 | U26: -0.0049810616 | W26: https://x.com/KoroushAK | X26: WB-C019 | Y26: WB-K109 | Z26: {=_xlfn.XLOOKUP(X26,'측정 관리'!$A$5:$A$204,'측정 관리'!$K$5:$K$204,"",0)}
A27: 20 | B27: @PhilakoneCrypto | C27: P3 | D27: 52 | E27: B | F27: 503 | G27: 185000 | H27: 7 | I27: 17926 | J27: 75.2892 | K27: 0.0042 | L27: 44 | M27: 18320 | N27: 119.08 | O27: 0.0065 | P27: 157 | Q27: 15729 | R27: 91.2282 | S27: 0.0058 | T27: 0.085021622 | U27: 0.16472757 | W27: https://x.com/PhilakoneCrypto | X27: WB-C020 | Y27: WB-K099 | Z27: {=_xlfn.XLOOKUP(X27,'측정 관리'!$A$5:$A$204,'측정 관리'!$K$5:$K$204,"",0)}
A28: 21 | B28: @0xklarck | C28: P3 | D28: 12 | E28: D | F28: 118 | G28: 95400 | H28: 2 | I28: 8659 | J28: 33.7701 | K28: 0.0039 | L28: 18 | M28: 37359 | N28: 85.9257 | O28: 0.0023 | P28: 57 | Q28: 28303 | R28: 87.7393 | S28: 0.0031 | T28: 0.29667715 | U28: 0.31996608 | V28: 30일은 9/4 이후만 수집 | W28: https://x.com/0xklarck | X28: WB-C021 | Y28: WB-K102 | Z28: {=_xlfn.XLOOKUP(X28,'측정 관리'!$A$5:$A$204,'측정 관리'!$K$5:$K$204,"",0)}
A29: 22 | B29: @w1nklerr | C29: P3 | D29: 8 | E29: D | F29: 79 | G29: 61000 | H29: 1 | I29: 27940 | J29: 226.314 | K29: 0.0081 | L29: 12 | M29: 7772 | N29: 48.1864 | O29: 0.0062 | P29: 39 | Q29: 12384 | R29: 84.2112 | S29: 0.0068 | T29: 0.20301639 | U29: -0.37241602 | V29: 30일은 9/11 이후만 수집 · 유료 파트너십 게시 있음 | W29: https://x.com/w1nklerr | X29: WB-C022 | Y29: WB-K115 | Z29: {=_xlfn.XLOOKUP(X29,'측정 관리'!$A$5:$A$204,'측정 관리'!$K$5:$K$204,"",0)}
A30: 23 | B30: @evancrypt | C30: P3 | D30: 46 | E30: B | F30: 436 | G30: 30300 | H30: 1 | I30: 373 | J30: 7.0124 | K30: 0.0188 | L30: 3 | M30: 5652 | N30: 54.2592 | O30: 0.0096 | P30: 31 | Q30: 5881 | R30: 79.3935 | S30: 0.0135 | T30: 0.19409241 | U30: -0.038938956 | W30: https://x.com/evancrypt | X30: WB-C023 | Y30: WB-K108 | Z30: {=_xlfn.XLOOKUP(X30,'측정 관리'!$A$5:$A$204,'측정 관리'!$K$5:$K$204,"",0)}
A31: 24 | B31: @WhaleNoName | C31: P3 | D31: 20 | E31: C | F31: 175 | G31: 50800 | H31: 2 | I31: 5424 | J31: 46.6464 | K31: 0.0086 | L31: 36 | M31: 22663 | N31: 77.0542 | O31: 0.0034 | P31: 36 | Q31: 22663 | R31: 77.0542 | S31: 0.0034 | T31: 0.44612205 | U31: 0 | V31: 게시량 과다 · 30일은 9/21 이후만 수집 | W31: https://x.com/WhaleNoName | X31: WB-C024 | Y31: WB-K103 | Z31: {=_xlfn.XLOOKUP(X31,'측정 관리'!$A$5:$A$204,'측정 관리'!$K$5:$K$204,"",0)}
A32: 25 | B32: @spacexbt | C32: P3 | D32: 91 | E32: B | F32: 547 | G32: 18500 | H32: 1 | I32: 1722 | J32: 9.9876 | K32: 0.0058 | L32: 13 | M32: 2642 | N32: 15.0594 | O32: 0.0057 | P32: 31 | Q32: 10491 | R32: 65.0442 | S32: 0.0062 | T32: 0.56708108 | U32: -0.74816509 | W32: https://x.com/spacexbt | X32: WB-C025 | Y32: WB-K105 | Z32: {=_xlfn.XLOOKUP(X32,'측정 관리'!$A$5:$A$204,'측정 관리'!$K$5:$K$204,"",0)}
A33: 26 | B33: @0xjayn3 | C33: P3 | D33: 26 | E33: C | F33: 193 | G33: 32500 | H33: 7 | I33: 5099 | J33: 56.089 | K33: 0.011 | L33: 56 | M33: 5937 | N33: 58.1826 | O33: 0.0098 | P33: 56 | Q33: 5937 | R33: 58.1826 | S33: 0.0098 | T33: 0.18267692 | U33: 0 | V33: 게시량 과다 · 30일은 9/22 이후만 수집 | W33: https://x.com/0xjayn3 | X33: WB-C026 | Y33: WB-K107 | Z33: {=_xlfn.XLOOKUP(X33,'측정 관리'!$A$5:$A$204,'측정 관리'!$K$5:$K$204,"",0)}
A34: 27 | B34: @ChadCaff | C34: P4 | D34: 133 | E34: A | F34: 1138 | G34: 132000 | L34: 6 | M34: 6670 | N34: 46.023 | O34: 0.0069 | P34: 25 | Q34: 6494 | R34: 42.211 | S34: 0.0065 | T34: 0.04919697 | U34: 0.02710194 | V34: 점수 대비 약함 | W34: https://x.com/ChadCaff | X34: WB-C027 | Y34: WB-K116 | Z34: {=_xlfn.XLOOKUP(X34,'측정 관리'!$A$5:$A$204,'측정 관리'!$K$5:$K$204,"",0)}
A35: 28 | B35: @0xFrogify | C35: P4 | D35: 5 | E35: D | F35: 59 | G35: 45200 | H35: 1 | I35: 5837 | J35: 35.022 | K35: 0.006 | L35: 8 | M35: 6773 | N35: 38.6061 | O35: 0.0057 | P35: 34 | Q35: 9013 | R35: 27.9403 | S35: 0.0031 | T35: 0.19940265 | U35: -0.2485299 | W35: https://x.com/0xFrogify | X35: WB-C028 | Y35: WB-K125 | Z35: {=_xlfn.XLOOKUP(X35,'측정 관리'!$A$5:$A$204,'측정 관리'!$K$5:$K$204,"",0)}
A36: 29 | B36: @0xchromium | C36: P4 | D36: 24 | E36: C | F36: 201 | G36: 22800 | H36: 1 | I36: 1687 | J36: 40.9941 | K36: 0.0243 | L36: 13 | M36: 1897 | N36: 25.6095 | O36: 0.0135 | P36: 16 | Q36: 2009 | R36: 27.1215 | S36: 0.0135 | T36: 0.088114035 | U36: -0.055749129 | V36: 30일은 9/19 이후만 수집 | W36: https://x.com/0xchromium | X36: WB-C029 | Y36: WB-K120 | Z36: {=_xlfn.XLOOKUP(X36,'측정 관리'!$A$5:$A$204,'측정 관리'!$K$5:$K$204,"",0)}
A37: 30 | B37: @0xDepressionn | C37: P4 | D37: 57 | E37: B | F37: 403 | G37: 46100 | H37: 1 | I37: 949 | J37: 11.0084 | K37: 0.0116 | L37: 6 | M37: 1263 | N37: 16.5453 | O37: 0.0131 | P37: 39 | Q37: 3489 | R37: 26.5164 | S37: 0.0076 | T37: 0.075683297 | U37: -0.63800516 | W37: https://x.com/0xDepressionn | X37: WB-C030 | Y37: WB-K118 | Z37: {=_xlfn.XLOOKUP(X37,'측정 관리'!$A$5:$A$204,'측정 관리'!$K$5:$K$204,"",0)}
A38: 31 | B38: @woody_research | C38: P4 | D38: 3 | E38: D | F38: 6 | G38: 21200 | L38: 8 | M38: 1865 | N38: 22.753 | O38: 0.0122 | P38: 28 | Q38: 3431 | R38: 23.6739 | S38: 0.0069 | T38: 0.16183962 | U38: -0.4564267 | V38: 30일은 9/4 이후만 수집 | W38: https://x.com/woody_research | X38: WB-C031 | Y38: WB-K119 | Z38: {=_xlfn.XLOOKUP(X38,'측정 관리'!$A$5:$A$204,'측정 관리'!$K$5:$K$204,"",0)}
A39: 32 | B39: @zeuuss_01 | C39: P4 | D39: 65 | E39: B | F39: 524 | G39: 31000 | H39: 1 | I39: 1646 | J39: 16.9538 | K39: 0.0103 | L39: 19 | M39: 3725 | N39: 28.31 | O39: 0.0076 | P39: 74 | Q39: 5332 | R39: 21.328 | S39: 0.004 | T39: 0.172 | U39: -0.30138785 | W39: https://x.com/zeuuss_01 | X39: WB-C032 | Y39: WB-K117 | Z39: {=_xlfn.XLOOKUP(X39,'측정 관리'!$A$5:$A$204,'측정 관리'!$K$5:$K$204,"",0)}
A40: 33 | B40: @terra_gatsuki | C40: P4 | D40: 30 | E40: C | F40: 261 | G40: 25800 | L40: 6 | M40: 665 | N40: 4.8545 | O40: 0.0073 | P40: 9 | Q40: 714 | R40: 3.57 | S40: 0.005 | T40: 0.027674419 | U40: -0.068627451 | W40: https://x.com/terra_gatsuki | X40: WB-C033 | Y40: WB-K123 | Z40: {=_xlfn.XLOOKUP(X40,'측정 관리'!$A$5:$A$204,'측정 관리'!$K$5:$K$204,"",0)}
A41: 34 | B41: @plutos_eth | C41: P4 | D41: 24 | E41: C | F41: 192 | G41: 44400 | H41: 1 | I41: 1465 | J41: 1.0255 | K41: 0.0007 | L41: 3 | M41: 1478 | N41: 2.6604 | O41: 0.0018 | P41: 24 | Q41: 1608 | R41: 2.8944 | S41: 0.0018 | T41: 0.036216216 | U41: -0.080845771 | V41: AI 에이전트 콘텐츠 위주 · 반응 매우 낮음 | W41: https://x.com/plutos_eth | X41: WB-C034 | Y41: WB-K121 | Z41: {=_xlfn.XLOOKUP(X41,'측정 관리'!$A$5:$A$204,'측정 관리'!$K$5:$K$204,"",0)}
A42: 35 | B42: @LookForEntries | C42: P4 | D42: 22 | E42: C | F42: 163 | G42: 56200 | H42: 23 | I42: 704 | J42: 7.5328 | K42: 0.0107 | V42: 게시량 과다(24h 23건) · 24h만 수집 | W42: https://x.com/LookForEntries | X42: WB-C035 | Y42: WB-K126 | Z42: {=_xlfn.XLOOKUP(X42,'측정 관리'!$A$5:$A$204,'측정 관리'!$K$5:$K$204,"",0)} -> 일부 수집
A43: 36 | B43: @onlineboss_ | C43: 비활동 | D43: 17 | E43: C | F43: 136 | G43: 52200 | P43: 1 | Q43: 3065 | R43: 52.105 | S43: 0.017 | T43: 0.058716475 | V43: 마지막 글 9/9 · 거의 비활동 | W43: https://x.com/onlineboss_ | X43: WB-C036 | Y43: WB-K127 | Z43: {=_xlfn.XLOOKUP(X43,'측정 관리'!$A$5:$A$204,'측정 관리'!$K$5:$K$204,"",0)}
A44: 37 | B44: @ItsRagnarYT | C44: 비활동 | D44: 39 | E44: C | F44: 255 | G44: 23300 | P44: 2 | Q44: 855 | R44: 8.9775 | S44: 0.0105 | T44: 0.036695279 | V44: 마지막 글 9/14 | W44: https://x.com/ItsRagnarYT | X44: WB-C037 | Y44: WB-K097 | Z44: {=_xlfn.XLOOKUP(X44,'측정 관리'!$A$5:$A$204,'측정 관리'!$K$5:$K$204,"",0)}
A45: 38 | B45: @fried_dev | C45: 비활동 | D45: 0 | E45: D | F45: 4 | G45: 1206 | V45: 마지막 글 7/10 · 비활동 | W45: https://x.com/fried_dev | X45: WB-C038 | Y45: WB-K131 | Z45: {=_xlfn.XLOOKUP(X45,'측정 관리'!$A$5:$A$204,'측정 관리'!$K$5:$K$204,"",0)}
A46: 39 | B46: @0xDarya_ | C46: 비활동 | D46: 21 | E46: C | F46: 199 | G46: 33700 | V46: 마지막 글 6/10 · 비활동 | W46: https://x.com/0xDarya_ | X46: WB-C039 | Y46: WB-K132 | Z46: {=_xlfn.XLOOKUP(X46,'측정 관리'!$A$5:$A$204,'측정 관리'!$K$5:$K$204,"",0)}
A47: 40 | B47: @0xCryptoAmbush | C47: 비활동 | D47: 0 | E47: D | G47: 798 | V47: 마지막 글 2/25 · 비활동 | W47: https://x.com/0xCryptoAmbush | X47: WB-C040 | Y47: WB-K133 | Z47: {=_xlfn.XLOOKUP(X47,'측정 관리'!$A$5:$A$204,'측정 관리'!$K$5:$K$204,"",0)}
A48: 41 | B48: @0xImmortal_ | C48: 비활동 | D48: 7 | E48: D | F48: 62 | G48: 9056 | V48: 마지막 글 6/24 · 비활동 | W48: https://x.com/0xImmortal_ | X48: WB-C041 | Y48: WB-K134 | Z48: {=_xlfn.XLOOKUP(X48,'측정 관리'!$A$5:$A$204,'측정 관리'!$K$5:$K$204,"",0)}
A49: 42 | B49: @kepochnik_ | C49: 없음 | V49: X 계정 없음 (삭제·변경) · TG kepochnikalpha는 7일 1건 | W49: https://x.com/kepochnik_ | X49: WB-C042 | Y49: WB-K128 | Z49: {=_xlfn.XLOOKUP(X49,'측정 관리'!$A$5:$A$204,'측정 관리'!$K$5:$K$204,"",0)}
A50: 43 | B50: @BULLX132 | C50: 없음 | V50: X 계정 없음 (삭제·변경) | W50: https://x.com/BULLX132 | X50: WB-C043 | Y50: WB-K135 | Z50: {=_xlfn.XLOOKUP(X50,'측정 관리'!$A$5:$A$204,'측정 관리'!$K$5:$K$204,"",0)}

Sheet 글로벌 YT
A1: 글로벌 YouTube — 26개 채널 (롱폼)
A2: ■ 롱폼 영상 기준 (쇼츠 제외) · 퍼포먼스 = 30일 중앙 조회 P1 10,000+ · P2 3,000+ · P3 1,000+ · 비활동 = 30일 0개
A3: ■ YouTube는 공개 페이지에 좋아요 수가 없어 ER 대신 도달률(중앙 조회 ÷ 구독자)로 반응을 봄 · 조회수는 표시값(천 단위 반올림)
A4: ■ ⚠️ 영상 2개 이하 채널은 표본이 작아 등급 변동 큼 · @Gatzkiee 30일 평균은 바이럴 1건 영향 (중앙값 기준 권장)
G6: 24시간 | I6: 7일 | L6: 30일
A7: 순위 | B7: 채널 | C7: 핸들 | D7: 퍼포먼스 | E7: 구독자 | F7: 최근 영상 (일 전) | G7: 영상 | H7: 평균 조회 | I7: 영상 | J7: 평균 조회 | K7: 중앙 조회 | L7: 영상 | M7: 평균 조회 | N7: 중앙 조회 | O7: 도달률 (중앙÷구독) | P7: 메모 | Q7: 링크 | X7: 채널 ID | Y7: KOL ID | Z7: 측정 상태
A8: 1 | B8: gatzkiee | C8: @Gatzkiee | D8: P1 | E8: 35200 | F8: 2 | I8: 3 | J8: 12000 | K8: 12000 | L8: 12 | M8: 52358 | N8: 14000 | O8: 0.39772727 | Q8: https://www.youtube.com/@Gatzkiee | X8: WB-C044 | Y8: WB-K087 | Z8: {=_xlfn.XLOOKUP(X8,'측정 관리'!$A$5:$A$204,'측정 관리'!$K$5:$K$204,"",0)}
A9: 2 | B9: 100XClub | C9: @100xclub | D9: P1 | E9: 42500 | F9: 0 | G9: 1 | H9: 1300 | I9: 5 | J9: 10220 | K9: 11000 | L9: 18 | M9: 12339 | N9: 13000 | O9: 0.30588235 | Q9: https://www.youtube.com/@100xclub | X9: WB-C045 | Y9: WB-K088 | Z9: {=_xlfn.XLOOKUP(X9,'측정 관리'!$A$5:$A$204,'측정 관리'!$K$5:$K$204,"",0)}
A10: 3 | B10: Insane on Crypto | C10: @InsaneonCrypto | D10: P1 | E10: 21600 | F10: 4 | I10: 1 | J10: 10000 | K10: 10000 | L10: 2 | M10: 5600 | N10: 10000 | O10: 0.46296296 | Q10: https://www.youtube.com/@InsaneonCrypto | X10: WB-C046 | Y10: WB-K089 | Z10: {=_xlfn.XLOOKUP(X10,'측정 관리'!$A$5:$A$204,'측정 관리'!$K$5:$K$204,"",0)}
A11: 4 | B11: ItsRagnar | C11: @ItsRagnar | D11: P2 | E11: 35900 | F11: 2 | I11: 1 | J11: 3400 | K11: 3400 | L11: 5 | M11: 6820 | N11: 5600 | O11: 0.15598886 | Q11: https://www.youtube.com/@ItsRagnar | X11: WB-C047 | Y11: WB-K097 | Z11: {=_xlfn.XLOOKUP(X11,'측정 관리'!$A$5:$A$204,'측정 관리'!$K$5:$K$204,"",0)}
A12: 5 | B12: Philakone | C12: @philakonecrypto | D12: P2 | E12: 85700 | F12: 1 | G12: 1 | H12: 3500 | I12: 2 | J12: 4400 | K12: 5300 | L12: 3 | M12: 4967 | N12: 5300 | O12: 0.061843641 | Q12: https://www.youtube.com/@philakonecrypto | X12: WB-C048 | Y12: WB-K099 | Z12: {=_xlfn.XLOOKUP(X12,'측정 관리'!$A$5:$A$204,'측정 관리'!$K$5:$K$204,"",0)}
A13: 6 | B13: Koroush AK | C13: @Koroushak | D13: P3 | E13: 106000 | F13: 5 | I13: 1 | J13: 2400 | K13: 2400 | L13: 4 | M13: 2750 | N13: 2600 | O13: 0.024528302 | Q13: https://www.youtube.com/@Koroushak | X13: WB-C049 | Y13: WB-K109 | Z13: {=_xlfn.XLOOKUP(X13,'측정 관리'!$A$5:$A$204,'측정 관리'!$K$5:$K$204,"",0)}
A14: 7 | B14: MrCrypto PH | C14: @MrCryptoPH | D14: P3 | E14: 33600 | F14: 21 | L14: 2 | M14: 1350 | N14: 1600 | O14: 0.047619048 | Q14: https://www.youtube.com/@MrCryptoPH | X14: WB-C050 | Y14: WB-K110 | Z14: {=_xlfn.XLOOKUP(X14,'측정 관리'!$A$5:$A$204,'측정 관리'!$K$5:$K$204,"",0)}
A15: 8 | B15: DalarinTV - Crypto | C15: @DalarinTV | D15: P3 | E15: 41300 | F15: 0 | G15: 1 | H15: 867 | I15: 2 | J15: 2934 | K15: 5000 | L15: 6 | M15: 2074 | N15: 1500 | O15: 0.036319613 | Q15: https://www.youtube.com/@DalarinTV | X15: WB-C051 | Y15: WB-K111 | Z15: {=_xlfn.XLOOKUP(X15,'측정 관리'!$A$5:$A$204,'측정 관리'!$K$5:$K$204,"",0)}
A16: 9 | B16: Indep | C16: @Indep15 | D16: P3 | E16: 14500 | F16: 3 | I16: 3 | J16: 3241 | K16: 1400 | L16: 5 | M16: 2545 | N16: 1400 | O16: 0.096551724 | Q16: https://www.youtube.com/@Indep15 | X16: WB-C052 | Y16: WB-K112 | Z16: {=_xlfn.XLOOKUP(X16,'측정 관리'!$A$5:$A$204,'측정 관리'!$K$5:$K$204,"",0)}
A17: 10 | B17: Smithii | C17: @Smithii | D17: P3 | E17: 10400 | F17: 10 | L17: 2 | M17: 896 | N17: 1400 | O17: 0.13461538 | Q17: https://www.youtube.com/@Smithii | X17: WB-C053 | Y17: WB-K113 | Z17: {=_xlfn.XLOOKUP(X17,'측정 관리'!$A$5:$A$204,'측정 관리'!$K$5:$K$204,"",0)}
A18: 11 | B18: Nazza Crypto | C18: @nazzacrypto | D18: P3 | E18: 36300 | F18: 1 | G18: 1 | H18: 1700 | I18: 8 | J18: 2219 | K18: 1700 | L18: 13 | M18: 3348 | N18: 1200 | O18: 0.033057851 | Q18: https://www.youtube.com/@nazzacrypto | X18: WB-C054 | Y18: WB-K114 | Z18: {=_xlfn.XLOOKUP(X18,'측정 관리'!$A$5:$A$204,'측정 관리'!$K$5:$K$204,"",0)}
A19: 12 | B19: Follis | C19: @follis_ | D19: P3 | E19: 7210 | F19: 0 | G19: 1 | H19: 565 | I19: 3 | J19: 847 | K19: 775 | L19: 7 | M19: 1196 | N19: 1200 | O19: 0.16643551 | Q19: https://www.youtube.com/@follis_ | X19: WB-C055 | Y19: WB-K094 | Z19: {=_xlfn.XLOOKUP(X19,'측정 관리'!$A$5:$A$204,'측정 관리'!$K$5:$K$204,"",0)}
A20: 13 | B20: Buhok Gaming | C20: @BuhokGaming | D20: P4 | E20: 64400 | F20: 3 | I20: 3 | J20: 7767 | K20: 11000 | L20: 8 | M20: 3170 | N20: 746 | O20: 0.011583851 | Q20: https://www.youtube.com/@BuhokGaming | X20: WB-C056 | Y20: WB-K122 | Z20: {=_xlfn.XLOOKUP(X20,'측정 관리'!$A$5:$A$204,'측정 관리'!$K$5:$K$204,"",0)}
A21: 14 | B21: MURO CRYPTO | C21: c/murocrypto | D21: P4 | E21: 14300 | F21: 14 | L21: 4 | M21: 535 | N21: 667 | O21: 0.046643357 | Q21: https://www.youtube.com/c/murocrypto | X21: WB-C057 | Y21: WB-K093 | Z21: {=_xlfn.XLOOKUP(X21,'측정 관리'!$A$5:$A$204,'측정 관리'!$K$5:$K$204,"",0)}
A22: 15 | B22: Creative Crypto | C22: @CreativeCrypto | D22: P4 | E22: 17100 | F22: 10 | L22: 2 | M22: 417 | N22: 440 | O22: 0.025730994 | Q22: https://www.youtube.com/@CreativeCrypto | X22: WB-C058 | Y22: WB-K124 | Z22: {=_xlfn.XLOOKUP(X22,'측정 관리'!$A$5:$A$204,'측정 관리'!$K$5:$K$204,"",0)}
A23: 16 | B23: Whocares ML | C23: @whocaresml6684 | D23: 비활동 | E23: 474000 | F23: 195 | P23: 최근 롱폼 195일 전 | Q23: https://www.youtube.com/@whocaresml6684 | X23: WB-C059 | Y23: WB-K129 | Z23: {=_xlfn.XLOOKUP(X23,'측정 관리'!$A$5:$A$204,'측정 관리'!$K$5:$K$204,"",0)}
A24: 17 | B24: Rekt Capital | C24: @RektCapital | D24: 비활동 | E24: 114000 | F24: 45 | P24: 최근 롱폼 45일 전 | Q24: https://www.youtube.com/@RektCapital | X24: WB-C060 | Y24: WB-K090 | Z24: {=_xlfn.XLOOKUP(X24,'측정 관리'!$A$5:$A$204,'측정 관리'!$K$5:$K$204,"",0)}
A25: 18 | B25: OnlineBoss-Crypto | C25: @onlineboss-crypto | D25: 비활동 | E25: 69800 | F25: 165 | P25: 최근 롱폼 165일 전 | Q25: https://www.youtube.com/@onlineboss-crypto | X25: WB-C061 | Y25: WB-K127 | Z25: {=_xlfn.XLOOKUP(X25,'측정 관리'!$A$5:$A$204,'측정 관리'!$K$5:$K$204,"",0)}
A26: 19 | B26: TraderXO | C26: @TraderXO | D26: 비활동 | E26: 61200 | F26: 75 | P26: 최근 롱폼 75일 전 | Q26: https://www.youtube.com/@TraderXO | X26: WB-C062 | Y26: WB-K083 | Z26: {=_xlfn.XLOOKUP(X26,'측정 관리'!$A$5:$A$204,'측정 관리'!$K$5:$K$204,"",0)}
A27: 20 | B27: BossJapz Review | C27: @bossjapzreview | D27: 비활동 | E27: 58900 | F27: 225 | P27: 최근 롱폼 225일 전 | Q27: https://www.youtube.com/@bossjapzreview | X27: WB-C063 | Y27: WB-K130 | Z27: {=_xlfn.XLOOKUP(X27,'측정 관리'!$A$5:$A$204,'측정 관리'!$K$5:$K$204,"",0)}
A28: 21 | B28: CryptoEliz | C28: @CryptoEliz | D28: 비활동 | E28: 28100 | F28: 365 | P28: 최근 롱폼 365일 전 | Q28: https://www.youtube.com/@CryptoEliz | X28: WB-C064 | Y28: WB-K084 | Z28: {=_xlfn.XLOOKUP(X28,'측정 관리'!$A$5:$A$204,'측정 관리'!$K$5:$K$204,"",0)}
A29: 22 | B29: Cold Blooded Shiller | C29: @ColdBloodedShiller | D29: 비활동 | E29: 14900 | F29: 365 | P29: 최근 롱폼 365일 전 | Q29: https://www.youtube.com/@ColdBloodedShiller | X29: WB-C065 | Y29: WB-K092 | Z29: {=_xlfn.XLOOKUP(X29,'측정 관리'!$A$5:$A$204,'측정 관리'!$K$5:$K$204,"",0)}
A30: 23 | B30: Inmortal | C30: c/inmortalcrypto | D30: 비활동 | E30: 11800 | P30: 영상 없음 | Q30: https://www.youtube.com/c/inmortalcrypto | X30: WB-C066 | Y30: WB-K095 | Z30: {=_xlfn.XLOOKUP(X30,'측정 관리'!$A$5:$A$204,'측정 관리'!$K$5:$K$204,"",0)}
A31: 24 | B31: AltcoinSherpa | C31: c/Altcoinsherpa | D31: 비활동 | E31: 11600 | F31: 195 | P31: 최근 롱폼 195일 전 | Q31: https://www.youtube.com/c/Altcoinsherpa | X31: WB-C067 | Y31: WB-K104 | Z31: {=_xlfn.XLOOKUP(X31,'측정 관리'!$A$5:$A$204,'측정 관리'!$K$5:$K$204,"",0)}
A32: 25 | B32: Income Sharks | C32: @IncomeSharks | D32: 비활동 | E32: 8570 | F32: 285 | P32: 최근 롱폼 285일 전 | Q32: https://www.youtube.com/@IncomeSharks | X32: WB-C068 | Y32: WB-K082 | Z32: {=_xlfn.XLOOKUP(X32,'측정 관리'!$A$5:$A$204,'측정 관리'!$K$5:$K$204,"",0)}
A33: 26 | B33: Daan Crypto | C33: @daancrypto | D33: 비활동 | E33: 7150 | F33: 225 | P33: 최근 롱폼 225일 전 | Q33: https://www.youtube.com/@daancrypto | X33: WB-C069 | Y33: WB-K096 | Z33: {=_xlfn.XLOOKUP(X33,'측정 관리'!$A$5:$A$204,'측정 관리'!$K$5:$K$204,"",0)}

Sheet 글로벌 TG
A1: 글로벌 Telegram — 28개 채널
A2: ■ 퍼포먼스 = 30일 중앙 조회 P1 3,000+ · P2 1,500+ · P3 500+ · P4 500 미만 · 비활동 = 30일 3건 미만
A3: ■ TG 공개 채널은 반응 수가 없어 도달률(중앙 조회 ÷ 구독자)이 반응 지표 · 8%+면 구독자 참여가 살아있는 채널로 봄 [제안]
A4: ■ 비공개 4개는 웹 미리보기가 막혀 측정 불가
G6: 24시간 | I6: 7일 | L6: 30일
A7: 순위 | B7: 채널명 | C7: 채널 | D7: 퍼포먼스 | E7: 구독자 | F7: 마지막 글 | G7: 게시 | H7: 평균 조회 | I7: 게시 | J7: 평균 조회 | K7: 중앙 조회 | L7: 게시 | M7: 평균 조회 | N7: 중앙 조회 | O7: 도달률 | P7: 추세 (7d vs 30d) | Q7: 메모 | R7: 링크 | X7: 채널 ID | Y7: KOL ID | Z7: 측정 상태
A8: 1 | B8: cyclop | C8: cyclopalpha | D8: P2 | E8: 77200 | F8: 2026-09-25 | I8: 9 | J8: 2837 | K8: 2860 | L8: 9 | M8: 2837 | N8: 2860 | O8: 0.037046632 | P8: 0 | R8: https://t.me/cyclopalpha | X8: WB-C070 | Y8: WB-K100 | Z8: {=_xlfn.XLOOKUP(X8,'측정 관리'!$A$5:$A$204,'측정 관리'!$K$5:$K$204,"",0)}
A9: 2 | B9: Eric Cryptomans Journal | C9: Erics_Calls | D9: P2 | E9: 31300 | F9: 2026-09-25 | I9: 10 | J9: 4727 | K9: 2600 | L9: 105 | M9: 3058 | N9: 2710 | O9: 0.08658147 | P9: 0.54578156 | R9: https://t.me/Erics_Calls | X9: WB-C071 | Y9: WB-K101 | Z9: {=_xlfn.XLOOKUP(X9,'측정 관리'!$A$5:$A$204,'측정 관리'!$K$5:$K$204,"",0)}
A10: 3 | B10: Poseidon Kitchen | C10: poseidonkitchen | D10: P3 | E10: 11000 | F10: 2026-09-24 | I10: 15 | J10: 1128 | K10: 1070 | L10: 102 | M10: 1101 | N10: 1090 | O10: 0.099090909 | P10: 0.024523161 | R10: https://t.me/poseidonkitchen | X10: WB-C072 | Y10: WB-K085 | Z10: {=_xlfn.XLOOKUP(X10,'측정 관리'!$A$5:$A$204,'측정 관리'!$K$5:$K$204,"",0)}
A11: 4 | B11: winkle. | C11: w1nklerr | D11: P3 | E11: 7940 | F11: 2026-09-08 | L11: 4 | M11: 659 | N11: 675 | O11: 0.085012594 | R11: https://t.me/w1nklerr | X11: WB-C073 | Y11: WB-K115 | Z11: {=_xlfn.XLOOKUP(X11,'측정 관리'!$A$5:$A$204,'측정 관리'!$K$5:$K$204,"",0)}
A12: 5 | B12: Jaynecrypto | C12: jaynecrypto | D12: P4 | E12: 5210 | F12: 2026-09-27 | G12: 3 | H12: 238 | I12: 13 | J12: 381 | K12: 400 | L12: 100 | M12: 445 | N12: 451 | O12: 0.086564299 | P12: -0.14382022 | R12: https://t.me/jaynecrypto | X12: WB-C074 | Y12: WB-K107 | Z12: {=_xlfn.XLOOKUP(X12,'측정 관리'!$A$5:$A$204,'측정 관리'!$K$5:$K$204,"",0)}
A13: 6 | B13: 0xFrogify | C13: frogify0x | D13: P4 | E13: 8000 | F13: 2026-09-27 | G13: 1 | H13: 53 | I13: 6 | J13: 134 | K13: 162 | L13: 32 | M13: 177 | N13: 179 | O13: 0.022375 | P13: -0.24293785 | R13: https://t.me/frogify0x | X13: WB-C075 | Y13: WB-K125 | Z13: {=_xlfn.XLOOKUP(X13,'측정 관리'!$A$5:$A$204,'측정 관리'!$K$5:$K$204,"",0)}
A14: 7 | B14: Evan NICHE | C14: EvanNiche | D14: P4 | E14: 549 | F14: 2026-09-17 | L14: 3 | M14: 43 | N14: 41 | O14: 0.074681239 | R14: https://t.me/EvanNiche | X14: WB-C076 | Y14: WB-K108 | Z14: {=_xlfn.XLOOKUP(X14,'측정 관리'!$A$5:$A$204,'측정 관리'!$K$5:$K$204,"",0)}
A15: 8 | B15: DeFi Oracle - Gems | C15: DeFiOracleGems | D15: 비활동 | E15: 1810 | F15: 2026-09-09 | L15: 1 | M15: 1730 | N15: 1730 | O15: 0.9558011 | Q15: 마지막 글 2026-09-09 | R15: https://t.me/DeFiOracleGems | X15: WB-C077 | Y15: WB-K106 | Z15: {=_xlfn.XLOOKUP(X15,'측정 관리'!$A$5:$A$204,'측정 관리'!$K$5:$K$204,"",0)}
A16: 9 | B16: 0xchromium | C16: xchromium | D16: 비활동 | E16: 2480 | F16: 2026-09-16 | L16: 2 | M16: 138 | N16: 183 | O16: 0.073790323 | Q16: 마지막 글 2026-09-16 | R16: https://t.me/xchromium | X16: WB-C078 | Y16: WB-K120 | Z16: {=_xlfn.XLOOKUP(X16,'측정 관리'!$A$5:$A$204,'측정 관리'!$K$5:$K$204,"",0)}
A17: 10 | B17: Woody in crypto | C17: woody_research | D17: 비활동 | E17: 2010 | F17: 2026-09-16 | L17: 2 | M17: 125 | N17: 156 | O17: 0.07761194 | Q17: 마지막 글 2026-09-16 | R17: https://t.me/woody_research | X17: WB-C079 | Y17: WB-K119 | Z17: {=_xlfn.XLOOKUP(X17,'측정 관리'!$A$5:$A$204,'측정 관리'!$K$5:$K$204,"",0)}
A18: 11 | B18: Kepochnik Alpha | C18: kepochnikalpha | D18: 비활동 | E18: 7820 | F18: 2026-09-25 | I18: 1 | J18: 147 | K18: 147 | L18: 1 | M18: 147 | N18: 147 | O18: 0.018797954 | P18: 0 | Q18: 마지막 글 2026-09-25 | R18: https://t.me/kepochnikalpha | X18: WB-C080 | Y18: WB-K128 | Z18: {=_xlfn.XLOOKUP(X18,'측정 관리'!$A$5:$A$204,'측정 관리'!$K$5:$K$204,"",0)}
A19: 12 | B19: Nazza Crypto | C19: nazzacrypto | D19: 비활동 | E19: 156 | F19: 2026-09-23 | I19: 1 | J19: 24 | K19: 24 | L19: 2 | M19: 50 | N19: 76 | O19: 0.48717949 | P19: -0.52 | Q19: 마지막 글 2026-09-23 | R19: https://t.me/nazzacrypto | X19: WB-C081 | Y19: WB-K114 | Z19: {=_xlfn.XLOOKUP(X19,'측정 관리'!$A$5:$A$204,'측정 관리'!$K$5:$K$204,"",0)}
A20: 13 | B20: Klarck Alpha | C20: klarck_alpha | D20: 비활동 | E20: 36800 | F20: 2026-04-07 | Q20: 마지막 글 2026-04-07 | R20: https://t.me/klarck_alpha | X20: WB-C082 | Y20: WB-K102 | Z20: {=_xlfn.XLOOKUP(X20,'측정 관리'!$A$5:$A$204,'측정 관리'!$K$5:$K$204,"",0)}
A21: 14 | B21: Chad Crypto | C21: Chad_Crypto | D21: 비활동 | E21: 16000 | F21: 2026-07-30 | Q21: 마지막 글 2026-07-30 | R21: https://t.me/Chad_Crypto | X21: WB-C083 | Y21: WB-K116 | Z21: {=_xlfn.XLOOKUP(X21,'측정 관리'!$A$5:$A$204,'측정 관리'!$K$5:$K$204,"",0)}
A22: 15 | B22: Money Land | C22: deronin_alpha | D22: 비활동 | E22: 11600 | F22: 2026-08-11 | Q22: 마지막 글 2026-08-11 | R22: https://t.me/deronin_alpha | X22: WB-C084 | Y22: WB-K091 | Z22: {=_xlfn.XLOOKUP(X22,'측정 관리'!$A$5:$A$204,'측정 관리'!$K$5:$K$204,"",0)}
A23: 16 | B23: Plutos | C23: plutos_research | D23: 비활동 | E23: 9340 | F23: 2025-11-03 | Q23: 마지막 글 2025-11-03 | R23: https://t.me/plutos_research | X23: WB-C085 | Y23: WB-K121 | Z23: {=_xlfn.XLOOKUP(X23,'측정 관리'!$A$5:$A$204,'측정 관리'!$K$5:$K$204,"",0)}
A24: 17 | B24: Kitchen of Sully | C24: kitchenofsully | D24: 비활동 | E24: 8310 | F24: 2026-07-31 | Q24: 마지막 글 2026-07-31 | R24: https://t.me/kitchenofsully | X24: WB-C086 | Y24: WB-K105 | Z24: {=_xlfn.XLOOKUP(X24,'측정 관리'!$A$5:$A$204,'측정 관리'!$K$5:$K$204,"",0)}
A25: 18 | B25: Fried Dev | C25: FriedDev | D25: 비활동 | E25: 3940 | F25: 2026-07-10 | Q25: 마지막 글 2026-07-10 | R25: https://t.me/FriedDev | X25: WB-C087 | Y25: WB-K131 | Z25: {=_xlfn.XLOOKUP(X25,'측정 관리'!$A$5:$A$204,'측정 관리'!$K$5:$K$204,"",0)}
A26: 19 | B26: CryptoDarya | C26: Daryacrypto | D26: 비활동 | E26: 3870 | F26: 2025-06-25 | Q26: 마지막 글 2025-06-25 | R26: https://t.me/Daryacrypto | X26: WB-C088 | Y26: WB-K132 | Z26: {=_xlfn.XLOOKUP(X26,'측정 관리'!$A$5:$A$204,'측정 관리'!$K$5:$K$204,"",0)}
A27: 20 | B27: ZEU$ | C27: zeuusss_01 | D27: 비활동 | E27: 2450 | F27: 2026-07-08 | Q27: 마지막 글 2026-07-08 | R27: https://t.me/zeuusss_01 | X27: WB-C089 | Y27: WB-K117 | Z27: {=_xlfn.XLOOKUP(X27,'측정 관리'!$A$5:$A$204,'측정 관리'!$K$5:$K$204,"",0)}
A28: 21 | B28: 0xDepressionn | C28: xDepressionn | D28: 비활동 | E28: 2150 | F28: 2026-08-02 | Q28: 마지막 글 2026-08-02 | R28: https://t.me/xDepressionn | X28: WB-C090 | Y28: WB-K118 | Z28: {=_xlfn.XLOOKUP(X28,'측정 관리'!$A$5:$A$204,'측정 관리'!$K$5:$K$204,"",0)}
A29: 22 | B29: Gatsuki Trust Fund | C29: gatsuki_fund | D29: 비활동 | E29: 429 | F29: 2025-12-09 | Q29: 마지막 글 2025-12-09 | R29: https://t.me/gatsuki_fund | X29: WB-C091 | Y29: WB-K123 | Z29: {=_xlfn.XLOOKUP(X29,'측정 관리'!$A$5:$A$204,'측정 관리'!$K$5:$K$204,"",0)}
A30: 23 | B30: Trader HuB | C30: BullX192 | D30: 비활동 | E30: 175 | F30: 2025-10-11 | Q30: 마지막 글 2025-10-11 | R30: https://t.me/BullX192 | X30: WB-C092 | Y30: WB-K135 | Z30: {=_xlfn.XLOOKUP(X30,'측정 관리'!$A$5:$A$204,'측정 관리'!$K$5:$K$204,"",0)}
A31: 24 | B31: NoName gateway | C31: whalenoname | D31: 비활동 | E31: 73 | F31: 2025-09-26 | Q31: 마지막 글 2025-09-26 | R31: https://t.me/whalenoname | X31: WB-C093 | Y31: WB-K103 | Z31: {=_xlfn.XLOOKUP(X31,'측정 관리'!$A$5:$A$204,'측정 관리'!$K$5:$K$204,"",0)}
A32: 25 | B32: OfficialSabiigal | C32: OfficialSabiigal | D32: 미측정 | Q32: 웹 미리보기 비공개 (구독자·조회 확인 불가) | R32: https://t.me/OfficialSabiigal | X32: WB-C094 | Y32: WB-K086 | Z32: {=_xlfn.XLOOKUP(X32,'측정 관리'!$A$5:$A$204,'측정 관리'!$K$5:$K$204,"",0)}
A33: 26 | B33: certifiedchads | C33: certifiedchads | D33: 미측정 | Q33: 웹 미리보기 비공개 (구독자·조회 확인 불가) | R33: https://t.me/certifiedchads | X33: WB-C095 | Y33: WB-K126 | Z33: {=_xlfn.XLOOKUP(X33,'측정 관리'!$A$5:$A$204,'측정 관리'!$K$5:$K$204,"",0)}
A34: 27 | B34: halosden | C34: halosden | D34: 미측정 | Q34: 웹 미리보기 비공개 (구독자·조회 확인 불가) | R34: https://t.me/halosden | X34: WB-C096 | Y34: WB-K098 | Z34: {=_xlfn.XLOOKUP(X34,'측정 관리'!$A$5:$A$204,'측정 관리'!$K$5:$K$204,"",0)}
A35: 28 | B35: DeFiImmortal | C35: DeFiImmortal | D35: 미측정 | Q35: 웹 미리보기 비공개 (구독자·조회 확인 불가) | R35: https://t.me/DeFiImmortal | X35: WB-C097 | Y35: WB-K134 | Z35: {=_xlfn.XLOOKUP(X35,'측정 관리'!$A$5:$A$204,'측정 관리'!$K$5:$K$204,"",0)} -> 조회 불가

Sheet 한국 TG
A1: 한국 Telegram — 67개 채널
A2: ■ 퍼포먼스 = 30일 중앙 조회 P1 3,000+ · P2 1,500+ · P3 500+ · P4 500 미만 · 비활동 = 30일 3건 미만
A3: ■ TG 공개 채널은 반응 수가 없어 도달률(중앙 조회 ÷ 구독자)이 반응 지표 · 8%+면 구독자 참여가 살아있는 채널로 봄 [제안]
A4: ■ '8/25 시트 평균' = 원본 시트 기재값 (실측과 비교용)
G6: 24시간 | I6: 7일 | K6: 30일
A7: 순위 | B7: KOL | C7: 채널 | D7: 퍼포먼스 | E7: 구독자 | F7: 마지막 글 | G7: 게시 | H7: 평균 조회 | I7: 게시 | J7: 평균 조회 | K7: 게시 | L7: 평균 조회 | M7: 중앙 조회 | N7: 도달률 | O7: 추세 (7d vs 30d) | P7: 8/25 시트 평균 | Q7: 메모 | R7: 링크 | X7: 채널 ID | Y7: KOL ID | Z7: 측정 상태
A8: 1 | B8: CoinFluencer P2E&NFT | C8: hjwnews | D8: P1 | E8: 6630 | F8: 2026-09-17 | K8: 4 | L8: 2255 | M8: 3290 | N8: 0.49622926 | P8: 1942 | Q8: 저빈도 (마지막 9/17) | R8: https://t.me/hjwnews | X8: WB-C098 | Y8: WB-K002 | Z8: {=_xlfn.XLOOKUP(X8,'측정 관리'!$A$5:$A$204,'측정 관리'!$K$5:$K$204,"",0)}
A9: 2 | B9: 코인하는 해달 | C9: seaotterbtc | D9: P1 | E9: 30100 | F9: 2026-09-28 | G9: 4 | H9: 2623 | I9: 24 | J9: 5280 | K9: 133 | L9: 6033 | M9: 5000 | N9: 0.16611296 | O9: -0.12481353 | P9: 3947 | Q9: 한국 1위 | R9: https://t.me/seaotterbtc | X9: WB-C099 | Y9: WB-K001 | Z9: {=_xlfn.XLOOKUP(X9,'측정 관리'!$A$5:$A$204,'측정 관리'!$K$5:$K$204,"",0)}
A10: 3 | B10: 취미생활방 | C10: enjoymyhobby | D10: P1 | E10: 49700 | F10: 2026-09-28 | G10: 19 | H10: 1705 | I10: 93 | J10: 2728 | K10: 431 | L10: 3065 | M10: 3010 | N10: 0.06056338 | O10: -0.10995106 | P10: 3006 | Q10: 하루 14건 → 고정 필요 | R10: https://t.me/enjoymyhobby | X10: WB-C100 | Y10: WB-K003 | Z10: {=_xlfn.XLOOKUP(X10,'측정 관리'!$A$5:$A$204,'측정 관리'!$K$5:$K$204,"",0)}
A11: 4 | B11: jobless | C11: Jobless_investor | D11: P2 | E11: 6050 | F11: 2026-09-03 | K11: 6 | L11: 1540 | M11: 1750 | N11: 0.2892562 | P11: 589 | Q11: 저빈도 (마지막 9/3) | R11: https://t.me/Jobless_investor | X11: WB-C101 | Y11: WB-K011 | Z11: {=_xlfn.XLOOKUP(X11,'측정 관리'!$A$5:$A$204,'측정 관리'!$K$5:$K$204,"",0)}
A12: 5 | B12: 크립토마카세 | C12: cryptomacase | D12: P2 | E12: 11000 | F12: 2026-09-28 | G12: 2 | H12: 1604 | I12: 6 | J12: 1925 | K12: 25 | L12: 2052 | M12: 1830 | N12: 0.16636364 | O12: -0.061890838 | P12: 786 | Q12: 저빈도 · 고효율 | R12: https://t.me/cryptomacase | X12: WB-C102 | Y12: WB-K010 | Z12: {=_xlfn.XLOOKUP(X12,'측정 관리'!$A$5:$A$204,'측정 관리'!$K$5:$K$204,"",0)}
A13: 6 | B13: 라오니 | C13: Raoni1 | D13: P2 | E13: 14900 | F13: 2026-09-28 | G13: 11 | H13: 1035 | I13: 75 | J13: 1989 | K13: 329 | L13: 2293 | M13: 2200 | N13: 0.14765101 | O13: -0.13257741 | P13: 1050 | R13: https://t.me/Raoni1 | X13: WB-C103 | Y13: WB-K008 | Z13: {=_xlfn.XLOOKUP(X13,'측정 관리'!$A$5:$A$204,'측정 관리'!$K$5:$K$204,"",0)}
A14: 7 | B14: Crypto Judy | C14: lovejudylee | D14: P2 | E14: 17400 | F14: 2026-09-28 | G14: 23 | H14: 1873 | I14: 282 | J14: 2331 | K14: 839 | L14: 2416 | M14: 2210 | N14: 0.12701149 | O14: -0.035182119 | P14: 1085 | Q14: 하루 28건+ · 30일 일부만 수집 | R14: https://t.me/lovejudylee | X14: WB-C104 | Y14: WB-K007 | Z14: {=_xlfn.XLOOKUP(X14,'측정 관리'!$A$5:$A$204,'측정 관리'!$K$5:$K$204,"",0)} -> 일부 수집
A15: 8 | B15: 졸업준비위원회 | C15: officialunivercityofcrypto | D15: P2 | E15: 23000 | F15: 2026-09-28 | G15: 5 | H15: 1455 | I15: 35 | J15: 2824 | K15: 157 | L15: 3193 | M15: 2830 | N15: 0.12304348 | O15: -0.1155653 | P15: 1753 | R15: https://t.me/officialunivercityofcrypto | X15: WB-C105 | Y15: WB-K006 | Z15: {=_xlfn.XLOOKUP(X15,'측정 관리'!$A$5:$A$204,'측정 관리'!$K$5:$K$204,"",0)}
A16: 9 | B16: 킬베로스 | C16: killberosDAO | D16: P2 | E16: 15100 | F16: 2026-09-28 | G16: 4 | H16: 317 | I16: 14 | J16: 1034 | K16: 38 | L16: 1659 | M16: 1650 | N16: 0.10927152 | O16: -0.37673297 | P16: 2231 | Q16: 8/25 대비 하락 | R16: https://t.me/killberosDAO | X16: WB-C106 | Y16: WB-K014 | Z16: {=_xlfn.XLOOKUP(X16,'측정 관리'!$A$5:$A$204,'측정 관리'!$K$5:$K$204,"",0)}
A17: 10 | B17: 신기돈 | C17: tlsrltnf | D17: P2 | E17: 22900 | F17: 2026-09-28 | G17: 2 | H17: 756 | I17: 38 | J17: 1985 | K17: 137 | L17: 1972 | M17: 1840 | N17: 0.080349345 | O17: 0.0065922921 | P17: 755 | R17: https://t.me/tlsrltnf | X17: WB-C107 | Y17: WB-K009 | Z17: {=_xlfn.XLOOKUP(X17,'측정 관리'!$A$5:$A$204,'측정 관리'!$K$5:$K$204,"",0)}
A18: 11 | B18: 마샬 | C18: marshallog | D18: P2 | E18: 21700 | F18: 2026-09-28 | G18: 3 | H18: 446 | I18: 28 | J18: 1537 | K18: 154 | L18: 1848 | M18: 1730 | N18: 0.079723502 | O18: -0.16829004 | P18: 1244 | R18: https://t.me/marshallog | X18: WB-C108 | Y18: WB-K012 | Z18: {=_xlfn.XLOOKUP(X18,'측정 관리'!$A$5:$A$204,'측정 관리'!$K$5:$K$204,"",0)}
A19: 12 | B19: 잼민123 | C19: mujammin123 | D19: P2 | E19: 26200 | F19: 2026-09-28 | G19: 24 | H19: 1126 | I19: 135 | J19: 1557 | K19: 430 | L19: 1764 | M19: 1690 | N19: 0.064503817 | O19: -0.11734694 | P19: 1158 | R19: https://t.me/mujammin123 | X19: WB-C109 | Y19: WB-K013 | Z19: {=_xlfn.XLOOKUP(X19,'측정 관리'!$A$5:$A$204,'측정 관리'!$K$5:$K$204,"",0)}
A20: 13 | B20: A라는 사람 | C20: aispersons | D20: P3 | E20: 3920 | F20: 2026-09-27 | G20: 1 | H20: 195 | I20: 5 | J20: 378 | K20: 18 | L20: 654 | M20: 707 | N20: 0.18035714 | O20: -0.42201835 | P20: 1807 | Q20: 8/25 대비 하락 | R20: https://t.me/aispersons | X20: WB-C110 | Y20: WB-K029 | Z20: {=_xlfn.XLOOKUP(X20,'측정 관리'!$A$5:$A$204,'측정 관리'!$K$5:$K$204,"",0)}
A21: 14 | B21: Road To Rome | C21: HeadingtoRome | D21: P3 | E21: 4840 | F21: 2026-09-27 | G21: 1 | H21: 197 | I21: 2 | J21: 388 | K21: 6 | L21: 918 | M21: 718 | N21: 0.14834711 | O21: -0.57734205 | P21: 154 | R21: https://t.me/HeadingtoRome | X21: WB-C111 | Y21: WB-K028 | Z21: {=_xlfn.XLOOKUP(X21,'측정 관리'!$A$5:$A$204,'측정 관리'!$K$5:$K$204,"",0)}
A22: 15 | B22: Trader Hyun's channel | C22: TraderHyun | D22: P3 | E22: 6530 | F22: 2026-09-24 | I22: 2 | J22: 412 | K22: 14 | L22: 814 | M22: 880 | N22: 0.13476263 | O22: -0.49385749 | P22: 556 | R22: https://t.me/TraderHyun | X22: WB-C112 | Y22: WB-K023 | Z22: {=_xlfn.XLOOKUP(X22,'측정 관리'!$A$5:$A$204,'측정 관리'!$K$5:$K$204,"",0)}
A23: 16 | B23: T.A Crypto | C23: yul_papa | D23: P3 | E23: 8060 | F23: 2026-09-28 | G23: 16 | H23: 797 | I23: 51 | J23: 972 | K23: 256 | L23: 1033 | M23: 1010 | N23: 0.12531017 | O23: -0.059051307 | P23: 1658 | R23: https://t.me/yul_papa | X23: WB-C113 | Y23: WB-K019 | Z23: {=_xlfn.XLOOKUP(X23,'측정 관리'!$A$5:$A$204,'측정 관리'!$K$5:$K$204,"",0)}
A24: 17 | B24: 알파스쿨 | C24: AlphaSchool77 | D24: P3 | E24: 10800 | F24: 2026-09-27 | G24: 1 | H24: 776 | I24: 4 | J24: 965 | K24: 101 | L24: 1223 | M24: 1300 | N24: 0.12037037 | O24: -0.21095666 | P24: 506 | R24: https://t.me/AlphaSchool77 | X24: WB-C114 | Y24: WB-K018 | Z24: {=_xlfn.XLOOKUP(X24,'측정 관리'!$A$5:$A$204,'측정 관리'!$K$5:$K$204,"",0)}
A25: 18 | B25: 코인위키 | C25: CoinWiki_MMWW | D25: P3 | E25: 5910 | F25: 2026-09-28 | G25: 5 | H25: 477 | I25: 25 | J25: 556 | K25: 82 | L25: 626 | M25: 615 | N25: 0.10406091 | O25: -0.11182109 | P25: 423 | R25: https://t.me/CoinWiki_MMWW | X25: WB-C115 | Y25: WB-K033 | Z25: {=_xlfn.XLOOKUP(X25,'측정 관리'!$A$5:$A$204,'측정 관리'!$K$5:$K$204,"",0)}
A26: 19 | B26: 21M 포밍 | C26: vc_21m | D26: P3 | E26: 5540 | F26: 2026-09-22 | I26: 2 | J26: 411 | K26: 8 | L26: 556 | M26: 567 | N26: 0.10234657 | O26: -0.26079137 | P26: 2093 | Q26: 8/25 대비 하락 | R26: https://t.me/vc_21m | X26: WB-C116 | Y26: WB-K034 | Z26: {=_xlfn.XLOOKUP(X26,'측정 관리'!$A$5:$A$204,'측정 관리'!$K$5:$K$204,"",0)}
A27: 20 | B27: 바나나우유 일기장 | C27: Bananamilkrich | D27: P3 | E27: 8760 | F27: 2026-09-24 | I27: 1 | J27: 323 | K27: 10 | L27: 928 | M27: 892 | N27: 0.10182648 | O27: -0.65193966 | P27: 985 | R27: https://t.me/Bananamilkrich | X27: WB-C117 | Y27: WB-K022 | Z27: {=_xlfn.XLOOKUP(X27,'측정 관리'!$A$5:$A$204,'측정 관리'!$K$5:$K$204,"",0)}
A28: 21 | B28: 크립토폴유 | C28: cryptoforu12 | D28: P3 | E28: 7620 | F28: 2026-09-27 | G28: 2 | H28: 601 | I28: 10 | J28: 999 | K28: 35 | L28: 962 | M28: 766 | N28: 0.10052493 | O28: 0.038461538 | P28: 573 | R28: https://t.me/cryptoforu12 | X28: WB-C118 | Y28: WB-K027 | Z28: {=_xlfn.XLOOKUP(X28,'측정 관리'!$A$5:$A$204,'측정 관리'!$K$5:$K$204,"",0)}
A29: 22 | B29: 개인적인 DYOR | C29: LEEHEESANGDYOR | D29: P3 | E29: 9730 | F29: 2026-09-28 | G29: 1 | H29: 403 | I29: 17 | J29: 899 | K29: 67 | L29: 1251 | M29: 976 | N29: 0.10030832 | O29: -0.2813749 | P29: 726 | R29: https://t.me/LEEHEESANGDYOR | X29: WB-C119 | Y29: WB-K021 | Z29: {=_xlfn.XLOOKUP(X29,'측정 관리'!$A$5:$A$204,'측정 관리'!$K$5:$K$204,"",0)}
A30: 23 | B30: BMT | C30: BMTube | D30: P3 | E30: 13700 | F30: 2026-09-28 | G30: 4 | H30: 629 | I30: 39 | J30: 1869 | K30: 84 | L30: 1622 | M30: 1200 | N30: 0.087591241 | O30: 0.15228113 | P30: 1248 | R30: https://t.me/BMTube | X30: WB-C120 | Y30: WB-K020 | Z30: {=_xlfn.XLOOKUP(X30,'측정 관리'!$A$5:$A$204,'측정 관리'!$K$5:$K$204,"",0)}
A31: 24 | B31: BQ 비큐 | C31: BQTelegram | D31: P3 | E31: 9600 | F31: 2026-09-27 | G31: 1 | H31: 281 | I31: 12 | J31: 519 | K31: 98 | L31: 1000 | M31: 821 | N31: 0.085520833 | O31: -0.481 | P31: 487 | R31: https://t.me/BQTelegram | X31: WB-C121 | Y31: WB-K025 | Z31: {=_xlfn.XLOOKUP(X31,'측정 관리'!$A$5:$A$204,'측정 관리'!$K$5:$K$204,"",0)}
A32: 25 | B32: 나백이의코인라이프 | C32: ysytop2 | D32: P3 | E32: 9360 | F32: 2026-09-27 | G32: 5 | H32: 701 | I32: 51 | J32: 954 | K32: 305 | L32: 891 | M32: 720 | N32: 0.076923077 | O32: 0.070707071 | P32: 366 | R32: https://t.me/ysytop2 | X32: WB-C122 | Y32: WB-K015 | Z32: {=_xlfn.XLOOKUP(X32,'측정 관리'!$A$5:$A$204,'측정 관리'!$K$5:$K$204,"",0)}
A33: 26 | B33: 코백남 | C33: cobacknamannounce | D33: P3 | E33: 18000 | F33: 2026-09-28 | G33: 12 | H33: 534 | I33: 78 | J33: 1168 | K33: 270 | L33: 1424 | M33: 1300 | N33: 0.072222222 | O33: -0.17977528 | P33: 465 | Q33: 시트 팔로워는 TG+YT 합산으로 보임 | R33: https://t.me/cobacknamannounce | X33: WB-C123 | Y33: WB-K005 | Z33: {=_xlfn.XLOOKUP(X33,'측정 관리'!$A$5:$A$204,'측정 관리'!$K$5:$K$204,"",0)}
A34: 27 | B34: 큐브의 유기농 크립토 쌀농장 | C34: cubestudy1557 | D34: P3 | E34: 9320 | F34: 2026-09-27 | I34: 12 | J34: 498 | K34: 38 | L34: 668 | M34: 624 | N34: 0.06695279 | O34: -0.25449102 | P34: 414 | R34: https://t.me/cubestudy1557 | X34: WB-C124 | Y34: WB-K031 | Z34: {=_xlfn.XLOOKUP(X34,'측정 관리'!$A$5:$A$204,'측정 관리'!$K$5:$K$204,"",0)}
A35: 28 | B35: 코인소년 | C35: coinboys | D35: P3 | E35: 15600 | F35: 2026-09-28 | G35: 15 | H35: 1006 | I35: 163 | J35: 1079 | K35: 616 | L35: 1197 | M35: 1030 | N35: 0.066025641 | O35: -0.098579783 | P35: 796 | Q35: 시트 팔로워는 TG+YT 합산으로 보임 | R35: https://t.me/coinboys | X35: WB-C125 | Y35: WB-K016 | Z35: {=_xlfn.XLOOKUP(X35,'측정 관리'!$A$5:$A$204,'측정 관리'!$K$5:$K$204,"",0)}
A36: 29 | B36: 요블이네 | C36: yobeullyANN | D36: P3 | E36: 22700 | F36: 2026-09-28 | G36: 12 | H36: 694 | I36: 45 | J36: 1294 | K36: 185 | L36: 1670 | M36: 1480 | N36: 0.065198238 | O36: -0.2251497 | P36: 851 | R36: https://t.me/yobeullyANN | X36: WB-C126 | Y36: WB-K017 | Z36: {=_xlfn.XLOOKUP(X36,'측정 관리'!$A$5:$A$204,'측정 관리'!$K$5:$K$204,"",0)}
A37: 30 | B37: 꿀찾는 양말 | C37: Honeyofwhitesocks_2 | D37: P3 | E37: 11400 | F37: 2026-09-28 | G37: 8 | H37: 386 | I37: 169 | J37: 642 | K37: 460 | L37: 683 | M37: 628 | N37: 0.055087719 | O37: -0.060029283 | P37: 312 | R37: https://t.me/Honeyofwhitesocks_2 | X37: WB-C127 | Y37: WB-K030 | Z37: {=_xlfn.XLOOKUP(X37,'측정 관리'!$A$5:$A$204,'측정 관리'!$K$5:$K$204,"",0)}
A38: 31 | B38: 젠티 | C38: Jenti_DeFi | D38: P3 | E38: 14400 | F38: 2026-09-27 | G38: 3 | H38: 446 | I38: 20 | J38: 586 | K38: 94 | L38: 732 | M38: 772 | N38: 0.053611111 | O38: -0.19945355 | P38: 856 | R38: https://t.me/Jenti_DeFi | X38: WB-C128 | Y38: WB-K026 | Z38: {=_xlfn.XLOOKUP(X38,'측정 관리'!$A$5:$A$204,'측정 관리'!$K$5:$K$204,"",0)}
A39: 32 | B39: 크립토스쿨 다오 | C39: CRYPTOSCH00L | D39: P3 | E39: 12600 | F39: 2026-09-28 | G39: 4 | H39: 229 | I39: 44 | J39: 459 | K39: 191 | L39: 530 | M39: 528 | N39: 0.041904762 | O39: -0.13396226 | P39: 265 | R39: https://t.me/CRYPTOSCH00L | X39: WB-C129 | Y39: WB-K035 | Z39: {=_xlfn.XLOOKUP(X39,'측정 관리'!$A$5:$A$204,'측정 관리'!$K$5:$K$204,"",0)}
A40: 33 | B40: 에어드랍코리아 | C40: airdrop_kor | D40: P3 | E40: 21900 | F40: 2026-09-28 | G40: 5 | H40: 360 | I40: 28 | J40: 779 | K40: 131 | L40: 959 | M40: 844 | N40: 0.038538813 | O40: -0.18769552 | P40: 756 | Q40: 에어드랍 키워드 | R40: https://t.me/airdrop_kor | X40: WB-C130 | Y40: WB-K024 | Z40: {=_xlfn.XLOOKUP(X40,'측정 관리'!$A$5:$A$204,'측정 관리'!$K$5:$K$204,"",0)}
A41: 34 | B41: 코인맵핵 | C41: centurywhale | D41: P3 | E41: 16700 | F41: 2026-09-28 | G41: 8 | H41: 221 | I41: 32 | J41: 451 | K41: 76 | L41: 625 | M41: 617 | N41: 0.036946108 | O41: -0.2784 | P41: 617 | R41: https://t.me/centurywhale | X41: WB-C131 | Y41: WB-K032 | Z41: {=_xlfn.XLOOKUP(X41,'측정 관리'!$A$5:$A$204,'측정 관리'!$K$5:$K$204,"",0)}
A42: 35 | B42: 농사꾼 돈벌레 | C42: donbug8282 | D42: P4 | E42: 92 | F42: 2026-09-27 | G42: 1 | H42: 12 | I42: 14 | J42: 15 | K42: 105 | L42: 21 | M42: 21 | N42: 0.22826087 | O42: -0.28571429 | P42: 8 | R42: https://t.me/donbug8282 | X42: WB-C132 | Y42: WB-K059 | Z42: {=_xlfn.XLOOKUP(X42,'측정 관리'!$A$5:$A$204,'측정 관리'!$K$5:$K$204,"",0)}
A43: 36 | B43: 투자하는 30대 직장인정보방 | C43: naverblog30 | D43: P4 | E43: 1300 | F43: 2026-09-27 | G43: 1 | H43: 42 | I43: 1 | J43: 42 | K43: 7 | L43: 673 | M43: 166 | N43: 0.12769231 | O43: -0.93759287 | P43: 143 | Q43: 평균 왜곡 | R43: https://t.me/naverblog30 | X43: WB-C133 | Y43: WB-K053 | Z43: {=_xlfn.XLOOKUP(X43,'측정 관리'!$A$5:$A$204,'측정 관리'!$K$5:$K$204,"",0)}
A44: 37 | B44: 생계형 에어드랍 | C44: sangp_airdrop | D44: P4 | E44: 1430 | F44: 2026-09-27 | G44: 1 | H44: 54 | I44: 3 | J44: 73 | K44: 13 | L44: 127 | M44: 116 | N44: 0.081118881 | O44: -0.42519685 | P44: 185 | R44: https://t.me/sangp_airdrop | X44: WB-C134 | Y44: WB-K056 | Z44: {=_xlfn.XLOOKUP(X44,'측정 관리'!$A$5:$A$204,'측정 관리'!$K$5:$K$204,"",0)}
A45: 38 | B45: 두신의 NFT | C45: doosin_nft | D45: P4 | E45: 5320 | F45: 2026-09-26 | I45: 14 | J45: 1468 | K45: 48 | L45: 778 | M45: 416 | N45: 0.078195489 | O45: 0.88688946 | P45: 381 | Q45: 평균은 바이럴 1건으로 부풀려짐 | R45: https://t.me/doosin_nft | X45: WB-C135 | Y45: WB-K040 | Z45: {=_xlfn.XLOOKUP(X45,'측정 관리'!$A$5:$A$204,'측정 관리'!$K$5:$K$204,"",0)}
A46: 39 | B46: 30대에 퇴학당했다 살아돌아온 불불 | C46: bulbul2cryptoDAO | D46: P4 | E46: 1900 | F46: 2026-09-23 | I46: 2 | J46: 129 | K46: 3 | L46: 207 | M46: 132 | N46: 0.069473684 | O46: -0.37681159 | P46: 204 | R46: https://t.me/bulbul2cryptoDAO | X46: WB-C136 | Y46: WB-K054 | Z46: {=_xlfn.XLOOKUP(X46,'측정 관리'!$A$5:$A$204,'측정 관리'!$K$5:$K$204,"",0)}
A47: 40 | B47: SignalQuant | C47: Signal_Quant | D47: P4 | E47: 4690 | F47: 2026-09-28 | G47: 3 | H47: 137 | I47: 18 | J47: 237 | K47: 70 | L47: 321 | M47: 318 | N47: 0.067803838 | O47: -0.26168224 | P47: 378 | R47: https://t.me/Signal_Quant | X47: WB-C137 | Y47: WB-K042 | Z47: {=_xlfn.XLOOKUP(X47,'측정 관리'!$A$5:$A$204,'측정 관리'!$K$5:$K$204,"",0)}
A48: 41 | B48: Daniel Social Club | C48: danielsocialclub | D48: P4 | E48: 4570 | F48: 2026-09-03 | K48: 3 | L48: 324 | M48: 297 | N48: 0.064989059 | P48: 378 | R48: https://t.me/danielsocialclub | X48: WB-C138 | Y48: WB-K043 | Z48: {=_xlfn.XLOOKUP(X48,'측정 관리'!$A$5:$A$204,'측정 관리'!$K$5:$K$204,"",0)}
A49: 42 | B49: 안성국밥 크립토 맛집 (구 에어드랍 포워딩 국밥집) | C49: coinkookbob | D49: P4 | E49: 4140 | F49: 2026-09-28 | G49: 8 | H49: 203 | I49: 28 | J49: 314 | K49: 146 | L49: 236 | M49: 181 | N49: 0.043719807 | O49: 0.33050847 | P49: 9 | Q49: 채널명 변경 | R49: https://t.me/coinkookbob | X49: WB-C139 | Y49: WB-K052 | Z49: {=_xlfn.XLOOKUP(X49,'측정 관리'!$A$5:$A$204,'측정 관리'!$K$5:$K$204,"",0)}
A50: 43 | B50: 부자가 되고 싶은 춘식이 | C50: choonsik | D50: P4 | E50: 6080 | F50: 2026-09-28 | G50: 3 | H50: 88 | I50: 18 | J50: 341 | K50: 70 | L50: 312 | M50: 257 | N50: 0.042269737 | O50: 0.092948718 | P50: 171 | R50: https://t.me/choonsik | X50: WB-C140 | Y50: WB-K047 | Z50: {=_xlfn.XLOOKUP(X50,'측정 관리'!$A$5:$A$204,'측정 관리'!$K$5:$K$204,"",0)}
A51: 44 | B51: 왕베이 | C51: cryptowangbei | D51: P4 | E51: 7210 | F51: 2026-09-28 | G51: 8 | H51: 125 | I51: 27 | J51: 305 | K51: 115 | L51: 335 | M51: 287 | N51: 0.039805825 | O51: -0.089552239 | P51: 468 | R51: https://t.me/cryptowangbei | X51: WB-C141 | Y51: WB-K044 | Z51: {=_xlfn.XLOOKUP(X51,'측정 관리'!$A$5:$A$204,'측정 관리'!$K$5:$K$204,"",0)}
A52: 45 | B52: WEB 2.5를 꿈꾸는 JackpotDAO | C52: jackpot777DAO | D52: P4 | E52: 3380 | F52: 2026-09-28 | G52: 6 | H52: 47 | I52: 30 | J52: 143 | K52: 112 | L52: 133 | M52: 131 | N52: 0.038757396 | O52: 0.07518797 | P52: 32 | R52: https://t.me/jackpot777DAO | X52: WB-C142 | Y52: WB-K055 | Z52: {=_xlfn.XLOOKUP(X52,'측정 관리'!$A$5:$A$204,'측정 관리'!$K$5:$K$204,"",0)}
A53: 46 | B53: 돈독(열충) | C53: yeolchoongNotice | D53: P4 | E53: 7100 | F53: 2026-09-28 | G53: 7 | H53: 133 | I53: 90 | J53: 255 | K53: 364 | L53: 278 | M53: 275 | N53: 0.038732394 | O53: -0.082733813 | P53: 340 | R53: https://t.me/yeolchoongNotice | X53: WB-C143 | Y53: WB-K045 | Z53: {=_xlfn.XLOOKUP(X53,'측정 관리'!$A$5:$A$204,'측정 관리'!$K$5:$K$204,"",0)}
A54: 47 | B54: 아크의 프리미엄 코인정보방 | C54: Board_the_Ark | D54: P4 | E54: 12000 | F54: 2026-09-28 | G54: 6 | H54: 158 | I54: 39 | J54: 320 | K54: 119 | L54: 418 | M54: 448 | N54: 0.037333333 | O54: -0.23444976 | P54: 278 | R54: https://t.me/Board_the_Ark | X54: WB-C144 | Y54: WB-K039 | Z54: {=_xlfn.XLOOKUP(X54,'측정 관리'!$A$5:$A$204,'측정 관리'!$K$5:$K$204,"",0)}
A55: 48 | B55: 최저시급 김으악 | C55: Ugh_HH | D55: P4 | E55: 9960 | F55: 2026-09-28 | G55: 24 | H55: 253 | I55: 249 | J55: 329 | K55: 869 | L55: 362 | M55: 340 | N55: 0.034136546 | O55: -0.091160221 | P55: 198 | Q55: 하루 29건+ · 30일 일부만 수집 | R55: https://t.me/Ugh_HH | X55: WB-C145 | Y55: WB-K041 | Z55: {=_xlfn.XLOOKUP(X55,'측정 관리'!$A$5:$A$204,'측정 관리'!$K$5:$K$204,"",0)}
A56: 49 | B56: 옹살랜드 | C56: OngsalYee | D56: P4 | E56: 6280 | F56: 2026-09-17 | K56: 4 | L56: 166 | M56: 209 | N56: 0.033280255 | P56: 544 | R56: https://t.me/OngsalYee | X56: WB-C146 | Y56: WB-K050 | Z56: {=_xlfn.XLOOKUP(X56,'측정 관리'!$A$5:$A$204,'측정 관리'!$K$5:$K$204,"",0)}
A57: 50 | B57: 희단이의 Web3 꿀정보 공지방 | C57: heedan22 | D57: P4 | E57: 8200 | F57: 2026-09-28 | G57: 4 | H57: 66 | I57: 13 | J57: 130 | K57: 37 | L57: 271 | M57: 264 | N57: 0.032195122 | O57: -0.5202952 | P57: 273 | R57: https://t.me/heedan22 | X57: WB-C147 | Y57: WB-K046 | Z57: {=_xlfn.XLOOKUP(X57,'측정 관리'!$A$5:$A$204,'측정 관리'!$K$5:$K$204,"",0)}
A58: 51 | B58: 코인한나의 Honeybag | C58: coinhanna_honeybag | D58: P4 | E58: 6680 | F58: 2026-09-28 | G58: 13 | H58: 165 | I58: 59 | J58: 186 | K58: 240 | L58: 239 | M58: 212 | N58: 0.031736527 | O58: -0.22175732 | P58: 186 | R58: https://t.me/coinhanna_honeybag | X58: WB-C148 | Y58: WB-K049 | Z58: {=_xlfn.XLOOKUP(X58,'측정 관리'!$A$5:$A$204,'측정 관리'!$K$5:$K$204,"",0)}
A59: 52 | B59: 부의길목에서 | C59: stay_news | D59: P4 | E59: 7770 | F59: 2026-09-28 | G59: 7 | H59: 478 | I59: 48 | J59: 332 | K59: 366 | L59: 253 | M59: 227 | N59: 0.029214929 | O59: 0.31225296 | P59: 139 | R59: https://t.me/stay_news | X59: WB-C149 | Y59: WB-K048 | Z59: {=_xlfn.XLOOKUP(X59,'측정 관리'!$A$5:$A$204,'측정 관리'!$K$5:$K$204,"",0)}
A60: 53 | B60: 크립토 부엉이 | C60: CryptoOwlNotice | D60: P4 | E60: 7810 | F60: 2026-09-28 | G60: 5 | H60: 141 | I60: 21 | J60: 168 | K60: 115 | L60: 193 | M60: 195 | N60: 0.02496799 | O60: -0.12953368 | P60: 207 | R60: https://t.me/CryptoOwlNotice | X60: WB-C150 | Y60: WB-K051 | Z60: {=_xlfn.XLOOKUP(X60,'측정 관리'!$A$5:$A$204,'측정 관리'!$K$5:$K$204,"",0)}
A61: 54 | B61: 크립토 원정대 | C61: legoleecm777 | D61: P4 | E61: 7120 | F61: 2026-09-28 | G61: 5 | H61: 55 | I61: 20 | J61: 87 | K61: 77 | L61: 104 | M61: 103 | N61: 0.014466292 | O61: -0.16346154 | P61: 93 | R61: https://t.me/legoleecm777 | X61: WB-C151 | Y61: WB-K057 | Z61: {=_xlfn.XLOOKUP(X61,'측정 관리'!$A$5:$A$204,'측정 관리'!$K$5:$K$204,"",0)}
A62: 55 | B62: 곰곰히 매매 | C62: Kindibearbtc | D62: 비활동 | E62: 33 | F62: 2026-09-02 | K62: 2 | L62: 26 | M62: 29 | N62: 0.87878788 | P62: 89 | Q62: 30일 2건 | R62: https://t.me/Kindibearbtc | X62: WB-C152 | Y62: WB-K062 | Z62: {=_xlfn.XLOOKUP(X62,'측정 관리'!$A$5:$A$204,'측정 관리'!$K$5:$K$204,"",0)}
A63: 56 | B63: 디젠걸 | C63: KDegengirl | D63: 비활동 | E63: 891 | F63: 2026-09-25 | I63: 2 | J63: 55 | K63: 2 | L63: 55 | M63: 58 | N63: 0.065095398 | O63: 0 | P63: 76 | Q63: 30일 2건 | R63: https://t.me/KDegengirl | X63: WB-C153 | Y63: WB-K061 | Z63: {=_xlfn.XLOOKUP(X63,'측정 관리'!$A$5:$A$204,'측정 관리'!$K$5:$K$204,"",0)}
A64: 57 | B64: ORCA ALPHA | C64: orcaalpha | D64: 비활동 | E64: 1500 | F64: 2026-09-27 | G64: 1 | H64: 93 | I64: 1 | J64: 93 | K64: 2 | L64: 95 | M64: 97 | N64: 0.064666667 | O64: -0.021052632 | P64: 159 | Q64: 30일 2건 | R64: https://t.me/orcaalpha | X64: WB-C154 | Y64: WB-K060 | Z64: {=_xlfn.XLOOKUP(X64,'측정 관리'!$A$5:$A$204,'측정 관리'!$K$5:$K$204,"",0)}
A65: 58 | B65: 코마카세 | C65: COMADAO | D65: 비활동 | E65: 486 | F65: 2026-05-30 | P65: 258 | Q65: 비활성 | R65: https://t.me/COMADAO | X65: WB-C155 | Y65: WB-K063 | Z65: {=_xlfn.XLOOKUP(X65,'측정 관리'!$A$5:$A$204,'측정 관리'!$K$5:$K$204,"",0)}
A66: 59 | B66: KryptoKlang | C66: KryptoKlang | D66: 비활동 | E66: 2620 | P66: 291 | Q66: 조회수 있는 게시물 없음 | R66: https://t.me/KryptoKlang | X66: WB-C156 | Y66: WB-K058 | Z66: {=_xlfn.XLOOKUP(X66,'측정 관리'!$A$5:$A$204,'측정 관리'!$K$5:$K$204,"",0)}
A67: 60 | B67: 코선생의 코인교실 | C67: crypto_class_ann | D67: 비활동 | E67: 1630 | F67: 2024-07-15 | P67: 880 | Q67: 비활성 | R67: https://t.me/crypto_class_ann | X67: WB-C157 | Y67: WB-K074 | Z67: {=_xlfn.XLOOKUP(X67,'측정 관리'!$A$5:$A$204,'측정 관리'!$K$5:$K$204,"",0)}
A68: 61 | B68: 0xEdenity / Web3 | C68: Edenitywl | D68: 비활동 | E68: 1380 | F68: 2026-08-21 | P68: 881 | Q68: 비활성 | R68: https://t.me/Edenitywl | X68: WB-C158 | Y68: WB-K075 | Z68: {=_xlfn.XLOOKUP(X68,'측정 관리'!$A$5:$A$204,'측정 관리'!$K$5:$K$204,"",0)}
A69: 62 | B69: NFT Forum | C69: NFTForumKR | D69: 비활동 | E69: 610 | F69: 2025-12-09 | P69: 823 | Q69: 비활성 | R69: https://t.me/NFTForumKR | X69: WB-C159 | Y69: WB-K076 | Z69: {=_xlfn.XLOOKUP(X69,'측정 관리'!$A$5:$A$204,'측정 관리'!$K$5:$K$204,"",0)}
A70: 63 | B70: KOL scan 공지방 | C70: kol_scan | D70: 비활동 | E70: 274 | F70: 2025-02-03 | P70: 914 | Q70: 비활성 | R70: https://t.me/kol_scan | X70: WB-C160 | Y70: WB-K077 | Z70: {=_xlfn.XLOOKUP(X70,'측정 관리'!$A$5:$A$204,'측정 관리'!$K$5:$K$204,"",0)}
A71: 64 | B71: 졸업하자 | C71: letsjolup | D71: 비활동 | E71: 261 | F71: 2026-05-20 | P71: 61 | Q71: 비활성 | R71: https://t.me/letsjolup | X71: WB-C161 | Y71: WB-K078 | Z71: {=_xlfn.XLOOKUP(X71,'측정 관리'!$A$5:$A$204,'측정 관리'!$K$5:$K$204,"",0)}
A72: 65 | B72: 후니방 | C72: hooniebang | D72: 비활동 | P72: 8 | Q72: 미리보기 비공개 | R72: https://t.me/hooniebang | X72: WB-C162 | Y72: WB-K079 | Z72: {=_xlfn.XLOOKUP(X72,'측정 관리'!$A$5:$A$204,'측정 관리'!$K$5:$K$204,"",0)} -> 조회 불가
A73: 66 | B73: Crypto SENA | C73: CryptoSenaNotice | D73: 비활동 | E73: 7 | F73: 2023-11-01 | P73: 500 | Q73: 비활성 | R73: https://t.me/CryptoSenaNotice | X73: WB-C163 | Y73: WB-K080 | Z73: {=_xlfn.XLOOKUP(X73,'측정 관리'!$A$5:$A$204,'측정 관리'!$K$5:$K$204,"",0)}
A74: 67 | B74: 기분좋은 마곤 | C74: magoniabbb | D74: 비활동 | E74: 5 | F74: 2026-05-31 | P74: 563 | Q74: 비활성 | R74: https://t.me/magoniabbb | X74: WB-C164 | Y74: WB-K081 | Z74: {=_xlfn.XLOOKUP(X74,'측정 관리'!$A$5:$A$204,'측정 관리'!$K$5:$K$204,"",0)}

Sheet 한국 YT
A1: 한국 YouTube — 23개 채널 (롱폼)
A2: ■ 퍼포먼스 = 30일 롱폼 중앙 조회 P1 10,000+ · P2 3,000+ · P3 1,000+ · 비활동 = 30일 0개
A3: ■ 한국 YT는 24시간 단위 수집을 하지 않아 '최근 영상'(경과일)으로 대체 · 쇼츠는 별도 칸 (최근 N개 평균)
A4: ■ 30일 안에 롱폼을 올린 채널은 23곳 중 소수 — 한국은 TG 중심으로 볼 것
G6: 7일 | I6: 30일
A7: 순위 | B7: KOL | C7: 채널 | D7: 퍼포먼스 | E7: 구독자 | F7: 최근 영상 | G7: 영상 | H7: 평균 조회 | I7: 영상 | J7: 평균 조회 | K7: 중앙 조회 | L7: 도달률 | M7: 쇼츠 평균 (최근 N개) | N7: 메모 | O7: 링크 | X7: 채널 ID | Y7: KOL ID | Z7: 측정 상태
A8: 1 | B8: 매실남 | C8: @pluman | D8: P2 | E8: 10200 | F8: 3일 전 | G8: 2 | H8: 3800 | I8: 3 | J8: 5867 | K8: 6200 | L8: 0.60784314 | O8: https://www.youtube.com/@pluman | X8: WB-C165 | Y8: WB-K004 | Z8: {=_xlfn.XLOOKUP(X8,'측정 관리'!$A$5:$A$204,'측정 관리'!$K$5:$K$204,"",0)}
A9: 2 | B9: 코백남 | C9: @cobacknam | D9: P2 | E9: 57900 | F9: 14일 전 | I9: 1 | J9: 4300 | K9: 4300 | L9: 0.074265976 | M9: 2,595 (10개) | N9: TG 채널 병행 | O9: https://www.youtube.com/@cobacknam | X9: WB-C166 | Y9: WB-K005 | Z9: {=_xlfn.XLOOKUP(X9,'측정 관리'!$A$5:$A$204,'측정 관리'!$K$5:$K$204,"",0)}
A10: 3 | B10: coinfluencer | C10: @CoinFluencer | D10: P2 | E10: 99300 | F10: 4일 전 | G10: 1 | H10: 2200 | I10: 2 | J10: 2750 | K10: 3300 | L10: 0.033232628 | M10: 2,395 (4개) | N10: TG hjwnews 병행 | O10: https://www.youtube.com/@CoinFluencer | X10: WB-C167 | Y10: WB-K002 | Z10: {=_xlfn.XLOOKUP(X10,'측정 관리'!$A$5:$A$204,'측정 관리'!$K$5:$K$204,"",0)}
A11: 4 | B11: 나백이 | C11: @naback222 | D11: P3 | E11: 16700 | F11: 21일 전 | I11: 1 | J11: 2900 | K11: 2900 | L11: 0.17365269 | O11: https://www.youtube.com/@naback222 | X11: WB-C168 | Y11: WB-K015 | Z11: {=_xlfn.XLOOKUP(X11,'측정 관리'!$A$5:$A$204,'측정 관리'!$K$5:$K$204,"",0)}
A12: 5 | B12: 코인소년 | C12: @coinboys | D12: P3 | E12: 53200 | F12: 2일 전 | G12: 2 | H12: 2350 | I12: 6 | J12: 2333 | K12: 2200 | L12: 0.041353383 | M12: 2,800 (9개) | N12: TG 채널 병행 | O12: https://www.youtube.com/@coinboys | X12: WB-C169 | Y12: WB-K016 | Z12: {=_xlfn.XLOOKUP(X12,'측정 관리'!$A$5:$A$204,'측정 관리'!$K$5:$K$204,"",0)}
A13: 6 | B13: T.A Crypto | C13: @TA_crypto | D13: P3 | E13: 7410 | F13: 10일 전 | I13: 1 | J13: 1200 | K13: 1200 | L13: 0.16194332 | M13: 1,142 (10개) | N13: TG 채널 병행 | O13: https://www.youtube.com/@TA_crypto | X13: WB-C170 | Y13: WB-K019 | Z13: {=_xlfn.XLOOKUP(X13,'측정 관리'!$A$5:$A$204,'측정 관리'!$K$5:$K$204,"",0)}
A14: 7 | B14: 크립토메이지 | C14: @cryptocurrencymage | D14: P4 | E14: 8590 | F14: 1일 전 | G14: 3 | H14: 711 | I14: 3 | J14: 711 | K14: 570 | L14: 0.066356228 | O14: https://www.youtube.com/@cryptocurrencymage | X14: WB-C171 | Y14: WB-K037 | Z14: {=_xlfn.XLOOKUP(X14,'측정 관리'!$A$5:$A$204,'측정 관리'!$K$5:$K$204,"",0)}
A15: 8 | B15: 에어드랍 ATM | C15: @airdropatm | D15: P4 | E15: 10000 | F15: 10일 전 | I15: 1 | J15: 476 | K15: 476 | L15: 0.0476 | M15: 조회 실패 | O15: https://www.youtube.com/@airdropatm | X15: WB-C172 | Y15: WB-K038 | Z15: {=_xlfn.XLOOKUP(X15,'측정 관리'!$A$5:$A$204,'측정 관리'!$K$5:$K$204,"",0)}
A16: 9 | B16: 돈버는 꿀정보 | C16: @donkkul | D16: 비활동 | E16: 9640 | F16: 약 2년 전 | M16: 28,983 (6개, 27,000 1건 포함) | N16: 롱폼 중단 | O16: https://www.youtube.com/@donkkul | X16: WB-C173 | Y16: WB-K071 | Z16: {=_xlfn.XLOOKUP(X16,'측정 관리'!$A$5:$A$204,'측정 관리'!$K$5:$K$204,"",0)}
A17: 10 | B17: 잼민123 | C17: @jammin2 | D17: 비활동 | E17: 25300 | F17: 105일 전 | M17: 5,800 (1개) | N17: 롱폼 중단 | O17: https://www.youtube.com/@jammin2 | X17: WB-C174 | Y17: WB-K013 | Z17: {=_xlfn.XLOOKUP(X17,'측정 관리'!$A$5:$A$204,'측정 관리'!$K$5:$K$204,"",0)}
A18: 11 | B18: 영투한 | C18: @02HAN | D18: 비활동 | E18: 10700 | F18: 45일 전 | M18: 4,600 (1개) | N18: 롱폼 중단 | O18: https://www.youtube.com/@02HAN | X18: WB-C175 | Y18: WB-K069 | Z18: {=_xlfn.XLOOKUP(X18,'측정 관리'!$A$5:$A$204,'측정 관리'!$K$5:$K$204,"",0)}
A19: 12 | B19: 왕베이 | C19: @Wangbei__ | D19: 비활동 | E19: 3140 | F19: 75일 전 | M19: 1,920 (5개) | N19: 롱폼 중단 | O19: https://www.youtube.com/@Wangbei__ | X19: WB-C176 | Y19: WB-K044 | Z19: {=_xlfn.XLOOKUP(X19,'측정 관리'!$A$5:$A$204,'측정 관리'!$K$5:$K$204,"",0)}
A20: 13 | B20: 두신의 NFT | C20: @doosinnft | D20: 비활동 | E20: 2290 | F20: 165일 전 | M20: 1,296 (10개) | N20: 롱폼 중단 | O20: https://www.youtube.com/@doosinnft | X20: WB-C177 | Y20: WB-K040 | Z20: {=_xlfn.XLOOKUP(X20,'측정 관리'!$A$5:$A$204,'측정 관리'!$K$5:$K$204,"",0)}
A21: 14 | B21: 오늘의 꿀통 | C21: @honeyoftoday | D21: 비활동 | E21: 10200 | F21: 255일 전 | M21: 534 (10개) | N21: 롱폼 중단 | O21: https://www.youtube.com/@honeyoftoday | X21: WB-C178 | Y21: WB-K070 | Z21: {=_xlfn.XLOOKUP(X21,'측정 관리'!$A$5:$A$204,'측정 관리'!$K$5:$K$204,"",0)}
A22: 15 | B22: Jerry Alpha | C22: @jerryalphanft | D22: 비활동 | E22: 11900 | F22: 225일 전 | M22: 478 (3개) | N22: 롱폼 중단 | O22: https://www.youtube.com/@jerryalphanft | X22: WB-C179 | Y22: WB-K067 | Z22: {=_xlfn.XLOOKUP(X22,'측정 관리'!$A$5:$A$204,'측정 관리'!$K$5:$K$204,"",0)}
A23: 16 | B23: CEN | C23: @CEN_CRYPTO | D23: 비활동 | E23: 6610 | F23: 약 2년 전 | M23: 157 (10개) | N23: 롱폼 중단 | O23: https://www.youtube.com/@CEN_CRYPTO | X23: WB-C180 | Y23: WB-K036 | Z23: {=_xlfn.XLOOKUP(X23,'측정 관리'!$A$5:$A$204,'측정 관리'!$K$5:$K$204,"",0)}
A24: 17 | B24: 1분 코인 | C24: channel/UCKsMT8_jAvNWtOOS6Lo23EQ | D24: 비활동 | E24: 34200 | F24: 195일 전 | M24: 없음 | N24: 롱폼 중단 | O24: https://www.youtube.com/channel/UCKsMT8_jAvNWtOOS6Lo23EQ | X24: WB-C181 | Y24: WB-K064 | Z24: {=_xlfn.XLOOKUP(X24,'측정 관리'!$A$5:$A$204,'측정 관리'!$K$5:$K$204,"",0)}
A25: 18 | B25: 크립토 청춘 (돈버는청춘) | C25: @CheongChun | D25: 비활동 | E25: 17700 | F25: 105일 전 | M25: 없음 | N25: 롱폼 중단 | O25: https://www.youtube.com/@CheongChun | X25: WB-C182 | Y25: WB-K065 | Z25: {=_xlfn.XLOOKUP(X25,'측정 관리'!$A$5:$A$204,'측정 관리'!$K$5:$K$204,"",0)}
A26: 19 | B26: 생계형 프로그래머 | C26: @sangptube | D26: 비활동 | E26: 4720 | F26: 255일 전 | M26: 없음 | N26: 롱폼 중단 | O26: https://www.youtube.com/@sangptube | X26: WB-C183 | Y26: WB-K072 | Z26: {=_xlfn.XLOOKUP(X26,'측정 관리'!$A$5:$A$204,'측정 관리'!$K$5:$K$204,"",0)}
A27: 20 | B27: 폐지줍는 츄카피 | C27: @chukapika | D27: 비활동 | E27: 2300 | F27: 365일 전 | M27: 없음 | N27: 롱폼 중단 | O27: https://www.youtube.com/@chukapika | X27: WB-C184 | Y27: WB-K073 | Z27: {=_xlfn.XLOOKUP(X27,'측정 관리'!$A$5:$A$204,'측정 관리'!$K$5:$K$204,"",0)}
A28: 21 | B28: 이도진 | C28: @leedogin | D28: 비활동 | E28: 12800 | F28: 75일 전 | M28: 없음 | N28: 롱폼 중단 | O28: https://www.youtube.com/@leedogin | X28: WB-C185 | Y28: WB-K066 | Z28: {=_xlfn.XLOOKUP(X28,'측정 관리'!$A$5:$A$204,'측정 관리'!$K$5:$K$204,"",0)}
A29: 22 | B29: 로로 | C29: @COINRORO | D29: 비활동 | E29: 11400 | M29: 없음 | N29: 공개 영상 0개 → 보류 | O29: https://www.youtube.com/@COINRORO | X29: WB-C186 | Y29: WB-K068 | Z29: {=_xlfn.XLOOKUP(X29,'측정 관리'!$A$5:$A$204,'측정 관리'!$K$5:$K$204,"",0)}
A30: 23 | B30: 부의길목에서 | C30: @CoinStay | D30: 비활동 | N30: 404 (채널 없음) → 보류 | O30: https://www.youtube.com/@CoinStay | X30: WB-C187 | Y30: WB-K048 | Z30: {=_xlfn.XLOOKUP(X30,'측정 관리'!$A$5:$A$204,'측정 관리'!$K$5:$K$204,"",0)} -> 계정 확인 필요

Sheet 한국 X
A1: 한국 X — 13개 계정
A2: ■ 퍼포먼스 = 게시물당 평균 반응 (평균 조회 × ER) · 한국 KOL은 X 비중이 낮아 대부분 P3 이하
A3: ■ 30일을 못 불러온 계정은 7일 기준으로 등급 산정 (메모 표기)
D5: 영향력 | H5: 24시간 | L5: 7일 | P5: 30일
A6: 순위 | B6: KOL | C6: 퍼포먼스 | D6: Twitter Score | E6: TS 등급 | F6: 스마트 팔로워 | G6: 팔로워 | H6: 게시 | I6: 평균 조회 | J6: 평균 반응 | K6: ER | L6: 게시 | M6: 평균 조회 | N6: 평균 반응 | O6: ER | P6: 게시 | Q6: 평균 조회 | R6: 평균 반응 | S6: ER | T6: 도달률 (조회÷팔로워) | U6: 추세 (7d vs 30d) | V6: 메모 | W6: 링크 | X6: 채널 ID | Y6: KOL ID | Z6: 측정 상태
A7: 1 | B7: @heedan123 | C7: P4 | D7: 3 | E7: D | G7: 4719 | P7: 4 | Q7: 1302 | R7: 37.4976 | S7: 0.0288 | T7: 0.27590591 | V7: 마지막 9/16 | W7: https://x.com/heedan123 | X7: WB-C188 | Y7: WB-K045 | Z7: {=_xlfn.XLOOKUP(X7,'측정 관리'!$A$5:$A$204,'측정 관리'!$K$5:$K$204,"",0)}
A8: 2 | B8: @AlphaSchool77 | C8: P4 | D8: 4 | E8: D | F8: 51 | G8: 19000 | H8: 1 | I8: 1727 | J8: 79.9601 | K8: 0.0463 | L8: 2 | M8: 1167 | N8: 57.9999 | O8: 0.0497 | P8: 17 | Q8: 910 | R8: 26.572 | S8: 0.0292 | T8: 0.047894737 | U8: 0.28241758 | V8: 9/16 이후만 수집 · WL 기브어웨이 위주 → ER 부풀려짐 | W8: https://x.com/AlphaSchool77 | X8: WB-C189 | Y8: WB-K018 | Z8: {=_xlfn.XLOOKUP(X8,'측정 관리'!$A$5:$A$204,'측정 관리'!$K$5:$K$204,"",0)} -> 일부 수집
A9: 3 | B9: @CENTWT | C9: P4 | D9: 6 | E9: D | F9: 68 | G9: 14000 | P9: 3 | Q9: 1961 | R9: 25.2969 | S9: 0.0129 | T9: 0.14007143 | V9: 마지막 9/7 | W9: https://x.com/CENTWT | X9: WB-C190 | Y9: WB-K036 | Z9: {=_xlfn.XLOOKUP(X9,'측정 관리'!$A$5:$A$204,'측정 관리'!$K$5:$K$204,"",0)}
A10: 4 | B10: @p2ecoin91 | C10: P4 | D10: 3 | E10: D | F10: 28 | G10: 2964 | H10: 2 | I10: 481 | J10: 11.0149 | K10: 0.0229 | L10: 6 | M10: 1412 | N10: 23.1568 | O10: 0.0164 | P10: 11 | Q10: 1294 | R10: 14.4928 | S10: 0.0112 | T10: 0.4365722 | U10: 0.091190108 | W10: https://x.com/p2ecoin91 | X10: WB-C191 | Y10: WB-K037 | Z10: {=_xlfn.XLOOKUP(X10,'측정 관리'!$A$5:$A$204,'측정 관리'!$K$5:$K$204,"",0)}
A11: 5 | B11: @cryptoyobeul | C11: P4 | D11: 18 | E11: C | F11: 149 | G11: 20700 | P11: 3 | Q11: 460 | R11: 5.658 | S11: 0.0123 | T11: 0.022222222 | V11: 마지막 9/17 | W11: https://x.com/cryptoyobeul | X11: WB-C192 | Y11: WB-K053 | Z11: {=_xlfn.XLOOKUP(X11,'측정 관리'!$A$5:$A$204,'측정 관리'!$K$5:$K$204,"",0)}
A12: 6 | B12: @Naback222 | C12: P4 | D12: 17 | E12: C | F12: 164 | G12: 32100 | L12: 5 | M12: 799 | N12: 3.5955 | O12: 0.0045 | P12: 41 | Q12: 782 | R12: 4.2228 | S12: 0.0054 | T12: 0.024361371 | U12: 0.02173913 | W12: https://x.com/Naback222 | X12: WB-C193 | Y12: WB-K015 | Z12: {=_xlfn.XLOOKUP(X12,'측정 관리'!$A$5:$A$204,'측정 관리'!$K$5:$K$204,"",0)}
A13: 7 | B13: @log_yun | C13: P4 | D13: 3 | E13: D | F13: 6 | G13: 5360 | H13: 1 | I13: 124 | J13: 3.0008 | K13: 0.0242 | L13: 1 | M13: 124 | N13: 3.0008 | O13: 0.0242 | P13: 8 | Q13: 583 | R13: 2.8567 | S13: 0.0049 | T13: 0.10876866 | U13: -0.78730703 | W13: https://x.com/log_yun | X13: WB-C194 | Z13: {=_xlfn.XLOOKUP(X13,'측정 관리'!$A$5:$A$204,'측정 관리'!$K$5:$K$204,"",0)} -> 기간 확인 필요
A14: 8 | B14: @Stay1104 | C14: P4 | D14: 2 | E14: D | F14: 6 | G14: 2879 | H14: 1 | I14: 14 | J14: 0.9996 | K14: 0.0714 | L14: 1 | M14: 14 | N14: 0.9996 | O14: 0.0714 | P14: 11 | Q14: 89 | R14: 1.9936 | S14: 0.0224 | T14: 0.030913512 | U14: -0.84269663 | W14: https://x.com/Stay1104 | X14: WB-C195 | Y14: WB-K058 | Z14: {=_xlfn.XLOOKUP(X14,'측정 관리'!$A$5:$A$204,'측정 관리'!$K$5:$K$204,"",0)}
A15: 9 | B15: @coinboy717 | C15: P4 | D15: 11 | E15: D | F15: 82 | G15: 17700 | H15: 1 | I15: 1295 | L15: 28 | M15: 1443 | N15: 24.8196 | O15: 0.0172 | V15: 9/21 이후만 수집 (하루 4건) · 30일 미수집 → 7일 기준 | W15: https://x.com/coinboy717 | X15: WB-C196 | Y15: WB-K016 | Z15: {=_xlfn.XLOOKUP(X15,'측정 관리'!$A$5:$A$204,'측정 관리'!$K$5:$K$204,"",0)}
A16: 10 | B16: @0xsangp | C16: P4 | D16: 1 | E16: D | G16: 1859 | H16: 5 | I16: 20 | L16: 5 | M16: 20 | P16: 7 | Q16: 36 | T16: 0.01936525 | U16: -0.44444444 | W16: https://x.com/0xsangp | X16: WB-C197 | Y16: WB-K057 | Z16: {=_xlfn.XLOOKUP(X16,'측정 관리'!$A$5:$A$204,'측정 관리'!$K$5:$K$204,"",0)}
A17: 11 | B17: @TheP2E_NFT | C17: 비활동 | D17: 2 | E17: D | F17: 6 | G17: 7219 | V17: 보류 · 시트 100,000 ≠ 실제 7,219 · 마지막 7/14 · 30일 미수집 → 7일 기준 | W17: https://x.com/TheP2E_NFT | X17: WB-C198 | Y17: WB-K002 | Z17: {=_xlfn.XLOOKUP(X17,'측정 관리'!$A$5:$A$204,'측정 관리'!$K$5:$K$204,"",0)}
A18: 12 | B18: @nftroro | C18: 비활동 | D18: 2 | E18: D | G18: 2480 | V18: 보류 · 시트 11,500 · 전체 게시물 77개 · 30일 미수집 → 7일 기준 | W18: https://x.com/nftroro | X18: WB-C199 | Y18: WB-K068 | Z18: {=_xlfn.XLOOKUP(X18,'측정 관리'!$A$5:$A$204,'측정 관리'!$K$5:$K$204,"",0)}
A19: 13 | B19: @Xrtrashbin | C19: 비활동 | G19: 12 | V19: 보류 · 계정 불일치 (시트 12,800) · 30일 미수집 → 7일 기준 | W19: https://x.com/Xrtrashbin | X19: WB-C200 | Y19: WB-K066 | Z19: {=_xlfn.XLOOKUP(X19,'측정 관리'!$A$5:$A$204,'측정 관리'!$K$5:$K$204,"",0)}

Sheet TwitterScore
A1: TwitterScore — 56개 X 계정
A2: ■ TwitterScore = twitterscore.io 공개 점수 (영향력 계정 팔로워 기반) · S 200+ · A 100–199 · B 40–99 · C 15–39 · D 15 미만
A3: ■ 스마트 팔로워 = 영향력 있는 계정 중 팔로워 수 · 스마트 비율 = 스마트 ÷ 전체 팔로워
A4: ■ 오른쪽 '30일 퍼포먼스'는 X 실측 (글로벌 X·한국 X 탭) — 점수가 높아도 실제 반응이 낮은 계정을 구분하기 위함
C6: TwitterScore | J6: X 실측 · 30일
A7: 순위 | B7: X 계정 | C7: 점수 | D7: 등급 | E7: 원 표기 | F7: 스마트 팔로워 | G7: 팔로워 | H7: 스마트 비율 | I7: 지역 | J7: 퍼포먼스 | K7: 평균 조회 | L7: ER | M7: 8/25 시트 팔로워 | N7: TwitterScore 링크
A8: 1 | B8: @ColdBloodShill | C8: 423 | D8: S | F8: 3185 | G8: 352483 | H8: 0.0090358968 | I8: Global | J8: P2 | K8: 38127 | L8: 0.0068 | M8: 14900 | N8: https://twitterscore.io/twitter/ColdBloodShill/overview/
A9: 2 | B9: @AltcoinSherpa | C9: 280 | D9: S | F9: 2014 | G9: 263424 | H9: 0.0076454689 | I9: Global | J9: P3 | K9: 14357 | L9: 0.0083 | M9: 11600 | N9: https://twitterscore.io/twitter/AltcoinSherpa/overview/
A10: 3 | B10: @Trader_XO | C10: 270 | D10: S | F10: 2422 | G10: 550420 | H10: 0.0044002762 | I10: Global | J10: P1 | K10: 85386 | L10: 0.0048 | M10: 61300 | N10: https://twitterscore.io/twitter/Trader_XO/overview/
A11: 4 | B11: @IncomeSharks | C11: 235 | D11: S | F11: 2206 | G11: 742429 | H11: 0.0029713279 | I11: Global | J11: P1 | K11: 89477 | L11: 0.0078 | M11: 8570 | N11: https://twitterscore.io/twitter/IncomeSharks/overview/
A12: 5 | B12: @EricCryptoman | C12: 227 | D12: S | F12: 1898 | G12: 272253 | H12: 0.0069714567 | I12: Global | J12: P2 | K12: 23777 | L12: 0.0088 | M12: 30870 | N12: https://twitterscore.io/twitter/EricCryptoman/overview/
A13: 6 | B13: @rektcapital | C13: 193 | D13: A | F13: 1860 | G13: 563000 | H13: 0.00330373 | I13: Global | J13: P2 | K13: 65242 | L13: 0.0053 | M13: 114000 | N13: https://twitterscore.io/twitter/rektcapital/overview/
A14: 7 | B14: @DaanCrypto | C14: 192 | D14: A | F14: 1601 | G14: 415069 | H14: 0.00385719 | I14: Global | J14: P2 | K14: 20832 | L14: 0.0082 | M14: 7170 | N14: https://twitterscore.io/twitter/DaanCrypto/overview/
A15: 8 | B15: @KoroushAK | C15: 189 | D15: A | F15: 1556 | G15: 377469 | H15: 0.0041221928 | I15: Global | J15: P3 | K15: 19273 | L15: 0.005 | M15: 106000 | N15: https://twitterscore.io/twitter/KoroushAK/overview/
A16: 9 | B16: @nobrainflip | C16: 163 | D16: A | F16: 1645 | G16: 543000 | H16: 0.0030294659 | I16: Global | J16: P2 | K16: 80343 | L16: 0.0041 | M16: 78377 | N16: https://twitterscore.io/twitter/nobrainflip/overview/
A17: 10 | B17: @DeRonin_ | C17: 153 | D17: A | F17: 1234 | G17: 118197 | H17: 0.010440197 | I17: Global | J17: P2 | K17: 39946 | L17: 0.0096 | M17: 11924 | N17: https://twitterscore.io/twitter/DeRonin_/overview/
A18: 11 | B18: @inmortalcrypto | C18: 145 | D18: A | F18: 1257 | G18: 232451 | H18: 0.0054075913 | I18: Global | J18: P2 | K18: 25898 | L18: 0.0113 | M18: 11800 | N18: https://twitterscore.io/twitter/inmortalcrypto/overview/
A19: 12 | B19: @MuroCrypto | C19: 143 | D19: A | F19: 1249 | G19: 403000 | H19: 0.0030992556 | I19: Global | J19: P2 | K19: 35672 | L19: 0.0048 | M19: 14300 | N19: https://twitterscore.io/twitter/MuroCrypto/overview/
... A36: 29 | B36: @0xchromium | C36: 24 | D36: C | F36: 201 | G36: 22800 | H36: 0.0088157895 | I36: Global | J36: P4 | K36: 2009 | L36: 0.0135 | M36: 2526 | N36: https://twitterscore.io/twitter/0xchromium/overview/
A37: 30 | B37: @LookForEntries | C37: 22 | D37: C | F37: 163 | G37: 56300 | H37: 0.0028952043 | I37: Global | J37: P4 | M37: 420 | N37: https://twitterscore.io/twitter/LookForEntries/overview/
A38: 31 | B38: @0xDarya_ | C38: 21 | D38: C | F38: 199 | G38: 33700 | H38: 0.0059050445 | I38: Global | J38: 비활동 | M38: 3968 | N38: https://twitterscore.io/twitter/0xDarya_/overview/
A39: 32 | B39: @WhaleNoName | C39: 20 | D39: C | F39: 175 | G39: 50776 | H39: 0.0034465102 | I39: Global | J39: P3 | K39: 22663 | L39: 0.0034 | M39: 69 | N39: https://twitterscore.io/twitter/WhaleNoName/overview/
A40: 33 | B40: @cryptoyobeul | C40: 18 | D40: C | F40: 149 | G40: 20700 | H40: 0.0071980676 | I40: KR | J40: P4 | K40: 460 | L40: 0.0123 | M40: 1325 | N40: https://twitterscore.io/twitter/cryptoyobeul/overview/
A41: 34 | B41: @Naback222 | C41: 17 | D41: C | F41: 164 | G41: 32200 | H41: 0.0050931677 | I41: KR | J41: P4 | K41: 782 | L41: 0.0054 | M41: 16800 | N41: https://twitterscore.io/twitter/Naback222/overview/
A42: 35 | B42: @onlineboss_ | C42: 17 | D42: C | F42: 136 | G42: 52300 | H42: 0.0026003824 | I42: Global | J42: 비활동 | K42: 3065 | L42: 0.017 | M42: 73900 | N42: https://twitterscore.io/twitter/onlineboss_/overview/
A43: 36 | B43: @0xklarck | C43: 12 | D43: D | F43: 118 | G43: 95473 | H43: 0.0012359515 | I43: Global | J43: P3 | K43: 28303 | L43: 0.0031 | M43: 37955 | N43: https://twitterscore.io/twitter/0xklarck/overview/
A44: 37 | B44: @coinboy717 | C44: 11 | D44: D | F44: 82 | G44: 17700 | H44: 0.0046327684 | I44: KR | J44: P4 | M44: 8035 | N44: https://twitterscore.io/twitter/coinboy717/overview/
A45: 38 | B45: @w1nklerr | C45: 8 | D45: D | E45: 보류 | F45: 79 | G45: 61000 | H45: 0.001295082 | I45: Global | J45: P3 | K45: 12384 | L45: 0.0068 | M45: 8096 | N45: https://twitterscore.io/twitter/w1nklerr/overview/
A46: 39 | B46: @0xImmortal_ | C46: 7 | D46: D | F46: 62 | G46: 9060 | H46: 0.0068432671 | I46: Global | J46: 비활동 | M46: 184 | N46: https://twitterscore.io/twitter/0xImmortal_/overview/
A47: 40 | B47: @CENTWT | C47: 6 | D47: D | F47: 68 | G47: 14700 | H47: 0.0046258503 | I47: KR | J47: P4 | K47: 1961 | L47: 0.0129 | M47: 6620 | N47: https://twitterscore.io/twitter/CENTWT/overview/
A48: 41 | B48: @0xFrogify | C48: 5 | D48: D | E48: 보류 | F48: 59 | G48: 45300 | H48: 0.0013024283 | I48: Global | J48: P4 | K48: 9013 | L48: 0.0031 | M48: 8198 | N48: https://twitterscore.io/twitter/0xFrogify/overview/
A49: 42 | B49: @AlphaSchool77 | C49: 4 | D49: D | F49: 51 | G49: 19100 | H49: 0.0026701571 | I49: KR | J49: P4 | K49: 910 | L49: 0.0292 | M49: 7606 | N49: https://twitterscore.io/twitter/AlphaSchool77/overview/
A50: 43 | B50: @log_yun | C50: 3 | D50: D | F50: 6 | G50: 5360 | H50: 0.001119403 | I50: KR | J50: P4 | K50: 583 | L50: 0.0049 | M50: 11243 | N50: https://twitterscore.io/twitter/log_yun/overview/
A51: 44 | B51: @p2ecoin91 | C51: 3 | D51: D | F51: 28 | G51: 2960 | H51: 0.0094594595 | I51: KR | J51: P4 | K51: 1294 | L51: 0.0112 | M51: 8560 | N51: https://twitterscore.io/twitter/p2ecoin91/overview/
A52: 45 | B52: @heedan123 | C52: 3 | D52: D | G52: 4720 | I52: KR | J52: P4 | K52: 1302 | L52: 0.0288 | M52: 7220 | N52: https://twitterscore.io/twitter/heedan123/overview/
A53: 46 | B53: @woody_research | C53: 3 | D53: D | E53: 보류 | F53: 6 | G53: 21200 | H53: 0.00028301887 | I53: Global | J53: P4 | K53: 3431 | L53: 0.0069 | M53: 2046 | N53: https://twitterscore.io/twitter/woody_research/overview/
A54: 47 | B54: @TheP2E_NFT | C54: 2 | D54: D | F54: 6 | G54: 7220 | H54: 0.00083102493 | I54: KR | J54: 비활동 | M54: 100000 | N54: https://twitterscore.io/twitter/TheP2E_NFT/overview/
A55: 48 | B55: @nftroro | C55: 2 | D55: D | G55: 2480 | I55: KR | J55: 비활동 | M55: 11500 | N55: https://twitterscore.io/twitter/nftroro/overview/
A56: 49 | B56: @Stay1104 | C56: 2 | D56: D | F56: 6 | G56: 2880 | H56: 0.0020833333 | I56: KR | J56: P4 | K56: 89 | L56: 0.0224 | M56: 2686 | N56: https://twitterscore.io/twitter/Stay1104/overview/
A57: 50 | B57: @0xsangp | C57: 1 | D57: D | G57: 1860 | I57: KR | J57: P4 | K57: 36 | M57: 7220 | N57: https://twitterscore.io/twitter/0xsangp/overview/
A58: 51 | B58: @midrizzy1 | C58: 1 | D58: D | E58: 보류 | F58: 6 | G58: 89800 | H58: 6.6815145e-05 | I58: Global | J58: P1 | K58: 62411 | L58: 0.028 | M58: 18273 | N58: https://twitterscore.io/twitter/midrizzy1/overview/
A59: 52 | B59: @fried_dev | C59: 0 | D59: D | F59: 4 | G59: 1200 | H59: 0.0033333333 | I59: Global | J59: 비활동 | M59: 4010 | N59: https://twitterscore.io/twitter/fried_dev/overview/
A60: 53 | B60: @0xCryptoAmbush | C60: 0 | D60: D | G60: 797 | I60: Global | J60: 비활동 | M60: 334 | N60: https://twitterscore.io/twitter/0xCryptoAmbush/overview/
A61: 54 | B61: @Xrtrashbin | E61: 조회불가 | I61: KR | J61: 비활동 | M61: 12800 | N61: https://twitterscore.io/twitter/Xrtrashbin/overview/
A62: 55 | B62: @kepochnik_ | E62: 조회불가 | I62: Global | J62: 없음 | M62: 8098 | N62: https://twitterscore.io/twitter/kepochnik_/overview/
A63: 56 | B63: @BULLX132 | E63: 조회불가 | I63: Global | J63: 없음 | M63: 177 | N63: https://twitterscore.io/twitter/BULLX132/overview/

Sheet KOL Rounds 선정
A1: KOL Rounds 선정 · 선정 이유 (v0.2 · 2026-09-28)
A2: ■ KOL 라운드 = 노드 판매 엔진 (로드맵 v0.1 베팅 ②): KOL이 노드를 구매하고 레퍼럴·할인으로 자기 커뮤니티에 판매 → 조회 규모보다 '팔로워가 실제로 반응하는가'를 우선
A3: ■ 선정 규칙 [제안] ① 퍼포먼스 P1–P2 ② 전환 신호: X ER 0.6%+ / TG 도달률 8%+ / YT 롱폼 도달률 5%+ ③ 30일 게시 충분 (X 10·TG 8·YT 3건+) ④ 리스크 없음
A4: ■ 분류: ①②③④ 충족 = 1차 · ③ 미달 = 예비(활동 재확인) · P3지만 ②③ 충족 = 예비(2차 충원) · ② 미달 = 런칭 홍보용 · ④ 해당 = 보류
A5: ■ 결과: 1차 · 한국 8 · 1차 · 글로벌 12 · 예비 (활동 재확인) 4 · 예비 (2차 충원) 18 · 런칭 홍보용 7 · 보류 3 (나머지 P3·P4·비활동은 제외 — 각 채널 탭에서 확인)
A6: ■ ⚠️ 적합성(홍보 이력)·노드 구매 의향은 미측정 → '접촉 전 확인' 칸 · 라운드 조건(할인·레퍼럴·수량)은 미정 (Open Decisions D3)
G8: 근거 (9/28 실측)
A9: 구분 | B9: # | C9: KOL | D9: 지역 | E9: 선정 채널 | F9: 퍼포먼스 | G9: 핵심 KPI (30일) | H9: Twitter Score | I9: 선정 이유 | J9: 메모 | K9: 접촉 전 확인 | L9: 링크
A10: 1차 · 한국 | B10: 1 | C10: 코인하는 해달 | D10: 한국 | E10: Telegram | F10: P1 | G10: TG 30일 133건 · 중앙 조회 5,000 · 구독 30,100 · 도달률 16.6% | I10: P1 · 매 글 구독자 17%가 조회 — 결속 강한 TG 커뮤니티라 노드 레퍼럴 판매에 적합 | J10: 한국 1위 | K10: 적합성(DePIN·노드·XRP 홍보 이력, 스캠 홍보 이력) · 연락 창구 · 노드 구매 의향 · 유료 표기 수용 | L10: https://t.me/seaotterbtc
A11: 1차 · 한국 | B11: 2 | C11: 졸업준비위원회 | D11: 한국 | E11: Telegram | F11: P2 | G11: TG 30일 157건 · 중앙 조회 2,830 · 구독 23,000 · 도달률 12.3% | I11: P2 · 매 글 구독자 12%가 조회 — 결속 강한 TG 커뮤니티라 노드 레퍼럴 판매에 적합 | K11: 적합성(DePIN·노드·XRP 홍보 이력, 스캠 홍보 이력) · 연락 창구 · 노드 구매 의향 · 유료 표기 수용 | L11: https://t.me/officialunivercityofcrypto
A12: 1차 · 한국 | B12: 3 | C12: 신기돈 | D12: 한국 | E12: Telegram | F12: P2 | G12: TG 30일 137건 · 중앙 조회 1,840 · 구독 22,900 · 도달률 8.0% | I12: P2 · 매 글 구독자 8%가 조회 — 결속 강한 TG 커뮤니티라 노드 레퍼럴 판매에 적합 | K12: 적합성(DePIN·노드·XRP 홍보 이력, 스캠 홍보 이력) · 연락 창구 · 노드 구매 의향 · 유료 표기 수용 | L12: https://t.me/tlsrltnf
A13: 1차 · 한국 | B13: 4 | C13: Crypto Judy | D13: 한국 | E13: Telegram | F13: P2 | G13: TG 30일 839건 · 중앙 조회 2,210 · 구독 17,400 · 도달률 12.7% | I13: P2 · 매 글 구독자 13%가 조회 — 결속 강한 TG 커뮤니티라 노드 레퍼럴 판매에 적합 | J13: 하루 28건+ · 30일 일부만 수집 | K13: 적합성(DePIN·노드·XRP 홍보 이력, 스캠 홍보 이력) · 연락 창구 · 노드 구매 의향 · 유료 표기 수용 | L13: https://t.me/lovejudylee
A14: 1차 · 한국 | B14: 5 | C14: 킬베로스 | D14: 한국 | E14: Telegram | F14: P2 | G14: TG 30일 38건 · 중앙 조회 1,650 · 구독 15,100 · 도달률 10.9% | I14: P2 · 매 글 구독자 11%가 조회 — 결속 강한 TG 커뮤니티라 노드 레퍼럴 판매에 적합 | J14: 8/25 대비 하락 | K14: 적합성(DePIN·노드·XRP 홍보 이력, 스캠 홍보 이력) · 연락 창구 · 노드 구매 의향 · 유료 표기 수용 | L14: https://t.me/killberosDAO
A15: 1차 · 한국 | B15: 6 | C15: 라오니 | D15: 한국 | E15: Telegram | F15: P2 | G15: TG 30일 329건 · 중앙 조회 2,200 · 구독 14,900 · 도달률 14.8% | I15: P2 · 매 글 구독자 15%가 조회 — 결속 강한 TG 커뮤니티라 노드 레퍼럴 판매에 적합 | K15: 적합성(DePIN·노드·XRP 홍보 이력, 스캠 홍보 이력) · 연락 창구 · 노드 구매 의향 · 유료 표기 수용 | L15: https://t.me/Raoni1
A16: 1차 · 한국 | B16: 7 | C16: 크립토마카세 | D16: 한국 | E16: Telegram | F16: P2 | G16: TG 30일 25건 · 중앙 조회 1,830 · 구독 11,000 · 도달률 16.6% | I16: P2 · 매 글 구독자 17%가 조회 — 결속 강한 TG 커뮤니티라 노드 레퍼럴 판매에 적합 | J16: 저빈도 · 고효율 | K16: 적합성(DePIN·노드·XRP 홍보 이력, 스캠 홍보 이력) · 연락 창구 · 노드 구매 의향 · 유료 표기 수용 | L16: https://t.me/cryptomacase
A17: 1차 · 한국 | B17: 8 | C17: 매실남 | D17: 한국 | E17: YouTube | F17: P2 | G17: YT 롱폼 30일 3건 · 중앙 조회 6,200 · 구독 10,200 · 도달률 60.8% | I17: P2 · 롱폼 중앙 조회가 구독자의 61% — 설명형 콘텐츠로 노드 구조 전달에 적합 | K17: 적합성(DePIN·노드·XRP 홍보 이력, 스캠 홍보 이력) · 연락 창구 · 노드 구매 의향 · 유료 표기 수용 | L17: https://www.youtube.com/@pluman
A18: 1차 · 글로벌 | B18: 1 | C18: @FefeDemeny | D18: 글로벌 | E18: YouTube | F18: P1 | G18: YT 롱폼 30일 18건 · 중앙 조회 13,000 · 구독 42,500 · 도달률 30.6% | H18: 59 (B) | I18: P1 · 롱폼 중앙 조회가 구독자의 31% — 설명형 콘텐츠로 노드 구조 전달에 적합 | J18: 다른 채널: X P2 | K18: 적합성(DePIN·노드·XRP 홍보 이력, 스캠 홍보 이력) · 연락 창구 · 노드 구매 의향 · 유료 표기 수용 | L18: https://www.youtube.com/@100xclub
A19: 1차 · 글로벌 | B19: 2 | C19: Gatzkiee | D19: 글로벌 | E19: YouTube | F19: P1 | G19: YT 롱폼 30일 12건 · 중앙 조회 14,000 · 구독 35,200 · 도달률 39.8% | I19: P1 · 롱폼 중앙 조회가 구독자의 40% — 설명형 콘텐츠로 노드 구조 전달에 적합 | K19: 적합성(DePIN·노드·XRP 홍보 이력, 스캠 홍보 이력) · 연락 창구 · 노드 구매 의향 · 유료 표기 수용 | L19: https://www.youtube.com/@Gatzkiee
A20: 1차 · 글로벌 | B20: 3 | C20: @eliz883 | D20: 글로벌 | E20: X | F20: P1 | G20: X 30일 304건 · 평균 조회 85,107 · ER 0.66% · 반응 562/건 | H20: 133 (A) | I20: P1 퍼포먼스 + ER 0.66% (기준 0.6%+) — 팔로워가 실제로 반응하는 채널이라 레퍼럴 판매 전환 기대 | J20: 다른 채널: YT 비활동 | K20: 적합성(DePIN·노드·XRP 홍보 이력, 스캠 홍보 이력) · 연락 창구 · 노드 구매 의향 · 유료 표기 수용 | L20: https://x.com/eliz883
A21: 1차 · 글로벌 | B21: 4 | C21: @CryptoPoseidonn | D21: 글로벌 | E21: X | F21: P1 | G21: X 30일 11건 · 평균 조회 74,045 · ER 0.89% · 반응 659/건 | H21: 128 (A) | I21: P1 퍼포먼스 + ER 0.89% (기준 0.6%+) — 팔로워가 실제로 반응하는 채널이라 레퍼럴 판매 전환 기대 | J21: 다른 채널: TG P3 · 도달률 42% · 효율 최상 | K21: 적합성(DePIN·노드·XRP 홍보 이력, 스캠 홍보 이력) · 연락 창구 · 노드 구매 의향 · 유료 표기 수용 | L21: https://x.com/CryptoPoseidonn
A22: 1차 · 글로벌 | B22: 5 | C22: @IncomeSharks | D22: 글로벌 | E22: X | F22: P1 | G22: X 30일 40건 · 평균 조회 89,477 · ER 0.78% · 반응 698/건 | H22: 235 (S) | I22: P1 퍼포먼스 + ER 0.78% (기준 0.6%+) — 팔로워가 실제로 반응하는 채널이라 레퍼럴 판매 전환 기대 | J22: 다른 채널: YT 비활동 | K22: 적합성(DePIN·노드·XRP 홍보 이력, 스캠 홍보 이력) · 연락 창구 · 노드 구매 의향 · 유료 표기 수용 | L22: https://x.com/IncomeSharks
A23: 1차 · 글로벌 | B23: 6 | C23: @PhilakoneCrypto | D23: 글로벌 | E23: YouTube | F23: P2 | G23: YT 롱폼 30일 3건 · 중앙 조회 5,300 · 구독 85,700 · 도달률 6.2% | H23: 52 (B) | I23: P2 · 롱폼 중앙 조회가 구독자의 6% — 설명형 콘텐츠로 노드 구조 전달에 적합 | J23: 다른 채널: X P3 | K23: 적합성(DePIN·노드·XRP 홍보 이력, 스캠 홍보 이력) · 연락 창구 · 노드 구매 의향 · 유료 표기 수용 | L23: https://www.youtube.com/@philakonecrypto
A24: 1차 · 글로벌 | B24: 7 | C24: @ItsRagnarYT | D24: 글로벌 | E24: YouTube | F24: P2 | G24: YT 롱폼 30일 5건 · 중앙 조회 5,600 · 구독 35,900 · 도달률 15.6% | H24: 39 (C) | I24: P2 · 롱폼 중앙 조회가 구독자의 16% — 설명형 콘텐츠로 노드 구조 전달에 적합 | J24: 다른 채널: X 비활동 | K24: 적합성(DePIN·노드·XRP 홍보 이력, 스캠 홍보 이력) · 연락 창구 · 노드 구매 의향 · 유료 표기 수용 | L24: https://www.youtube.com/@ItsRagnar
A25: 1차 · 글로벌 | B25: 8 | C25: @EricCryptoman | D25: 글로벌 | E25: Telegram | F25: P2 | G25: TG 30일 105건 · 중앙 조회 2,710 · 구독 31,300 · 도달률 8.7% | H25: 227 (S) | I25: P2 · 매 글 구독자 9%가 조회 — 결속 강한 TG 커뮤니티라 노드 레퍼럴 판매에 적합 | J25: 다른 채널: X P2 | K25: 적합성(DePIN·노드·XRP 홍보 이력, 스캠 홍보 이력) · 연락 창구 · 노드 구매 의향 · 유료 표기 수용 | L25: https://t.me/Erics_Calls
A26: 1차 · 글로벌 | B26: 9 | C26: @ColdBloodShill | D26: 글로벌 | E26: X | F26: P2 | G26: X 30일 146건 · 평균 조회 38,127 · ER 0.68% · 반응 259/건 | H26: 423 (S) | I26: P2 퍼포먼스 + ER 0.68% (기준 0.6%+) — 팔로워가 실제로 반응하는 채널이라 레퍼럴 판매 전환 기대 | J26: 다른 채널: YT 비활동 | K26: 적합성(DePIN·노드·XRP 홍보 이력, 스캠 홍보 이력) · 연락 창구 · 노드 구매 의향 · 유료 표기 수용 | L26: https://x.com/ColdBloodShill
A27: 1차 · 글로벌 | B27: 10 | C27: @DeRonin_ | D27: 글로벌 | E27: X | F27: P2 | G27: X 30일 48건 · 평균 조회 39,946 · ER 0.96% · 반응 383/건 | H27: 153 (A) | I27: P2 퍼포먼스 + ER 0.96% (기준 0.6%+) — 팔로워가 실제로 반응하는 채널이라 레퍼럴 판매 전환 기대 | J27: 다른 채널: TG 비활동 · 가성비 후보 | K27: 적합성(DePIN·노드·XRP 홍보 이력, 스캠 홍보 이력) · 연락 창구 · 노드 구매 의향 · 유료 표기 수용 | L27: https://x.com/DeRonin_
A28: 1차 · 글로벌 | B28: 11 | C28: @inmortalcrypto | D28: 글로벌 | E28: X | F28: P2 | G28: X 30일 42건 · 평균 조회 25,898 · ER 1.13% · 반응 293/건 | H28: 145 (A) | I28: P2 퍼포먼스 + ER 1.13% (기준 0.6%+) — 팔로워가 실제로 반응하는 채널이라 레퍼럴 판매 전환 기대 | J28: 다른 채널: YT 비활동 | K28: 적합성(DePIN·노드·XRP 홍보 이력, 스캠 홍보 이력) · 연락 창구 · 노드 구매 의향 · 유료 표기 수용 | L28: https://x.com/inmortalcrypto
A29: 1차 · 글로벌 | B29: 12 | C29: @follis_ | D29: 글로벌 | E29: X | F29: P2 | G29: X 30일 145건 · 평균 조회 26,419 · ER 1.09% · 반응 288/건 | H29: 121 (A) | I29: P2 퍼포먼스 + ER 1.09% (기준 0.6%+) — 팔로워가 실제로 반응하는 채널이라 레퍼럴 판매 전환 기대 | J29: 다른 채널: YT P3 | K29: 적합성(DePIN·노드·XRP 홍보 이력, 스캠 홍보 이력) · 연락 창구 · 노드 구매 의향 · 유료 표기 수용 | L29: https://x.com/follis_
A30: 예비 (활동 재확인) | B30: 1 | C30: InsaneonCrypto | D30: 글로벌 | E30: YouTube | F30: P1 | G30: YT 롱폼 30일 2건 · 중앙 조회 10,000 · 구독 21,600 · 도달률 46.3% | I30: P1 · 도달률 46.3%로 조건은 충족하나 30일 게시 2건으로 표본이 작음 → 활동 재확인 후 1차 편입 | K30: 최근 2주 게시 재측정 → 기준 충족 시 1차 편입 | L30: https://www.youtube.com/@InsaneonCrypto
A31: 예비 (활동 재확인) | B31: 2 | C31: CoinFluencer | D31: 한국 | E31: Telegram | F31: P1 | G31: TG 30일 4건 · 중앙 조회 3,290 · 구독 6,630 · 도달률 49.6% | H31: 2 (D) | I31: P1 · 도달률 49.6%로 조건은 충족하나 30일 게시 4건으로 표본이 작음 → 활동 재확인 후 1차 편입 | J31: 다른 채널: X 비활동, YT P2 · 저빈도 (마지막 9/17) | K31: 최근 2주 게시 재측정 → 기준 충족 시 1차 편입 | L31: https://t.me/hjwnews
A32: 예비 (활동 재확인) | B32: 3 | C32: 코백남 | D32: 한국 | E32: YouTube | F32: P2 | G32: YT 롱폼 30일 1건 · 중앙 조회 4,300 · 구독 57,900 · 도달률 7.4% | I32: P2 · 도달률 7.4%로 조건은 충족하나 30일 게시 1건으로 표본이 작음 → 활동 재확인 후 1차 편입 | J32: 다른 채널: TG P3 · TG 채널 병행 | K32: 최근 2주 게시 재측정 → 기준 충족 시 1차 편입 | L32: https://www.youtube.com/@cobacknam
A33: 예비 (활동 재확인) | B33: 4 | C33: jobless | D33: 한국 | E33: Telegram | F33: P2 | G33: TG 30일 6건 · 중앙 조회 1,750 · 구독 6,050 · 도달률 28.9% | I33: P2 · 도달률 28.9%로 조건은 충족하나 30일 게시 6건으로 표본이 작음 → 활동 재확인 후 1차 편입 | J33: 저빈도 (마지막 9/3) | K33: 최근 2주 게시 재측정 → 기준 충족 시 1차 편입 | L33: https://t.me/Jobless_investor
A34: 예비 (2차 충원) | B34: 1 | C34: @0xjayn3 | D34: 글로벌 | E34: X | F34: P3 | G34: X 30일 56건 · 평균 조회 5,937 · ER 0.98% · 반응 58/건 | H34: 26 (C) | I34: P3 규모지만 ER 0.98%로 전환 신호 강함 → 1차 레퍼럴 성과 리뷰 후 2차 충원 | J34: 다른 채널: TG P4 · 게시량 과다 · 30일은 9/22 이후만 수집 | K34: 최근 2주 게시 재측정 → 기준 충족 시 1차 편입 | L34: https://x.com/0xjayn3
A35: 예비 (2차 충원) | B35: 2 | C35: Indep | D35: 글로벌 | E35: YouTube | F35: P3 | G35: YT 롱폼 30일 5건 · 중앙 조회 1,400 · 구독 14,500 · 도달률 9.7% | I35: P3 규모지만 도달률 9.7%로 전환 신호 강함 → 1차 레퍼럴 성과 리뷰 후 2차 충원 | K35: 최근 2주 게시 재측정 → 기준 충족 시 1차 편입 | L35: https://www.youtube.com/@Indep15
A36: 예비 (2차 충원) | B36: 3 | C36: @AltcoinSherpa | D36: 글로벌 | E36: X | F36: P3 | G36: X 30일 530건 · 평균 조회 14,357 · ER 0.83% · 반응 119/건 | H36: 280 (S) | I36: P3 규모지만 ER 0.83%로 전환 신호 강함 → 1차 레퍼럴 성과 리뷰 후 2차 충원 | J36: 다른 채널: YT 비활동 · 30일 530건 → 스폰서 글 묻힘 위험 | K36: 최근 2주 게시 재측정 → 기준 충족 시 1차 편입 | L36: https://x.com/AltcoinSherpa
A37: 예비 (2차 충원) | B37: 4 | C37: @spacexbt | D37: 글로벌 | E37: X | F37: P3 | G37: X 30일 31건 · 평균 조회 10,491 · ER 0.62% · 반응 65/건 | H37: 91 (B) | I37: P3 규모지만 ER 0.62%로 전환 신호 강함 → 1차 레퍼럴 성과 리뷰 후 2차 충원 | J37: 다른 채널: TG 비활동 | K37: 최근 2주 게시 재측정 → 기준 충족 시 1차 편입 | L37: https://x.com/spacexbt
A38: 예비 (2차 충원) | B38: 5 | C38: @w1nklerr | D38: 글로벌 | E38: X | F38: P3 | G38: X 30일 39건 · 평균 조회 12,384 · ER 0.68% · 반응 84/건 | H38: 8 (D) | I38: P3 규모지만 ER 0.68%로 전환 신호 강함 → 1차 레퍼럴 성과 리뷰 후 2차 충원 | J38: 다른 채널: TG P3 · 30일은 9/11 이후만 수집 · 유료 파트너십 게시 있음 | K38: 최근 2주 게시 재측정 → 기준 충족 시 1차 편입 | L38: https://x.com/w1nklerr
A39: 예비 (2차 충원) | B39: 6 | C39: @DeFiOracle_ | D39: 글로벌 | E39: X | F39: P3 | G39: X 30일 18건 · 평균 조회 7,805 · ER 1.48% · 반응 116/건 | H39: 46 (B) | I39: P3 규모지만 ER 1.48%로 전환 신호 강함 → 1차 레퍼럴 성과 리뷰 후 2차 충원 | J39: 다른 채널: TG 비활동 | K39: 최근 2주 게시 재측정 → 기준 충족 시 1차 편입 | L39: https://x.com/DeFiOracle_
A40: 예비 (2차 충원) | B40: 7 | C40: @evancrypt | D40: 글로벌 | E40: X | F40: P3 | G40: X 30일 31건 · 평균 조회 5,881 · ER 1.35% · 반응 79/건 | H40: 46 (B) | I40: P3 규모지만 ER 1.35%로 전환 신호 강함 → 1차 레퍼럴 성과 리뷰 후 2차 충원 | J40: 다른 채널: TG P4 | K40: 최근 2주 게시 재측정 → 기준 충족 시 1차 편입 | L40: https://x.com/evancrypt
A41: 예비 (2차 충원) | B41: 8 | C41: T.A Crypto | D41: 한국 | E41: Telegram | F41: P3 | G41: TG 30일 256건 · 중앙 조회 1,010 · 구독 8,060 · 도달률 12.5% | I41: P3 규모지만 도달률 12.5%로 전환 신호 강함 → 1차 레퍼럴 성과 리뷰 후 2차 충원 | J41: 다른 채널: YT P3 | K41: 최근 2주 게시 재측정 → 기준 충족 시 1차 편입 | L41: https://t.me/yul_papa
A42: 예비 (2차 충원) | B42: 9 | C42: BMT | D42: 한국 | E42: Telegram | F42: P3 | G42: TG 30일 84건 · 중앙 조회 1,200 · 구독 13,700 · 도달률 8.8% | I42: P3 규모지만 도달률 8.8%로 전환 신호 강함 → 1차 레퍼럴 성과 리뷰 후 2차 충원 | K42: 최근 2주 게시 재측정 → 기준 충족 시 1차 편입 | L42: https://t.me/BMTube
A43: 예비 (2차 충원) | B43: 10 | C43: 알파스쿨 | D43: 한국 | E43: Telegram | F43: P3 | G43: TG 30일 101건 · 중앙 조회 1,300 · 구독 10,800 · 도달률 12.0% | H43: 4 (D) | I43: P3 규모지만 도달률 12.0%로 전환 신호 강함 → 1차 레퍼럴 성과 리뷰 후 2차 충원 | J43: 다른 채널: X P4, X P4 | K43: 최근 2주 게시 재측정 → 기준 충족 시 1차 편입 | L43: https://t.me/AlphaSchool77
A44: 예비 (2차 충원) | B44: 11 | C44: BQ 비큐 | D44: 한국 | E44: Telegram | F44: P3 | G44: TG 30일 98건 · 중앙 조회 821 · 구독 9,600 · 도달률 8.6% | I44: P3 규모지만 도달률 8.6%로 전환 신호 강함 → 1차 레퍼럴 성과 리뷰 후 2차 충원 | K44: 최근 2주 게시 재측정 → 기준 충족 시 1차 편입 | L44: https://t.me/BQTelegram
A45: 예비 (2차 충원) | B45: 12 | C45: 바나나우유 일기장 | D45: 한국 | E45: Telegram | F45: P3 | G45: TG 30일 10건 · 중앙 조회 892 · 구독 8,760 · 도달률 10.2% | I45: P3 규모지만 도달률 10.2%로 전환 신호 강함 → 1차 레퍼럴 성과 리뷰 후 2차 충원 | K45: 최근 2주 게시 재측정 → 기준 충족 시 1차 편입 | L45: https://t.me/Bananamilkrich
A46: 예비 (2차 충원) | B46: 13 | C46: 개인적인 DYOR | D46: 한국 | E46: Telegram | F46: P3 | G46: TG 30일 67건 · 중앙 조회 976 · 구독 9,730 · 도달률 10.0% | I46: P3 규모지만 도달률 10.0%로 전환 신호 강함 → 1차 레퍼럴 성과 리뷰 후 2차 충원 | K46: 최근 2주 게시 재측정 → 기준 충족 시 1차 편입 | L46: https://t.me/LEEHEESANGDYOR
A47: 예비 (2차 충원) | B47: 14 | C47: 크립토폴유 | D47: 한국 | E47: Telegram | F47: P3 | G47: TG 30일 35건 · 중앙 조회 766 · 구독 7,620 · 도달률 10.1% | I47: P3 규모지만 도달률 10.1%로 전환 신호 강함 → 1차 레퍼럴 성과 리뷰 후 2차 충원 | K47: 최근 2주 게시 재측정 → 기준 충족 시 1차 편입 | L47: https://t.me/cryptoforu12
A48: 예비 (2차 충원) | B48: 15 | C48: Trader Hyun | D48: 한국 | E48: Telegram | F48: P3 | G48: TG 30일 14건 · 중앙 조회 880 · 구독 6,530 · 도달률 13.5% | I48: P3 규모지만 도달률 13.5%로 전환 신호 강함 → 1차 레퍼럴 성과 리뷰 후 2차 충원 | K48: 최근 2주 게시 재측정 → 기준 충족 시 1차 편입 | L48: https://t.me/TraderHyun
A49: 예비 (2차 충원) | B49: 16 | C49: 21M 포밍 | D49: 한국 | E49: Telegram | F49: P3 | G49: TG 30일 8건 · 중앙 조회 567 · 구독 5,540 · 도달률 10.2% | I49: P3 규모지만 도달률 10.2%로 전환 신호 강함 → 1차 레퍼럴 성과 리뷰 후 2차 충원 | J49: 8/25 대비 하락 | K49: 최근 2주 게시 재측정 → 기준 충족 시 1차 편입 | L49: https://t.me/vc_21m
A50: 예비 (2차 충원) | B50: 17 | C50: 코인위키 | D50: 한국 | E50: Telegram | F50: P3 | G50: TG 30일 82건 · 중앙 조회 615 · 구독 5,910 · 도달률 10.4% | I50: P3 규모지만 도달률 10.4%로 전환 신호 강함 → 1차 레퍼럴 성과 리뷰 후 2차 충원 | K50: 최근 2주 게시 재측정 → 기준 충족 시 1차 편입 | L50: https://t.me/CoinWiki_MMWW
A51: 예비 (2차 충원) | B51: 18 | C51: A라는 사람 | D51: 한국 | E51: Telegram | F51: P3 | G51: TG 30일 18건 · 중앙 조회 707 · 구독 3,920 · 도달률 18.0% | I51: P3 규모지만 도달률 18.0%로 전환 신호 강함 → 1차 레퍼럴 성과 리뷰 후 2차 충원 | J51: 8/25 대비 하락 | K51: 최근 2주 게시 재측정 → 기준 충족 시 1차 편입 | L51: https://t.me/aispersons
A52: 런칭 홍보용 | B52: 1 | C52: @Trader_XO | D52: 글로벌 | E52: X | F52: P1 | G52: X 30일 59건 · 평균 조회 85,386 · ER 0.48% · 반응 410/건 | H52: 270 (S) | I52: P1 도달은 크지만 ER 0.48% (기준 0.6% 미만) → 판매 전환보다 런칭 노출용으로 활용 | J52: 다른 채널: YT 비활동 | K52: 런칭 게시 단가 · 유료 표기 수용 · 게시 일정 | L52: https://x.com/Trader_XO
A53: 런칭 홍보용 | B53: 2 | C53: 취미생활방 | D53: 한국 | E53: Telegram | F53: P1 | G53: TG 30일 431건 · 중앙 조회 3,010 · 구독 49,700 · 도달률 6.1% | I53: P1 도달은 크지만 도달률 6.1% (기준 8% 미만) → 판매 전환보다 런칭 노출용으로 활용 | J53: 하루 14건 → 고정 필요 | K53: 런칭 게시 단가 · 유료 표기 수용 · 게시 일정 | L53: https://t.me/enjoymyhobby
A54: 런칭 홍보용 | B54: 3 | C54: @rektcapital | D54: 글로벌 | E54: X | F54: P2 | G54: X 30일 81건 · 평균 조회 65,242 · ER 0.53% · 반응 346/건 | H54: 193 (A) | I54: P2 도달은 크지만 ER 0.53% (기준 0.6% 미만) → 판매 전환보다 런칭 노출용으로 활용 | J54: 다른 채널: YT 비활동 | K54: 런칭 게시 단가 · 유료 표기 수용 · 게시 일정 | L54: https://x.com/rektcapital
A55: 런칭 홍보용 | B55: 4 | C55: @nobrainflip | D55: 글로벌 | E55: X | F55: P2 | G55: X 30일 71건 · 평균 조회 80,343 · ER 0.41% · 반응 329/건 | H55: 163 (A) | I55: P2 도달은 크지만 ER 0.41% (기준 0.6% 미만) → 판매 전환보다 런칭 노출용으로 활용 | J55: 다른 채널: TG P2 | K55: 런칭 게시 단가 · 유료 표기 수용 · 게시 일정 | L55: https://x.com/nobrainflip
A56: 런칭 홍보용 | B56: 5 | C56: @MuroCrypto | D56: 글로벌 | E56: X | F56: P2 | G56: X 30일 147건 · 평균 조회 35,672 · ER 0.48% · 반응 171/건 | H56: 143 (A) | I56: P2 도달은 크지만 ER 0.48% (기준 0.6% 미만) → 판매 전환보다 런칭 노출용으로 활용 | J56: 다른 채널: YT P4 | K56: 런칭 게시 단가 · 유료 표기 수용 · 게시 일정 | L56: https://x.com/MuroCrypto
A57: 런칭 홍보용 | B57: 6 | C57: 잼민123 | D57: 한국 | E57: Telegram | F57: P2 | G57: TG 30일 430건 · 중앙 조회 1,690 · 구독 26,200 · 도달률 6.5% | I57: P2 도달은 크지만 도달률 6.5% (기준 8% 미만) → 판매 전환보다 런칭 노출용으로 활용 | J57: 다른 채널: YT 비활동 | K57: 런칭 게시 단가 · 유료 표기 수용 · 게시 일정 | L57: https://t.me/mujammin123
A58: 런칭 홍보용 | B58: 7 | C58: 마샬 | D58: 한국 | E58: Telegram | F58: P2 | G58: TG 30일 154건 · 중앙 조회 1,730 · 구독 21,700 · 도달률 8.0% | I58: P2 도달은 크지만 도달률 7.97% (기준 8% 미만) → 판매 전환보다 런칭 노출용으로 활용 | K58: 런칭 게시 단가 · 유료 표기 수용 · 게시 일정 | L58: https://t.me/marshallog
A59: 보류 | B59: 1 | C59: @midrizzy1 | D59: 글로벌 | E59: X | F59: P1 | G59: X 30일 11건 · 평균 조회 62,411 · ER 2.80% · 반응 1,748/건 | H59: 1 (D) | I59: 포렉스·라이프스타일 게시 비중 높음 · TwitterScore 1 → 크립토 노드 구매층과 오디언스 불일치 가능 | J59: 포렉스·라이프스타일 비중 높음 | K59: 사유 해소 여부 확인 후 재검토 | L59: https://x.com/midrizzy1
A60: 보류 | B60: 2 | C60: @DaanCrypto | D60: 글로벌 | E60: X | F60: P2 | G60: X 30일 7건 · 평균 조회 20,832 · ER 0.82% · 반응 171/건 | H60: 192 (A) | I60: 8/30 이후 X 게시 없음 → 라운드 기간 활동 불확실 | J60: 다른 채널: YT 비활동 · 8/30 이후 게시 없음 | K60: 사유 해소 여부 확인 후 재검토 | L60: https://x.com/DaanCrypto
A61: 보류 | B61: 3 | C61: @haloETH | D61: 글로벌 | E61: X | F61: P2 | G61: X 30일 16건 · 평균 조회 5,438 · ER 3.71% · 반응 202/건 | H61: 47 (B) | I61: ER 3.71%가 답글 비중으로 부풀려짐 (참여 품앗이 의심) → 실제 전환력 판단 불가 | J61: 답글 비중 과다 · 참여 품앗이 의심 | K61: 사유 해소 여부 확인 후 재검토 | L61: https://x.com/haloETH

Sheet 선정 기준
A1: 선정 기준 및 지표 정의
A2: 기존 기준을 편집 가능한 입력값으로 분리. 경계 구간은 임시 검토 규칙이며 성과로 보정 필요.
A3: 비율은 고유 도달률·구매전환율이 아님. 숫자를 바꾸면 연결된 등급·후보 분류가 갱신됩니다.
A4: 채널 | B4: P1 최소 | C4: P2 최소 | D4: P3 최소 | E4: 최소 표본 | F4: 검토 비율 기준 | G4: 경계 폭 ± | H4: 기준 지표 | I4: 비율 정의
A5: X | B5: 400 | C5: 150 | D5: 50 | E5: 10 | F5: 0.006 | G5: 0.0005 | H5: 게시물당 공개 반응 수 | I5: (좋아요+답글+리포스트)÷조회
A6: Telegram | B6: 3000 | C6: 1500 | D6: 500 | E6: 8 | F6: 0.08 | G6: 0.005 | H6: 표본 게시물 중앙 조회 | I6: 중앙 조회÷구독자
A7: YouTube | B7: 10000 | C7: 3000 | D7: 1000 | E7: 3 | F7: 0.05 | G7: 0.005 | H7: 표본 롱폼 중앙 조회 | I7: 중앙 조회÷구독자
A9: 항목 | B9: 정의
A10: 24시간·7일·30일 | B10: 해당 기간에 게시된 콘텐츠의 수집 시점 누적 조회. 기간 중 발생한 조회 증가량이 아님.
A11: 기간 확인 필요 | B11: 기존 집계 수치는 존재하지만 게시물별 원자료·수집 시작/종료시각으로 전체 기간을 검증하지 못함.
A12: 일부 수집 | B12: 원본 메모에 30일 미수집 또는 일부 기간만 수집이라고 기록된 표본.
A13: 조회 불가 | B13: 비공개·미리보기 제한·공개 수치 미확보. 조회수 0이나 비활동을 의미하지 않음.
A14: 계정 확인 필요 | B14: 404 또는 계정 불일치. 동일 KOL 계정 여부 확인 필요.
A15: 측정 완료 | B15: 게시물 원자료와 수집 시각으로 기간·계정이 확인된 경우에만 수동 선택.
A16: 표본 부족 | B16: 노출 규모 등급은 계산하되, 최소 게시 수 미달 시 우선 접촉 후보로 확정하지 않음.
A17: 경계값 검토 | B17: 비율 기준의 ±경계 폭 안은 양쪽 모두 같은 검토 그룹. 성과 차이로 단정하지 않음.
A18: 봇 비율 | B18: 미측정. TwitterScore·스마트 팔로워 비율·높은 ER로 봇 비율을 대체하지 않음.
A19: 게시 시점 보정 | B19: 24시간·7일·30일 누적값은 노출 경과시간이 다름. 차이를 성장률로 확정하지 않음.
A20: 견적·성과 | B20: 미입력은 공란. 0원·0건이 확인된 경우에만 0 입력. 통화별 합계만 계산.
... A24: 개정 | B24: 2026-09-28: 검증 상태 분리 / 비율 명칭 수정 / 경계값 검토 / 단가·성과 관리 추가

Sheet 측정 관리
A1: 측정 관리
A2: 200개 채널의 기존 집계와 수집 범위를 관리합니다. 빈 날짜·원자료 링크는 미확인입니다.
A3: 수집 시점 누적 조회 기준. 노란 칸은 확인 후 입력하며, 기존 조회·게시·ER 수치는 채널 탭에서 연결됩니다.
A4: 채널 ID | B4: KOL ID | C4: 채널명 | D4: 지역 | E4: 플랫폼 | F4: 채널 URL | G4: 집계 원본 탭 | H4: 기존 측정일 | I4: 수집 시작일 | J4: 수집 종료시각 | K4: 측정 상태 | L4: 수집 한계·메모 | M4: 계정 연결 | N4: 게시물 원자료 URL | O4: 표본 게시 수 | P4: 평균 조회 | Q4: 중앙 조회 | R4: 공개 ER (X) | S4: 구독·팔로워 | T4: 조회÷구독·팔로워 | U4: 퍼포먼스 | V4: 등급 기준값 | W4: 선별 비율 | X4: 비율 기준 | Y4: 최소 표본 | Z4: 기존 등급
A5: WB-C001 | B5: WB-K086 | C5: @midrizzy1 | D5: Global | E5: X | F5: https://x.com/midrizzy1 | G5: 글로벌 X | H5: 46293 | K5: 기간 확인 필요 | L5: 포렉스·라이프스타일 비중 높음 | M5: 기존 목록 연결 | O5: {=IF(_xlfn.XLOOKUP(A5,'글로벌 X'!$X$8:$X$50,'글로벌 X'!$P$8:$P$50,"",0)="","",_xlfn.XLOOKUP(A5,'글로벌 X'!$X$8:$X$50,'글로벌 X'!$P$8:$P$50,"",0))} -> 11 | P5: {=IF(_xlfn.XLOOKUP(A5,'글로벌 X'!$X$8:$X$50,'글로벌 X'!$Q$8:$Q$50,"",0)="","",_xlfn.XLOOKUP(A5,'글로벌 X'!$X$8:$X$50,'글로벌 X'!$Q$8:$Q$50,"",0))} -> 62411 | R5: {=IF(_xlfn.XLOOKUP(A5,'글로벌 X'!$X$8:$X$50,'글로벌 X'!$S$8:$S$50,"",0)="","",_xlfn.XLOOKUP(A5,'글로벌 X'!$X$8:$X$50,'글로벌 X'!$S$8:$S$50,"",0))} -> 0.028 | S5: {=IF(_xlfn.XLOOKUP(A5,'글로벌 X'!$X$8:$X$50,'글로벌 X'!$G$8:$G$50,"",0)="","",_xlfn.XLOOKUP(A5,'글로벌 X'!$X$8:$X$50,'글로벌 X'!$G$8:$G$50,"",0))} -> 89700 | T5: =IF(OR(S5="",S5<=0,IF(E5="X",P5,Q5)=""),"",IF(E5="X",P5,Q5)/S5) -> 0.6957748 | U5: {=IF(OR(K5="조회 불가",K5="계정 확인 필요",O5="",V5=""),"미측정",IF(O5<IF(E5="YouTube",1,3),"저빈도",IF(V5>=_xlfn.XLOOKUP(E5,'선정 기준'!$A$5:$A$7,'선정 기준'!$B$5:$B$7),"P1",IF(V5>=_xlfn.XLOOKUP(E5,'선정 기준'!$A$5:$A$7,'선정 기준'!$C$5:$C$7),"P2",IF(V5>=_xlfn.XLOOKUP(E5,'선정 기준'!$A$5:$A$7,'선정 기준'!$D$5:$D$7),"P3","P4")))))} -> P1 | V5: =IF(E5="X",IF(OR(P5="",R5=""),"",P5*R5),IF(Q5="","",Q5)) -> 1747.508 | W5: =IF(E5="X",IF(R5="","",R5),IF(T5="","",T5)) -> 0.028 | X5: {=_xlfn.XLOOKUP(E5,'선정 기준'!$A$5:$A$7,'선정 기준'!$F$5:$F$7)} -> 0.006 | Y5: {=_xlfn.XLOOKUP(E5,'선정 기준'!$A$5:$A$7,'선정 기준'!$E$5:$E$7)} -> 10 | Z5: P1
A11: WB-C007 | B11: WB-K090 | C11: @rektcapital | D11: Global | E11: X | F11: https://x.com/rektcapital | G11: 글로벌 X | H11: 46293 | K11: 기간 확인 필요 | M11: 기존 목록 연결 | O11: {=IF(_xlfn.XLOOKUP(A11,'글로벌 X'!$X$8:$X$50,'글로벌 X'!$P$8:$P$50,"",0)="","",_xlfn.XLOOKUP(A11,'글로벌 X'!$X$8:$X$50,'글로벌 X'!$P$8:$P$50,"",0))} -> 81 | P11: {=IF(_xlfn.XLOOKUP(A11,'글로벌 X'!$X$8:$X$50,'글로벌 X'!$Q$8:$Q$50,"",0)="","",_xlfn.XLOOKUP(A11,'글로벌 X'!$X$8:$X$50,'글로벌 X'!$Q$8:$Q$50,"",0))} -> 65242 | R11: {=IF(_xlfn.XLOOKUP(A11,'글로벌 X'!$X$8:$X$50,'글로벌 X'!$S$8:$S$50,"",0)="","",_xlfn.XLOOKUP(A11,'글로벌 X'!$X$8:$X$50,'글로벌 X'!$S$8:$S$50,"",0))} -> 0.0053 | S11: {=IF(_xlfn.XLOOKUP(A11,'글로벌 X'!$X$8:$X$50,'글로벌 X'!$G$8:$G$50,"",0)="","",_xlfn.XLOOKUP(A11,'글로벌 X'!$X$8:$X$50,'글로벌 X'!$G$8:$G$50,"",0))} -> 563000 | T11: =IF(OR(S11="",S11<=0,IF(E11="X",P11,Q11)=""),"",IF(E11="X",P11,Q11)/S11) -> 0.11588277 | U11: {=IF(OR(K11="조회 불가",K11="계정 확인 필요",O11="",V11=""),"미측정",IF(O11<IF(E11="YouTube",1,3),"저빈도",IF(V11>=_xlfn.XLOOKUP(E11,'선정 기준'!$A$5:$A$7,'선정 기준'!$B$5:$B$7),"P1",IF(V11>=_xlfn.XLOOKUP(E11,'선정 기준'!$A$5:$A$7,'선정 기준'!$C$5:$C$7),"P2",IF(V11>=_xlfn.XLOOKUP(E11,'선정 기준'!$A$5:$A$7,'선정 기준'!$D$5:$D$7),"P3","P4")))))} -> P2 | V11: =IF(E11="X",IF(OR(P11="",R11=""),"",P11*R11),IF(Q11="","",Q11)) -> 345.7826 | W11: =IF(E11="X",IF(R11="","",R11),IF(T11="","",T11)) -> 0.0053 | X11: {=_xlfn.XLOOKUP(E11,'선정 기준'!$A$5:$A$7,'선정 기준'!$F$5:$F$7)} -> 0.006 | Y11: {=_xlfn.XLOOKUP(E11,'선정 기준'!$A$5:$A$7,'선정 기준'!$E$5:$E$7)} -> 10 | Z11: P2
A39: WB-C035 | B39: WB-K126 | C39: @LookForEntries | D39: Global | E39: X | F39: https://x.com/LookForEntries | G39: 글로벌 X | H39: 46293 | K39: 일부 수집 | L39: 게시량 과다(24h 23건) · 24h만 수집 | M39: 기존 목록 연결 | O39: {=IF(_xlfn.XLOOKUP(A39,'글로벌 X'!$X$8:$X$50,'글로벌 X'!$P$8:$P$50,"",0)="","",_xlfn.XLOOKUP(A39,'글로벌 X'!$X$8:$X$50,'글로벌 X'!$P$8:$P$50,"",0))} | P39: {=IF(_xlfn.XLOOKUP(A39,'글로벌 X'!$X$8:$X$50,'글로벌 X'!$Q$8:$Q$50,"",0)="","",_xlfn.XLOOKUP(A39,'글로벌 X'!$X$8:$X$50,'글로벌 X'!$Q$8:$Q$50,"",0))} | R39: {=IF(_xlfn.XLOOKUP(A39,'글로벌 X'!$X$8:$X$50,'글로벌 X'!$S$8:$S$50,"",0)="","",_xlfn.XLOOKUP(A39,'글로벌 X'!$X$8:$X$50,'글로벌 X'!$S$8:$S$50,"",0))} | S39: {=IF(_xlfn.XLOOKUP(A39,'글로벌 X'!$X$8:$X$50,'글로벌 X'!$G$8:$G$50,"",0)="","",_xlfn.XLOOKUP(A39,'글로벌 X'!$X$8:$X$50,'글로벌 X'!$G$8:$G$50,"",0))} -> 56200 | T39: =IF(OR(S39="",S39<=0,IF(E39="X",P39,Q39)=""),"",IF(E39="X",P39,Q39)/S39) | U39: {=IF(OR(K39="조회 불가",K39="계정 확인 필요",O39="",V39=""),"미측정",IF(O39<IF(E39="YouTube",1,3),"저빈도",IF(V39>=_xlfn.XLOOKUP(E39,'선정 기준'!$A$5:$A$7,'선정 기준'!$B$5:$B$7),"P1",IF(V39>=_xlfn.XLOOKUP(E39,'선정 기준'!$A$5:$A$7,'선정 기준'!$C$5:$C$7),"P2",IF(V39>=_xlfn.XLOOKUP(E39,'선정 기준'!$A$5:$A$7,'선정 기준'!$D$5:$D$7),"P3","P4")))))} -> 미측정 | V39: =IF(E39="X",IF(OR(P39="",R39=""),"",P39*R39),IF(Q39="","",Q39)) | W39: =IF(E39="X",IF(R39="","",R39),IF(T39="","",T39)) | X39: {=_xlfn.XLOOKUP(E39,'선정 기준'!$A$5:$A$7,'선정 기준'!$F$5:$F$7)} -> 0.006 | Y39: {=_xlfn.XLOOKUP(E39,'선정 기준'!$A$5:$A$7,'선정 기준'!$E$5:$E$7)} -> 10 | Z39: P4
A101: WB-C097 | B101: WB-K134 | C101: DeFiImmortal | D101: Global | E101: Telegram | F101: https://t.me/DeFiImmortal | G101: 글로벌 TG | H101: 46293 | K101: 조회 불가 | L101: 웹 미리보기 비공개 (구독자·조회 확인 불가) | M101: 기존 목록 연결 | O101: {=IF(_xlfn.XLOOKUP(A101,'글로벌 TG'!$X$8:$X$35,'글로벌 TG'!$L$8:$L$35,"",0)="","",_xlfn.XLOOKUP(A101,'글로벌 TG'!$X$8:$X$35,'글로벌 TG'!$L$8:$L$35,"",0))} | P101: {=IF(_xlfn.XLOOKUP(A101,'글로벌 TG'!$X$8:$X$35,'글로벌 TG'!$M$8:$M$35,"",0)="","",_xlfn.XLOOKUP(A101,'글로벌 TG'!$X$8:$X$35,'글로벌 TG'!$M$8:$M$35,"",0))} | Q101: {=IF(_xlfn.XLOOKUP(A101,'글로벌 TG'!$X$8:$X$35,'글로벌 TG'!$N$8:$N$35,"",0)="","",_xlfn.XLOOKUP(A101,'글로벌 TG'!$X$8:$X$35,'글로벌 TG'!$N$8:$N$35,"",0))} | S101: {=IF(_xlfn.XLOOKUP(A101,'글로벌 TG'!$X$8:$X$35,'글로벌 TG'!$E$8:$E$35,"",0)="","",_xlfn.XLOOKUP(A101,'글로벌 TG'!$X$8:$X$35,'글로벌 TG'!$E$8:$E$35,"",0))} | T101: =IF(OR(S101="",S101<=0,IF(E101="X",P101,Q101)=""),"",IF(E101="X",P101,Q101)/S101) | U101: {=IF(OR(K101="조회 불가",K101="계정 확인 필요",O101="",V101=""),"미측정",IF(O101<IF(E101="YouTube",1,3),"저빈도",IF(V101>=_xlfn.XLOOKUP(E101,'선정 기준'!$A$5:$A$7,'선정 기준'!$B$5:$B$7),"P1",IF(V101>=_xlfn.XLOOKUP(E101,'선정 기준'!$A$5:$A$7,'선정 기준'!$C$5:$C$7),"P2",IF(V101>=_xlfn.XLOOKUP(E101,'선정 기준'!$A$5:$A$7,'선정 기준'!$D$5:$D$7),"P3","P4")))))} -> 미측정 | V101: =IF(E101="X",IF(OR(P101="",R101=""),"",P101*R101),IF(Q101="","",Q101)) | W101: =IF(E101="X",IF(R101="","",R101),IF(T101="","",T101)) | X101: {=_xlfn.XLOOKUP(E101,'선정 기준'!$A$5:$A$7,'선정 기준'!$F$5:$F$7)} -> 0.08 | Y101: {=_xlfn.XLOOKUP(E101,'선정 기준'!$A$5:$A$7,'선정 기준'!$E$5:$E$7)} -> 8 | Z101: 미측정
A108: WB-C104 | B108: WB-K007 | C108: Crypto Judy | D108: KR | E108: Telegram | F108: https://t.me/lovejudylee | G108: 한국 TG | H108: 46293 | K108: 일부 수집 | L108: 하루 28건+ · 30일 일부만 수집 | M108: 기존 목록 연결 | O108: {=IF(_xlfn.XLOOKUP(A108,'한국 TG'!$X$8:$X$74,'한국 TG'!$K$8:$K$74,"",0)="","",_xlfn.XLOOKUP(A108,'한국 TG'!$X$8:$X$74,'한국 TG'!$K$8:$K$74,"",0))} -> 839 | P108: {=IF(_xlfn.XLOOKUP(A108,'한국 TG'!$X$8:$X$74,'한국 TG'!$L$8:$L$74,"",0)="","",_xlfn.XLOOKUP(A108,'한국 TG'!$X$8:$X$74,'한국 TG'!$L$8:$L$74,"",0))} -> 2416 | Q108: {=IF(_xlfn.XLOOKUP(A108,'한국 TG'!$X$8:$X$74,'한국 TG'!$M$8:$M$74,"",0)="","",_xlfn.XLOOKUP(A108,'한국 TG'!$X$8:$X$74,'한국 TG'!$M$8:$M$74,"",0))} -> 2210 | S108: {=IF(_xlfn.XLOOKUP(A108,'한국 TG'!$X$8:$X$74,'한국 TG'!$E$8:$E$74,"",0)="","",_xlfn.XLOOKUP(A108,'한국 TG'!$X$8:$X$74,'한국 TG'!$E$8:$E$74,"",0))} -> 17400 | T108: =IF(OR(S108="",S108<=0,IF(E108="X",P108,Q108)=""),"",IF(E108="X",P108,Q108)/S108) -> 0.12701149 | U108: {=IF(OR(K108="조회 불가",K108="계정 확인 필요",O108="",V108=""),"미측정",IF(O108<IF(E108="YouTube",1,3),"저빈도",IF(V108>=_xlfn.XLOOKUP(E108,'선정 기준'!$A$5:$A$7,'선정 기준'!$B$5:$B$7),"P1",IF(V108>=_xlfn.XLOOKUP(E108,'선정 기준'!$A$5:$A$7,'선정 기준'!$C$5:$C$7),"P2",IF(V108>=_xlfn.XLOOKUP(E108,'선정 기준'!$A$5:$A$7,'선정 기준'!$D$5:$D$7),"P3","P4")))))} -> P2 | V108: =IF(E108="X",IF(OR(P108="",R108=""),"",P108*R108),IF(Q108="","",Q108)) -> 2210 | W108: =IF(E108="X",IF(R108="","",R108),IF(T108="","",T108)) -> 0.12701149 | X108: {=_xlfn.XLOOKUP(E108,'선정 기준'!$A$5:$A$7,'선정 기준'!$F$5:$F$7)} -> 0.08 | Y108: {=_xlfn.XLOOKUP(E108,'선정 기준'!$A$5:$A$7,'선정 기준'!$E$5:$E$7)} -> 8 | Z108: P2
A166: WB-C162 | B166: WB-K079 | C166: 후니방 | D166: KR | E166: Telegram | F166: https://t.me/hooniebang | G166: 한국 TG | H166: 46293 | K166: 조회 불가 | L166: 미리보기 비공개 | M166: 기존 목록 연결 | O166: {=IF(_xlfn.XLOOKUP(A166,'한국 TG'!$X$8:$X$74,'한국 TG'!$K$8:$K$74,"",0)="","",_xlfn.XLOOKUP(A166,'한국 TG'!$X$8:$X$74,'한국 TG'!$K$8:$K$74,"",0))} | P166: {=IF(_xlfn.XLOOKUP(A166,'한국 TG'!$X$8:$X$74,'한국 TG'!$L$8:$L$74,"",0)="","",_xlfn.XLOOKUP(A166,'한국 TG'!$X$8:$X$74,'한국 TG'!$L$8:$L$74,"",0))} | Q166: {=IF(_xlfn.XLOOKUP(A166,'한국 TG'!$X$8:$X$74,'한국 TG'!$M$8:$M$74,"",0)="","",_xlfn.XLOOKUP(A166,'한국 TG'!$X$8:$X$74,'한국 TG'!$M$8:$M$74,"",0))} | S166: {=IF(_xlfn.XLOOKUP(A166,'한국 TG'!$X$8:$X$74,'한국 TG'!$E$8:$E$74,"",0)="","",_xlfn.XLOOKUP(A166,'한국 TG'!$X$8:$X$74,'한국 TG'!$E$8:$E$74,"",0))} | T166: =IF(OR(S166="",S166<=0,IF(E166="X",P166,Q166)=""),"",IF(E166="X",P166,Q166)/S166) | U166: {=IF(OR(K166="조회 불가",K166="계정 확인 필요",O166="",V166=""),"미측정",IF(O166<IF(E166="YouTube",1,3),"저빈도",IF(V166>=_xlfn.XLOOKUP(E166,'선정 기준'!$A$5:$A$7,'선정 기준'!$B$5:$B$7),"P1",IF(V166>=_xlfn.XLOOKUP(E166,'선정 기준'!$A$5:$A$7,'선정 기준'!$C$5:$C$7),"P2",IF(V166>=_xlfn.XLOOKUP(E166,'선정 기준'!$A$5:$A$7,'선정 기준'!$D$5:$D$7),"P3","P4")))))} -> 미측정 | V166: =IF(E166="X",IF(OR(P166="",R166=""),"",P166*R166),IF(Q166="","",Q166)) | W166: =IF(E166="X",IF(R166="","",R166),IF(T166="","",T166)) | X166: {=_xlfn.XLOOKUP(E166,'선정 기준'!$A$5:$A$7,'선정 기준'!$F$5:$F$7)} -> 0.08 | Y166: {=_xlfn.XLOOKUP(E166,'선정 기준'!$A$5:$A$7,'선정 기준'!$E$5:$E$7)} -> 8 | Z166: 비활동
A191: WB-C187 | B191: WB-K048 | C191: 부의길목에서 | D191: KR | E191: YouTube | F191: https://www.youtube.com/@CoinStay | G191: 한국 YT | H191: 46293 | K191: 계정 확인 필요 | L191: 404 (채널 없음) → 보류 | M191: 기존 목록 연결 | O191: {=IF(_xlfn.XLOOKUP(A191,'한국 YT'!$X$8:$X$30,'한국 YT'!$I$8:$I$30,"",0)="","",_xlfn.XLOOKUP(A191,'한국 YT'!$X$8:$X$30,'한국 YT'!$I$8:$I$30,"",0))} | P191: {=IF(_xlfn.XLOOKUP(A191,'한국 YT'!$X$8:$X$30,'한국 YT'!$J$8:$J$30,"",0)="","",_xlfn.XLOOKUP(A191,'한국 YT'!$X$8:$X$30,'한국 YT'!$J$8:$J$30,"",0))} | Q191: {=IF(_xlfn.XLOOKUP(A191,'한국 YT'!$X$8:$X$30,'한국 YT'!$K$8:$K$30,"",0)="","",_xlfn.XLOOKUP(A191,'한국 YT'!$X$8:$X$30,'한국 YT'!$K$8:$K$30,"",0))} | S191: {=IF(_xlfn.XLOOKUP(A191,'한국 YT'!$X$8:$X$30,'한국 YT'!$E$8:$E$30,"",0)="","",_xlfn.XLOOKUP(A191,'한국 YT'!$X$8:$X$30,'한국 YT'!$E$8:$E$30,"",0))} | T191: =IF(OR(S191="",S191<=0,IF(E191="X",P191,Q191)=""),"",IF(E191="X",P191,Q191)/S191) | U191: {=IF(OR(K191="조회 불가",K191="계정 확인 필요",O191="",V191=""),"미측정",IF(O191<IF(E191="YouTube",1,3),"저빈도",IF(V191>=_xlfn.XLOOKUP(E191,'선정 기준'!$A$5:$A$7,'선정 기준'!$B$5:$B$7),"P1",IF(V191>=_xlfn.XLOOKUP(E191,'선정 기준'!$A$5:$A$7,'선정 기준'!$C$5:$C$7),"P2",IF(V191>=_xlfn.XLOOKUP(E191,'선정 기준'!$A$5:$A$7,'선정 기준'!$D$5:$D$7),"P3","P4")))))} -> 미측정 | V191: =IF(E191="X",IF(OR(P191="",R191=""),"",P191*R191),IF(Q191="","",Q191)) | W191: =IF(E191="X",IF(R191="","",R191),IF(T191="","",T191)) | X191: {=_xlfn.XLOOKUP(E191,'선정 기준'!$A$5:$A$7,'선정 기준'!$F$5:$F$7)} -> 0.05 | Y191: {=_xlfn.XLOOKUP(E191,'선정 기준'!$A$5:$A$7,'선정 기준'!$E$5:$E$7)} -> 3 | Z191: 비활동
A193: WB-C189 | B193: WB-K018 | C193: @AlphaSchool77 | D193: KR | E193: X | F193: https://x.com/AlphaSchool77 | G193: 한국 X | H193: 46293 | I193: 46281 | K193: 일부 수집 | L193: 9/16 이후만 수집 · WL 기브어웨이 위주 → 이벤트 포함 ER; 일반 게시물과 분리 필요 | M193: 연결 확인 필요 | O193: {=IF(_xlfn.XLOOKUP(A193,'한국 X'!$X$7:$X$19,'한국 X'!$P$7:$P$19,"",0)="","",_xlfn.XLOOKUP(A193,'한국 X'!$X$7:$X$19,'한국 X'!$P$7:$P$19,"",0))} -> 17 | P193: {=IF(_xlfn.XLOOKUP(A193,'한국 X'!$X$7:$X$19,'한국 X'!$Q$7:$Q$19,"",0)="","",_xlfn.XLOOKUP(A193,'한국 X'!$X$7:$X$19,'한국 X'!$Q$7:$Q$19,"",0))} -> 910 | R193: {=IF(_xlfn.XLOOKUP(A193,'한국 X'!$X$7:$X$19,'한국 X'!$S$7:$S$19,"",0)="","",_xlfn.XLOOKUP(A193,'한국 X'!$X$7:$X$19,'한국 X'!$S$7:$S$19,"",0))} -> 0.0292 | S193: {=IF(_xlfn.XLOOKUP(A193,'한국 X'!$X$7:$X$19,'한국 X'!$G$7:$G$19,"",0)="","",_xlfn.XLOOKUP(A193,'한국 X'!$X$7:$X$19,'한국 X'!$G$7:$G$19,"",0))} -> 19000 | T193: =IF(OR(S193="",S193<=0,IF(E193="X",P193,Q193)=""),"",IF(E193="X",P193,Q193)/S193) -> 0.047894737 | U193: {=IF(OR(K193="조회 불가",K193="계정 확인 필요",O193="",V193=""),"미측정",IF(O193<IF(E193="YouTube",1,3),"저빈도",IF(V193>=_xlfn.XLOOKUP(E193,'선정 기준'!$A$5:$A$7,'선정 기준'!$B$5:$B$7),"P1",IF(V193>=_xlfn.XLOOKUP(E193,'선정 기준'!$A$5:$A$7,'선정 기준'!$C$5:$C$7),"P2",IF(V193>=_xlfn.XLOOKUP(E193,'선정 기준'!$A$5:$A$7,'선정 기준'!$D$5:$D$7),"P3","P4")))))} -> P4 | V193: =IF(E193="X",IF(OR(P193="",R193=""),"",P193*R193),IF(Q193="","",Q193)) -> 26.572 | W193: =IF(E193="X",IF(R193="","",R193),IF(T193="","",T193)) -> 0.0292 | X193: {=_xlfn.XLOOKUP(E193,'선정 기준'!$A$5:$A$7,'선정 기준'!$F$5:$F$7)} -> 0.006 | Y193: {=_xlfn.XLOOKUP(E193,'선정 기준'!$A$5:$A$7,'선정 기준'!$E$5:$E$7)} -> 10 | Z193: P4
A198: WB-C194 | C198: @log_yun | D198: KR | E198: X | F198: https://x.com/log_yun | G198: 한국 X | H198: 46293 | K198: 기간 확인 필요 | M198: 연결 확인 필요 | O198: {=IF(_xlfn.XLOOKUP(A198,'한국 X'!$X$7:$X$19,'한국 X'!$P$7:$P$19,"",0)="","",_xlfn.XLOOKUP(A198,'한국 X'!$X$7:$X$19,'한국 X'!$P$7:$P$19,"",0))} -> 8 | P198: {=IF(_xlfn.XLOOKUP(A198,'한국 X'!$X$7:$X$19,'한국 X'!$Q$7:$Q$19,"",0)="","",_xlfn.XLOOKUP(A198,'한국 X'!$X$7:$X$19,'한국 X'!$Q$7:$Q$19,"",0))} -> 583 | R198: {=IF(_xlfn.XLOOKUP(A198,'한국 X'!$X$7:$X$19,'한국 X'!$S$7:$S$19,"",0)="","",_xlfn.XLOOKUP(A198,'한국 X'!$X$7:$X$19,'한국 X'!$S$7:$S$19,"",0))} -> 0.0049 | S198: {=IF(_xlfn.XLOOKUP(A198,'한국 X'!$X$7:$X$19,'한국 X'!$G$7:$G$19,"",0)="","",_xlfn.XLOOKUP(A198,'한국 X'!$X$7:$X$19,'한국 X'!$G$7:$G$19,"",0))} -> 5360 | T198: =IF(OR(S198="",S198<=0,IF(E198="X",P198,Q198)=""),"",IF(E198="X",P198,Q198)/S198) -> 0.10876866 | U198: {=IF(OR(K198="조회 불가",K198="계정 확인 필요",O198="",V198=""),"미측정",IF(O198<IF(E198="YouTube",1,3),"저빈도",IF(V198>=_xlfn.XLOOKUP(E198,'선정 기준'!$A$5:$A$7,'선정 기준'!$B$5:$B$7),"P1",IF(V198>=_xlfn.XLOOKUP(E198,'선정 기준'!$A$5:$A$7,'선정 기준'!$C$5:$C$7),"P2",IF(V198>=_xlfn.XLOOKUP(E198,'선정 기준'!$A$5:$A$7,'선정 기준'!$D$5:$D$7),"P3","P4")))))} -> P4 | V198: =IF(E198="X",IF(OR(P198="",R198=""),"",P198*R198),IF(Q198="","",Q198)) -> 2.8567 | W198: =IF(E198="X",IF(R198="","",R198),IF(T198="","",T198)) -> 0.0049 | X198: {=_xlfn.XLOOKUP(E198,'선정 기준'!$A$5:$A$7,'선정 기준'!$F$5:$F$7)} -> 0.006 | Y198: {=_xlfn.XLOOKUP(E198,'선정 기준'!$A$5:$A$7,'선정 기준'!$E$5:$E$7)} -> 10 | Z198: P4

Sheet 단가·섭외

Sheet 판매 성과
